Workbook

Sheet Calculation
A1: FREELANCER SHEET
A2: COMPANY NAME | B2: DATE ASSIGNED | C2: TASK | D2: INCHARGE | E2: DUTY | F2: QTY | G2: COST FOR ONE WORK | H2: TOTAL COST(F*G) | I2: SUBMISSION DATE | J2: INCHARGE + BONUS | K2: INCHARGE + BONUS + WORK | L2: HOBO AMOUNT
A3: Sony Tyres | B3: 45456 | C3: Short video design | D3: Anu Shigha | E3: Anu Shigha | F3: 2 | G3: =IF(OR(A3="NIL", C3="NIL", D3="NIL", E3="NIL"), 0, INDEX($B$136:$F$152, MATCH(E3, $A$136:$A$152, 0), MATCH(C3, $B$135:$F$135, 0))) -> 312.5 | H3: =G3*F3 -> 625 | I3: 45486 | J3: =IF(OR(A3="NIL", C3="NIL", D3="NIL", E3="NIL"), 0, IFERROR( (INDEX($B$136:$G$136, 1, MATCH(C3, $B$135:$I$135, 0)) - G3) * F3 + INDEX($G$138:$I$141, MATCH(D3, $A$138:$A$141, 0), MATCH(C3, $B$135:$F$135, 0)) * F3, 0) ) -> 172 | K3: =IFERROR(IFS(D3=E3,H3+J3,D3<>E3,J3),0) -> 797 | L3: =SUM(VLOOKUP(A3,$A$165:$C$178,2,False)*25%,VLOOKUP(A3,$A$165:$C$178,3,False)*25%) -> 1875
B4: 45489 | C4: Short video design | D4: Anu Shigha | E4: Anu Shigha | F4: 3 | G4: =IF(OR(A4="NIL", C4="NIL", D4="NIL", E4="NIL"), 0, INDEX($B$136:$F$152, MATCH(E4, $A$136:$A$152, 0), MATCH(C4, $B$135:$F$135, 0))) -> 312.5 | H4: =G4*F4 -> 937.5 | I4: 45447 | J4: =IF(OR(A4="NIL", C4="NIL", D4="NIL", E4="NIL"), 0, IFERROR( (INDEX($B$136:$G$136, 1, MATCH(C4, $B$135:$I$135, 0)) - G4) * F4 + INDEX($G$138:$I$141, MATCH(D4, $A$138:$A$141, 0), MATCH(C4, $B$135:$F$135, 0)) * F4, 0) ) -> 258 | K4: =IFERROR(IFS(D4=E4,H4+J4,D4<>E4,J4),0) -> 1195.5
B5: 45455 | C5: Poster Design | D5: Anu Shigha | E5: Ram | F5: 1 | G5: =IF(OR(A5="NIL", C5="NIL", D5="NIL", E5="NIL"), 0, INDEX($B$136:$F$152, MATCH(E5, $A$136:$A$152, 0), MATCH(C5, $B$135:$F$135, 0))) -> 100 | H5: =G5*F5 -> 100 | I5: 45455 | J5: =IF(OR(A5="NIL", C5="NIL", D5="NIL", E5="NIL"), 0, IFERROR( (INDEX($B$136:$G$136, 1, MATCH(C5, $B$135:$I$135, 0)) - G5) * F5 + INDEX($G$138:$I$141, MATCH(D5, $A$138:$A$141, 0), MATCH(C5, $B$135:$F$135, 0)) * F5, 0) ) -> 0 | K5: =IFERROR(IFS(D5=E5,H5+J5,D5<>E5,J5),0) -> 0
B6: 45448 | C6: Short video design | D6: Nebil Divay | E6: Nebil Divay | F6: 2 | G6: =IF(OR(A6="NIL", C6="NIL", D6="NIL", E6="NIL"), 0, INDEX($B$136:$F$152, MATCH(E6, $A$136:$A$152, 0), MATCH(C6, $B$135:$F$135, 0))) -> 312.5 | H6: =G6*F6 -> 625 | I6: 45455 | J6: {=IF(OR(A6="NIL", C6="NIL", D6="NIL", E6="NIL"), 0, IFERROR( (INDEX($B$136:$F$136, 1, MATCH(C6, $B$135:$F$135, 0)) - G6) * F6 + INDEX($G$138:$I$141, MATCH(D6, $A$138:$A$141, 0), MATCH(C6, $B$135:$F$135, 0)) * F6, 0) )} -> 172 | K6: =IFERROR(IFS(D6=E6,H6+J6,D6<>E6,J6),0) -> 797
B7: 45458 | C7: Short video design | D7: Vishnu Kalpamangalam | E7: Dyan | F7: 10 | G7: =IF(OR(A7="NIL", C7="NIL", D7="NIL", E7="NIL"), 0, INDEX($B$136:$F$152, MATCH(E7, $A$136:$A$152, 0), MATCH(C7, $B$135:$F$135, 0))) -> 200 | H7: =G7*F7 -> 2000 | I7: 45473 | J7: =IFERROR(IFS(A7="NIL",0,C7="NIL",0,D7="NIL",0,E7="NIL",0,AND(D7=$A$138,C7=$F$135),SUM(($F$136-G7)*F7,$G$138*F7), AND(D7=$A$138,C7=$B$135),SUM(($B$136-G7)*F7,$H$138*F7),AND(D7=$A$138,C7=$C$135),SUM(($C$136-G7)*F7,$I$138*F7),AND(D7=$A$139,C7=$F$135),SUM(($F$136-G7)*F7,$G$139*F7), AND(D7=$A$139,C7=$B$135),SUM(($B$136-G7)*F7,$H$139*F7),AND(D7=$A$139,C7=$C$135),SUM(($C$136-G7)*F7,$I$139*F7),AND(D7=$A$140,C7=$F$135),SUM(($F$136-G7)*F7,$G$140*F7), AND(D7=$A$140,C7=$B$135),SUM(($B$136-G7)*F7,$H$140*F7),AND(D7=$A$140,C7=$C$135),SUM(($C$136-G7)*F7,$I$140*F7),AND(D7=$A$141,C7=$F$135),SUM(($F$136-G7)*F7,$G$141*F7), AND(D7=$A$141,C7=$B$135),SUM(($B$136-G7)*F7,$H$141*F7),AND(D7=$A$141,C7=$C$135),SUM(($C$136-G7)*F7,$I$141*F7)),"") -> 2687.5 | K7: =IFERROR(IFS(D7=E7,H7+J7,D7<>E7,J7),0) -> 2687.5
B8: 45457 | C8: Short video design | D8: Anu Shigha | E8: Anuba | F8: 2 | G8: =IF(OR(A8="NIL", C8="NIL", D8="NIL", E8="NIL"), 0, INDEX($B$136:$F$152, MATCH(E8, $A$136:$A$152, 0), MATCH(C8, $B$135:$F$135, 0))) -> 35 | H8: =G8*F8 -> 70 | I8: 45447 | J8: =IFERROR(IFS(A8="NIL",0,C8="NIL",0,D8="NIL",0,E8="NIL",0,AND(D8=$A$138,C8=$F$135),SUM(($F$136-G8)*F8,$G$138*F8), AND(D8=$A$138,C8=$B$135),SUM(($B$136-G8)*F8,$H$138*F8),AND(D8=$A$138,C8=$C$135),SUM(($C$136-G8)*F8,$I$138*F8),AND(D8=$A$139,C8=$F$135),SUM(($F$136-G8)*F8,$G$139*F8), AND(D8=$A$139,C8=$B$135),SUM(($B$136-G8)*F8,$H$139*F8),AND(D8=$A$139,C8=$C$135),SUM(($C$136-G8)*F8,$I$139*F8),AND(D8=$A$140,C8=$F$135),SUM(($F$136-G8)*F8,$G$140*F8), AND(D8=$A$140,C8=$B$135),SUM(($B$136-G8)*F8,$H$140*F8),AND(D8=$A$140,C8=$C$135),SUM(($C$136-G8)*F8,$I$140*F8),AND(D8=$A$141,C8=$F$135),SUM(($F$136-G8)*F8,$G$141*F8), AND(D8=$A$141,C8=$B$135),SUM(($B$136-G8)*F8,$H$141*F8),AND(D8=$A$141,C8=$C$135),SUM(($C$136-G8)*F8,$I$141*F8)),"") -> 867.5 | K8: =IFERROR(IFS(D8=E8,H8+J8,D8<>E8,J8),0) -> 867.5
B9: 45471 | C9: Short video design | D9: Vishnu Kalpamangalam | E9: Dyan | F9: 2 | G9: =IF(OR(A9="NIL", C9="NIL", D9="NIL", E9="NIL"), 0, INDEX($B$136:$F$152, MATCH(E9, $A$136:$A$152, 0), MATCH(C9, $B$135:$F$135, 0))) -> 200 | H9: =G9*F9 -> 400 | I9: 45447 | J9: =IFERROR(IFS(A9="NIL",0,C9="NIL",0,D9="NIL",0,E9="NIL",0,AND(D9=$A$138,C9=$F$135),SUM(($F$136-G9)*F9,$G$138*F9), AND(D9=$A$138,C9=$B$135),SUM(($B$136-G9)*F9,$H$138*F9),AND(D9=$A$138,C9=$C$135),SUM(($C$136-G9)*F9,$I$138*F9),AND(D9=$A$139,C9=$F$135),SUM(($F$136-G9)*F9,$G$139*F9), AND(D9=$A$139,C9=$B$135),SUM(($B$136-G9)*F9,$H$139*F9),AND(D9=$A$139,C9=$C$135),SUM(($C$136-G9)*F9,$I$139*F9),AND(D9=$A$140,C9=$F$135),SUM(($F$136-G9)*F9,$G$140*F9), AND(D9=$A$140,C9=$B$135),SUM(($B$136-G9)*F9,$H$140*F9),AND(D9=$A$140,C9=$C$135),SUM(($C$136-G9)*F9,$I$140*F9),AND(D9=$A$141,C9=$F$135),SUM(($F$136-G9)*F9,$G$141*F9), AND(D9=$A$141,C9=$B$135),SUM(($B$136-G9)*F9,$H$141*F9),AND(D9=$A$141,C9=$C$135),SUM(($C$136-G9)*F9,$I$141*F9)),"") -> 537.5 | K9: =IFERROR(IFS(D9=E9,H9+J9,D9<>E9,J9),0) -> 537.5
B10: 45464 | C10: Short video design | D10: Siddharth Mohan | E10: Siddharth Mohan | F10: 2 | G10: =IF(OR(A10="NIL", C10="NIL", D10="NIL", E10="NIL"), 0, INDEX($B$136:$F$152, MATCH(E10, $A$136:$A$152, 0), MATCH(C10, $B$135:$F$135, 0))) -> 312.5 | H10: =G10*F10 -> 625 | J10: =IFERROR(IFS(A10="NIL",0,C10="NIL",0,D10="NIL",0,E10="NIL",0,AND(D10=$A$138,C10=$F$135),SUM(($F$136-G10)*F10,$G$138*F10), AND(D10=$A$138,C10=$B$135),SUM(($B$136-G10)*F10,$H$138*F10),AND(D10=$A$138,C10=$C$135),SUM(($C$136-G10)*F10,$I$138*F10),AND(D10=$A$139,C10=$F$135),SUM(($F$136-G10)*F10,$G$139*F10), AND(D10=$A$139,C10=$B$135),SUM(($B$136-G10)*F10,$H$139*F10),AND(D10=$A$139,C10=$C$135),SUM(($C$136-G10)*F10,$I$139*F10),AND(D10=$A$140,C10=$F$135),SUM(($F$136-G10)*F10,$G$140*F10), AND(D10=$A$140,C10=$B$135),SUM(($B$136-G10)*F10,$H$140*F10),AND(D10=$A$140,C10=$C$135),SUM(($C$136-G10)*F10,$I$140*F10),AND(D10=$A$141,C10=$F$135),SUM(($F$136-G10)*F10,$G$141*F10), AND(D10=$A$141,C10=$B$135),SUM(($B$136-G10)*F10,$H$141*F10),AND(D10=$A$141,C10=$C$135),SUM(($C$136-G10)*F10,$I$141*F10)),"") -> 312.5 | K10: =IFERROR(IFS(D10=E10,H10+J10,D10<>E10,J10),0) -> 937.5
B11: 45498 | C11: Poster Design | D11: Nebil Divay | E11: Sachu | F11: 4 | G11: =IF(OR(A11="NIL", C11="NIL", D11="NIL", E11="NIL"), 0, INDEX($B$136:$F$152, MATCH(E11, $A$136:$A$152, 0), MATCH(C11, $B$135:$F$135, 0))) -> 44 | H11: =G11*F11 -> 176 | I11: 45974 | J11: =IFERROR(IFS(A11="NIL",0,C11="NIL",0,D11="NIL",0,E11="NIL",0,AND(D11=$A$138,C11=$F$135),SUM(($F$136-G11)*F11,$G$138*F11), AND(D11=$A$138,C11=$B$135),SUM(($B$136-G11)*F11,$H$138*F11),AND(D11=$A$138,C11=$C$135),SUM(($C$136-G11)*F11,$I$138*F11),AND(D11=$A$139,C11=$F$135),SUM(($F$136-G11)*F11,$G$139*F11), AND(D11=$A$139,C11=$B$135),SUM(($B$136-G11)*F11,$H$139*F11),AND(D11=$A$139,C11=$C$135),SUM(($C$136-G11)*F11,$I$139*F11),AND(D11=$A$140,C11=$F$135),SUM(($F$136-G11)*F11,$G$140*F11), AND(D11=$A$140,C11=$B$135),SUM(($B$136-G11)*F11,$H$140*F11),AND(D11=$A$140,C11=$C$135),SUM(($C$136-G11)*F11,$I$140*F11),AND(D11=$A$141,C11=$F$135),SUM(($F$136-G11)*F11,$G$141*F11), AND(D11=$A$141,C11=$B$135),SUM(($B$136-G11)*F11,$H$141*F11),AND(D11=$A$141,C11=$C$135),SUM(($C$136-G11)*F11,$I$141*F11)),"") -> 728 | K11: =IFERROR(IFS(D11=E11,H11+J11,D11<>E11,J11),0) -> 728
B12: 45463 | C12: Poster Design | D12: Anu Shigha | E12: Achu | F12: 5 | G12: =IF(OR(A12="NIL", C12="NIL", D12="NIL", E12="NIL"), 0, INDEX($B$136:$F$152, MATCH(E12, $A$136:$A$152, 0), MATCH(C12, $B$135:$F$135, 0))) -> 44 | H12: =G12*F12 -> 220 | J12: =IFERROR(IFS(A12="NIL",0,C12="NIL",0,D12="NIL",0,E12="NIL",0,AND(D12=$A$138,C12=$F$135),SUM(($F$136-G12)*F12,$G$138*F12), AND(D12=$A$138,C12=$B$135),SUM(($B$136-G12)*F12,$H$138*F12),AND(D12=$A$138,C12=$C$135),SUM(($C$136-G12)*F12,$I$138*F12),AND(D12=$A$139,C12=$F$135),SUM(($F$136-G12)*F12,$G$139*F12), AND(D12=$A$139,C12=$B$135),SUM(($B$136-G12)*F12,$H$139*F12),AND(D12=$A$139,C12=$C$135),SUM(($C$136-G12)*F12,$I$139*F12),AND(D12=$A$140,C12=$F$135),SUM(($F$136-G12)*F12,$G$140*F12), AND(D12=$A$140,C12=$B$135),SUM(($B$136-G12)*F12,$H$140*F12),AND(D12=$A$140,C12=$C$135),SUM(($C$136-G12)*F12,$I$140*F12),AND(D12=$A$141,C12=$F$135),SUM(($F$136-G12)*F12,$G$141*F12), AND(D12=$A$141,C12=$B$135),SUM(($B$136-G12)*F12,$H$141*F12),AND(D12=$A$141,C12=$C$135),SUM(($C$136-G12)*F12,$I$141*F12)),"") -> 910 | K12: =IFERROR(IFS(D12=E12,H12+J12,D12<>E12,J12),0) -> 910
B13: 45470 | C13: Content for Poster | D13: Anu Shigha | E13: Rehan | F13: 2 | G13: =IF(OR(A13="NIL", C13="NIL", D13="NIL", E13="NIL"), 0, INDEX($B$136:$F$152, MATCH(E13, $A$136:$A$152, 0), MATCH(C13, $B$135:$F$135, 0))) -> 22 | H13: =G13*F13 -> 44 | I13: 45987 | J13: =IFERROR(IFS(A13="NIL",0,C13="NIL",0,D13="NIL",0,E13="NIL",0,AND(D13=$A$138,C13=$F$135),SUM(($F$136-G13)*F13,$G$138*F13), AND(D13=$A$138,C13=$B$135),SUM(($B$136-G13)*F13,$H$138*F13),AND(D13=$A$138,C13=$C$135),SUM(($C$136-G13)*F13,$I$138*F13),AND(D13=$A$139,C13=$F$135),SUM(($F$136-G13)*F13,$G$139*F13), AND(D13=$A$139,C13=$B$135),SUM(($B$136-G13)*F13,$H$139*F13),AND(D13=$A$139,C13=$C$135),SUM(($C$136-G13)*F13,$I$139*F13),AND(D13=$A$140,C13=$F$135),SUM(($F$136-G13)*F13,$G$140*F13), AND(D13=$A$140,C13=$B$135),SUM(($B$136-G13)*F13,$H$140*F13),AND(D13=$A$140,C13=$C$135),SUM(($C$136-G13)*F13,$I$140*F13),AND(D13=$A$141,C13=$F$135),SUM(($F$136-G13)*F13,$G$141*F13), AND(D13=$A$141,C13=$B$135),SUM(($B$136-G13)*F13,$H$141*F13),AND(D13=$A$141,C13=$C$135),SUM(($C$136-G13)*F13,$I$141*F13)),"") | K13: =IFERROR(IFS(D13=E13,H13+J13,D13<>E13,J13),0)
B14: 45532 | C14: Content for Poster | D14: Nebil Divay | E14: Sreeju | F14: 1 | G14: =IF(OR(A14="NIL", C14="NIL", D14="NIL", E14="NIL"), 0, INDEX($B$136:$F$152, MATCH(E14, $A$136:$A$152, 0), MATCH(C14, $B$135:$F$135, 0))) -> 44 | H14: =G14*F14 -> 44 | I14: 45979 | J14: =IFERROR(IFS(A14="NIL",0,C14="NIL",0,D14="NIL",0,E14="NIL",0,AND(D14=$A$138,C14=$F$135),SUM(($F$136-G14)*F14,$G$138*F14), AND(D14=$A$138,C14=$B$135),SUM(($B$136-G14)*F14,$H$138*F14),AND(D14=$A$138,C14=$C$135),SUM(($C$136-G14)*F14,$I$138*F14),AND(D14=$A$139,C14=$F$135),SUM(($F$136-G14)*F14,$G$139*F14), AND(D14=$A$139,C14=$B$135),SUM(($B$136-G14)*F14,$H$139*F14),AND(D14=$A$139,C14=$C$135),SUM(($C$136-G14)*F14,$I$139*F14),AND(D14=$A$140,C14=$F$135),SUM(($F$136-G14)*F14,$G$140*F14), AND(D14=$A$140,C14=$B$135),SUM(($B$136-G14)*F14,$H$140*F14),AND(D14=$A$140,C14=$C$135),SUM(($C$136-G14)*F14,$I$140*F14),AND(D14=$A$141,C14=$F$135),SUM(($F$136-G14)*F14,$G$141*F14), AND(D14=$A$141,C14=$B$135),SUM(($B$136-G14)*F14,$H$141*F14),AND(D14=$A$141,C14=$C$135),SUM(($C$136-G14)*F14,$I$141*F14)),"") | K14: =IFERROR(IFS(D14=E14,H14+J14,D14<>E14,J14),0)
B15: 45525 | C15: Poster Design | D15: NIL | E15: NIL | G15: =IF(OR(A15="NIL", C15="NIL", D15="NIL", E15="NIL"), 0, INDEX($B$136:$F$152, MATCH(E15, $A$136:$A$152, 0), MATCH(C15, $B$135:$F$135, 0))) -> 0 | H15: =G15*F15 -> 0 | J15: =IFERROR(IFS(A15="NIL",0,C15="NIL",0,D15="NIL",0,E15="NIL",0,AND(D15=$A$138,C15=$F$135),SUM(($F$136-G15)*F15,$G$138*F15), AND(D15=$A$138,C15=$B$135),SUM(($B$136-G15)*F15,$H$138*F15),AND(D15=$A$138,C15=$C$135),SUM(($C$136-G15)*F15,$I$138*F15),AND(D15=$A$139,C15=$F$135),SUM(($F$136-G15)*F15,$G$139*F15), AND(D15=$A$139,C15=$B$135),SUM(($B$136-G15)*F15,$H$139*F15),AND(D15=$A$139,C15=$C$135),SUM(($C$136-G15)*F15,$I$139*F15),AND(D15=$A$140,C15=$F$135),SUM(($F$136-G15)*F15,$G$140*F15), AND(D15=$A$140,C15=$B$135),SUM(($B$136-G15)*F15,$H$140*F15),AND(D15=$A$140,C15=$C$135),SUM(($C$136-G15)*F15,$I$140*F15),AND(D15=$A$141,C15=$F$135),SUM(($F$136-G15)*F15,$G$141*F15), AND(D15=$A$141,C15=$B$135),SUM(($B$136-G15)*F15,$H$141*F15),AND(D15=$A$141,C15=$C$135),SUM(($C$136-G15)*F15,$I$141*F15)),"") -> 0 | K15: =IFERROR(IFS(D15=E15,H15+J15,D15<>E15,J15),0) -> 0
A16: Alfah Cements | B16: 45471 | C16: Content for Poster | D16: Hobo | E16: Ram | F16: 2 | G16: =IF(OR(A16="NIL", C16="NIL", D16="NIL", E16="NIL"), 0, INDEX($B$136:$F$152, MATCH(E16, $A$136:$A$152, 0), MATCH(C16, $B$135:$F$135, 0))) -> 50 | H16: =G16*F16 -> 100 | I16: 45986 | J16: =IFERROR(IFS(A16="NIL",0,C16="NIL",0,D16="NIL",0,E16="NIL",0,AND(D16=$A$138,C16=$F$135),SUM(($F$136-G16)*F16,$G$138*F16), AND(D16=$A$138,C16=$B$135),SUM(($B$136-G16)*F16,$H$138*F16),AND(D16=$A$138,C16=$C$135),SUM(($C$136-G16)*F16,$I$138*F16),AND(D16=$A$139,C16=$F$135),SUM(($F$136-G16)*F16,$G$139*F16), AND(D16=$A$139,C16=$B$135),SUM(($B$136-G16)*F16,$H$139*F16),AND(D16=$A$139,C16=$C$135),SUM(($C$136-G16)*F16,$I$139*F16),AND(D16=$A$140,C16=$F$135),SUM(($F$136-G16)*F16,$G$140*F16), AND(D16=$A$140,C16=$B$135),SUM(($B$136-G16)*F16,$H$140*F16),AND(D16=$A$140,C16=$C$135),SUM(($C$136-G16)*F16,$I$140*F16),AND(D16=$A$141,C16=$F$135),SUM(($F$136-G16)*F16,$G$141*F16), AND(D16=$A$141,C16=$B$135),SUM(($B$136-G16)*F16,$H$141*F16),AND(D16=$A$141,C16=$C$135),SUM(($C$136-G16)*F16,$I$141*F16)),"") | K16: =IFERROR(IFS(D16=E16,H16+J16,D16<>E16,J16),0) | L16: =SUM(VLOOKUP(A16,$A$165:$C$178,2,False)*25%,VLOOKUP(A16,$A$165:$C$178,3,False)*25%) -> 1875
B17: 45455 | C17: NIL | D17: NIL | E17: NIL | G17: =IF(OR(A17="NIL", C17="NIL", D17="NIL", E17="NIL"), 0, INDEX($B$136:$F$152, MATCH(E17, $A$136:$A$152, 0), MATCH(C17, $B$135:$F$135, 0))) -> 0 | H17: =G17*F17 -> 0 | J17: =IFERROR(IFS(A17="NIL",0,C17="NIL",0,D17="NIL",0,E17="NIL",0,AND(D17=$A$138,C17=$F$135),SUM(($F$136-G17)*F17,$G$138*F17), AND(D17=$A$138,C17=$B$135),SUM(($B$136-G17)*F17,$H$138*F17),AND(D17=$A$138,C17=$C$135),SUM(($C$136-G17)*F17,$I$138*F17),AND(D17=$A$139,C17=$F$135),SUM(($F$136-G17)*F17,$G$139*F17), AND(D17=$A$139,C17=$B$135),SUM(($B$136-G17)*F17,$H$139*F17),AND(D17=$A$139,C17=$C$135),SUM(($C$136-G17)*F17,$I$139*F17),AND(D17=$A$140,C17=$F$135),SUM(($F$136-G17)*F17,$G$140*F17), AND(D17=$A$140,C17=$B$135),SUM(($B$136-G17)*F17,$H$140*F17),AND(D17=$A$140,C17=$C$135),SUM(($C$136-G17)*F17,$I$140*F17),AND(D17=$A$141,C17=$F$135),SUM(($F$136-G17)*F17,$G$141*F17), AND(D17=$A$141,C17=$B$135),SUM(($B$136-G17)*F17,$H$141*F17),AND(D17=$A$141,C17=$C$135),SUM(($C$136-G17)*F17,$I$141*F17)),"") -> 0 | K17: =IFERROR(IFS(D17=E17,H17+J17,D17<>E17,J17),0) -> 0
C18: NIL | D18: NIL | E18: NIL | G18: =IF(OR(A18="NIL", C18="NIL", D18="NIL", E18="NIL"), 0, INDEX($B$136:$F$152, MATCH(E18, $A$136:$A$152, 0), MATCH(C18, $B$135:$F$135, 0))) -> 0 | H18: =G18*F18 -> 0 | J18: =IFERROR(IFS(A18="NIL",0,C18="NIL",0,D18="NIL",0,E18="NIL",0,AND(D18=$A$138,C18=$F$135),SUM(($F$136-G18)*F18,$G$138*F18), AND(D18=$A$138,C18=$B$135),SUM(($B$136-G18)*F18,$H$138*F18),AND(D18=$A$138,C18=$C$135),SUM(($C$136-G18)*F18,$I$138*F18),AND(D18=$A$139,C18=$F$135),SUM(($F$136-G18)*F18,$G$139*F18), AND(D18=$A$139,C18=$B$135),SUM(($B$136-G18)*F18,$H$139*F18),AND(D18=$A$139,C18=$C$135),SUM(($C$136-G18)*F18,$I$139*F18),AND(D18=$A$140,C18=$F$135),SUM(($F$136-G18)*F18,$G$140*F18), AND(D18=$A$140,C18=$B$135),SUM(($B$136-G18)*F18,$H$140*F18),AND(D18=$A$140,C18=$C$135),SUM(($C$136-G18)*F18,$I$140*F18),AND(D18=$A$141,C18=$F$135),SUM(($F$136-G18)*F18,$G$141*F18), AND(D18=$A$141,C18=$B$135),SUM(($B$136-G18)*F18,$H$141*F18),AND(D18=$A$141,C18=$C$135),SUM(($C$136-G18)*F18,$I$141*F18)),"") -> 0 | K18: =IFERROR(IFS(D18=E18,H18+J18,D18<>E18,J18),0) -> 0
C19: NIL | D19: NIL | E19: NIL | G19: =IF(OR(A19="NIL", C19="NIL", D19="NIL", E19="NIL"), 0, INDEX($B$136:$F$152, MATCH(E19, $A$136:$A$152, 0), MATCH(C19, $B$135:$F$135, 0))) -> 0 | H19: =G19*F19 -> 0 | J19: =IFERROR(IFS(A19="NIL",0,C19="NIL",0,D19="NIL",0,E19="NIL",0,AND(D19=$A$138,C19=$F$135),SUM(($F$136-G19)*F19,$G$138*F19), AND(D19=$A$138,C19=$B$135),SUM(($B$136-G19)*F19,$H$138*F19),AND(D19=$A$138,C19=$C$135),SUM(($C$136-G19)*F19,$I$138*F19),AND(D19=$A$139,C19=$F$135),SUM(($F$136-G19)*F19,$G$139*F19), AND(D19=$A$139,C19=$B$135),SUM(($B$136-G19)*F19,$H$139*F19),AND(D19=$A$139,C19=$C$135),SUM(($C$136-G19)*F19,$I$139*F19),AND(D19=$A$140,C19=$F$135),SUM(($F$136-G19)*F19,$G$140*F19), AND(D19=$A$140,C19=$B$135),SUM(($B$136-G19)*F19,$H$140*F19),AND(D19=$A$140,C19=$C$135),SUM(($C$136-G19)*F19,$I$140*F19),AND(D19=$A$141,C19=$F$135),SUM(($F$136-G19)*F19,$G$141*F19), AND(D19=$A$141,C19=$B$135),SUM(($B$136-G19)*F19,$H$141*F19),AND(D19=$A$141,C19=$C$135),SUM(($C$136-G19)*F19,$I$141*F19)),"") -> 0 | K19: =IFERROR(IFS(D19=E19,H19+J19,D19<>E19,J19),0) -> 0
C20: NIL | D20: NIL | E20: NIL | G20: =IF(OR(A20="NIL", C20="NIL", D20="NIL", E20="NIL"), 0, INDEX($B$136:$F$152, MATCH(E20, $A$136:$A$152, 0), MATCH(C20, $B$135:$F$135, 0))) -> 0 | H20: =G20*F20 -> 0 | J20: =IFERROR(IFS(A20="NIL",0,C20="NIL",0,D20="NIL",0,E20="NIL",0,AND(D20=$A$138,C20=$F$135),SUM(($F$136-G20)*F20,$G$138*F20), AND(D20=$A$138,C20=$B$135),SUM(($B$136-G20)*F20,$H$138*F20),AND(D20=$A$138,C20=$C$135),SUM(($C$136-G20)*F20,$I$138*F20),AND(D20=$A$139,C20=$F$135),SUM(($F$136-G20)*F20,$G$139*F20), AND(D20=$A$139,C20=$B$135),SUM(($B$136-G20)*F20,$H$139*F20),AND(D20=$A$139,C20=$C$135),SUM(($C$136-G20)*F20,$I$139*F20),AND(D20=$A$140,C20=$F$135),SUM(($F$136-G20)*F20,$G$140*F20), AND(D20=$A$140,C20=$B$135),SUM(($B$136-G20)*F20,$H$140*F20),AND(D20=$A$140,C20=$C$135),SUM(($C$136-G20)*F20,$I$140*F20),AND(D20=$A$141,C20=$F$135),SUM(($F$136-G20)*F20,$G$141*F20), AND(D20=$A$141,C20=$B$135),SUM(($B$136-G20)*F20,$H$141*F20),AND(D20=$A$141,C20=$C$135),SUM(($C$136-G20)*F20,$I$141*F20)),"") -> 0 | K20: =IFERROR(IFS(D20=E20,H20+J20,D20<>E20,J20),0) -> 0
C21: NIL | D21: NIL | E21: NIL | F21: 2 | G21: =IF(OR(A21="NIL", C21="NIL", D21="NIL", E21="NIL"), 0, INDEX($B$136:$F$152, MATCH(E21, $A$136:$A$152, 0), MATCH(C21, $B$135:$F$135, 0))) -> 0 | H21: =G21*F21 -> 0 | J21: =IFERROR(IFS(A21="NIL",0,C21="NIL",0,D21="NIL",0,E21="NIL",0,AND(D21=$A$138,C21=$F$135),SUM(($F$136-G21)*F21,$G$138*F21), AND(D21=$A$138,C21=$B$135),SUM(($B$136-G21)*F21,$H$138*F21),AND(D21=$A$138,C21=$C$135),SUM(($C$136-G21)*F21,$I$138*F21),AND(D21=$A$139,C21=$F$135),SUM(($F$136-G21)*F21,$G$139*F21), AND(D21=$A$139,C21=$B$135),SUM(($B$136-G21)*F21,$H$139*F21),AND(D21=$A$139,C21=$C$135),SUM(($C$136-G21)*F21,$I$139*F21),AND(D21=$A$140,C21=$F$135),SUM(($F$136-G21)*F21,$G$140*F21), AND(D21=$A$140,C21=$B$135),SUM(($B$136-G21)*F21,$H$140*F21),AND(D21=$A$140,C21=$C$135),SUM(($C$136-G21)*F21,$I$140*F21),AND(D21=$A$141,C21=$F$135),SUM(($F$136-G21)*F21,$G$141*F21), AND(D21=$A$141,C21=$B$135),SUM(($B$136-G21)*F21,$H$141*F21),AND(D21=$A$141,C21=$C$135),SUM(($C$136-G21)*F21,$I$141*F21)),"") -> 0 | K21: =IFERROR(IFS(D21=E21,H21+J21,D21<>E21,J21),0) -> 0
C22: NIL | D22: NIL | E22: NIL | G22: =IF(OR(A22="NIL", C22="NIL", D22="NIL", E22="NIL"), 0, INDEX($B$136:$F$152, MATCH(E22, $A$136:$A$152, 0), MATCH(C22, $B$135:$F$135, 0))) -> 0 | H22: =G22*F22 -> 0 | J22: =IFERROR(IFS(A22="NIL",0,C22="NIL",0,D22="NIL",0,E22="NIL",0,AND(D22=$A$138,C22=$F$135),SUM(($F$136-G22)*F22,$G$138*F22), AND(D22=$A$138,C22=$B$135),SUM(($B$136-G22)*F22,$H$138*F22),AND(D22=$A$138,C22=$C$135),SUM(($C$136-G22)*F22,$I$138*F22),AND(D22=$A$139,C22=$F$135),SUM(($F$136-G22)*F22,$G$139*F22), AND(D22=$A$139,C22=$B$135),SUM(($B$136-G22)*F22,$H$139*F22),AND(D22=$A$139,C22=$C$135),SUM(($C$136-G22)*F22,$I$139*F22),AND(D22=$A$140,C22=$F$135),SUM(($F$136-G22)*F22,$G$140*F22), AND(D22=$A$140,C22=$B$135),SUM(($B$136-G22)*F22,$H$140*F22),AND(D22=$A$140,C22=$C$135),SUM(($C$136-G22)*F22,$I$140*F22),AND(D22=$A$141,C22=$F$135),SUM(($F$136-G22)*F22,$G$141*F22), AND(D22=$A$141,C22=$B$135),SUM(($B$136-G22)*F22,$H$141*F22),AND(D22=$A$141,C22=$C$135),SUM(($C$136-G22)*F22,$I$141*F22)),"") -> 0 | K22: =IFERROR(IFS(D22=E22,H22+J22,D22<>E22,J22),0) -> 0
C23: NIL | D23: NIL | E23: NIL | G23: =IF(OR(A23="NIL", C23="NIL", D23="NIL", E23="NIL"), 0, INDEX($B$136:$F$152, MATCH(E23, $A$136:$A$152, 0), MATCH(C23, $B$135:$F$135, 0))) -> 0 | H23: =G23*F23 -> 0 | J23: =IFERROR(IFS(A23="NIL",0,C23="NIL",0,D23="NIL",0,E23="NIL",0,AND(D23=$A$138,C23=$F$135),SUM(($F$136-G23)*F23,$G$138*F23), AND(D23=$A$138,C23=$B$135),SUM(($B$136-G23)*F23,$H$138*F23),AND(D23=$A$138,C23=$C$135),SUM(($C$136-G23)*F23,$I$138*F23),AND(D23=$A$139,C23=$F$135),SUM(($F$136-G23)*F23,$G$139*F23), AND(D23=$A$139,C23=$B$135),SUM(($B$136-G23)*F23,$H$139*F23),AND(D23=$A$139,C23=$C$135),SUM(($C$136-G23)*F23,$I$139*F23),AND(D23=$A$140,C23=$F$135),SUM(($F$136-G23)*F23,$G$140*F23), AND(D23=$A$140,C23=$B$135),SUM(($B$136-G23)*F23,$H$140*F23),AND(D23=$A$140,C23=$C$135),SUM(($C$136-G23)*F23,$I$140*F23),AND(D23=$A$141,C23=$F$135),SUM(($F$136-G23)*F23,$G$141*F23), AND(D23=$A$141,C23=$B$135),SUM(($B$136-G23)*F23,$H$141*F23),AND(D23=$A$141,C23=$C$135),SUM(($C$136-G23)*F23,$I$141*F23)),"") -> 0 | K23: =IFERROR(IFS(D23=E23,H23+J23,D23<>E23,J23),0) -> 0
C24: NIL | D24: NIL | E24: NIL | G24: =IF(OR(A24="NIL", C24="NIL", D24="NIL", E24="NIL"), 0, INDEX($B$136:$F$152, MATCH(E24, $A$136:$A$152, 0), MATCH(C24, $B$135:$F$135, 0))) -> 0 | H24: =G24*F24 -> 0 | J24: =IFERROR(IFS(A24="NIL",0,C24="NIL",0,D24="NIL",0,E24="NIL",0,AND(D24=$A$138,C24=$F$135),SUM(($F$136-G24)*F24,$G$138*F24), AND(D24=$A$138,C24=$B$135),SUM(($B$136-G24)*F24,$H$138*F24),AND(D24=$A$138,C24=$C$135),SUM(($C$136-G24)*F24,$I$138*F24),AND(D24=$A$139,C24=$F$135),SUM(($F$136-G24)*F24,$G$139*F24), AND(D24=$A$139,C24=$B$135),SUM(($B$136-G24)*F24,$H$139*F24),AND(D24=$A$139,C24=$C$135),SUM(($C$136-G24)*F24,$I$139*F24),AND(D24=$A$140,C24=$F$135),SUM(($F$136-G24)*F24,$G$140*F24), AND(D24=$A$140,C24=$B$135),SUM(($B$136-G24)*F24,$H$140*F24),AND(D24=$A$140,C24=$C$135),SUM(($C$136-G24)*F24,$I$140*F24),AND(D24=$A$141,C24=$F$135),SUM(($F$136-G24)*F24,$G$141*F24), AND(D24=$A$141,C24=$B$135),SUM(($B$136-G24)*F24,$H$141*F24),AND(D24=$A$141,C24=$C$135),SUM(($C$136-G24)*F24,$I$141*F24)),"") -> 0 | K24: =IFERROR(IFS(D24=E24,H24+J24,D24<>E24,J24),0) -> 0
C25: NIL | D25: NIL | E25: NIL | G25: =IF(OR(A25="NIL", C25="NIL", D25="NIL", E25="NIL"), 0, INDEX($B$136:$F$152, MATCH(E25, $A$136:$A$152, 0), MATCH(C25, $B$135:$F$135, 0))) -> 0 | H25: =G25*F25 -> 0 | J25: =IFERROR(IFS(A25="NIL",0,C25="NIL",0,D25="NIL",0,E25="NIL",0,AND(D25=$A$138,C25=$F$135),SUM(($F$136-G25)*F25,$G$138*F25), AND(D25=$A$138,C25=$B$135),SUM(($B$136-G25)*F25,$H$138*F25),AND(D25=$A$138,C25=$C$135),SUM(($C$136-G25)*F25,$I$138*F25),AND(D25=$A$139,C25=$F$135),SUM(($F$136-G25)*F25,$G$139*F25), AND(D25=$A$139,C25=$B$135),SUM(($B$136-G25)*F25,$H$139*F25),AND(D25=$A$139,C25=$C$135),SUM(($C$136-G25)*F25,$I$139*F25),AND(D25=$A$140,C25=$F$135),SUM(($F$136-G25)*F25,$G$140*F25), AND(D25=$A$140,C25=$B$135),SUM(($B$136-G25)*F25,$H$140*F25),AND(D25=$A$140,C25=$C$135),SUM(($C$136-G25)*F25,$I$140*F25),AND(D25=$A$141,C25=$F$135),SUM(($F$136-G25)*F25,$G$141*F25), AND(D25=$A$141,C25=$B$135),SUM(($B$136-G25)*F25,$H$141*F25),AND(D25=$A$141,C25=$C$135),SUM(($C$136-G25)*F25,$I$141*F25)),"") -> 0 | K25: =IFERROR(IFS(D25=E25,H25+J25,D25<>E25,J25),0) -> 0
C26: NIL | D26: NIL | E26: NIL | G26: =IF(OR(A26="NIL", C26="NIL", D26="NIL", E26="NIL"), 0, INDEX($B$136:$F$152, MATCH(E26, $A$136:$A$152, 0), MATCH(C26, $B$135:$F$135, 0))) -> 0 | H26: =G26*F26 -> 0 | J26: =IFERROR(IFS(A26="NIL",0,C26="NIL",0,D26="NIL",0,E26="NIL",0,AND(D26=$A$138,C26=$F$135),SUM(($F$136-G26)*F26,$G$138*F26), AND(D26=$A$138,C26=$B$135),SUM(($B$136-G26)*F26,$H$138*F26),AND(D26=$A$138,C26=$C$135),SUM(($C$136-G26)*F26,$I$138*F26),AND(D26=$A$139,C26=$F$135),SUM(($F$136-G26)*F26,$G$139*F26), AND(D26=$A$139,C26=$B$135),SUM(($B$136-G26)*F26,$H$139*F26),AND(D26=$A$139,C26=$C$135),SUM(($C$136-G26)*F26,$I$139*F26),AND(D26=$A$140,C26=$F$135),SUM(($F$136-G26)*F26,$G$140*F26), AND(D26=$A$140,C26=$B$135),SUM(($B$136-G26)*F26,$H$140*F26),AND(D26=$A$140,C26=$C$135),SUM(($C$136-G26)*F26,$I$140*F26),AND(D26=$A$141,C26=$F$135),SUM(($F$136-G26)*F26,$G$141*F26), AND(D26=$A$141,C26=$B$135),SUM(($B$136-G26)*F26,$H$141*F26),AND(D26=$A$141,C26=$C$135),SUM(($C$136-G26)*F26,$I$141*F26)),"") -> 0 | K26: =IFERROR(IFS(D26=E26,H26+J26,D26<>E26,J26),0) -> 0
C27: NIL | D27: NIL | E27: NIL | G27: =IF(OR(A27="NIL", C27="NIL", D27="NIL", E27="NIL"), 0, INDEX($B$136:$F$152, MATCH(E27, $A$136:$A$152, 0), MATCH(C27, $B$135:$F$135, 0))) -> 0 | H27: =G27*F27 -> 0 | J27: =IFERROR(IFS(A27="NIL",0,C27="NIL",0,D27="NIL",0,E27="NIL",0,AND(D27=$A$138,C27=$F$135),SUM(($F$136-G27)*F27,$G$138*F27), AND(D27=$A$138,C27=$B$135),SUM(($B$136-G27)*F27,$H$138*F27),AND(D27=$A$138,C27=$C$135),SUM(($C$136-G27)*F27,$I$138*F27),AND(D27=$A$139,C27=$F$135),SUM(($F$136-G27)*F27,$G$139*F27), AND(D27=$A$139,C27=$B$135),SUM(($B$136-G27)*F27,$H$139*F27),AND(D27=$A$139,C27=$C$135),SUM(($C$136-G27)*F27,$I$139*F27),AND(D27=$A$140,C27=$F$135),SUM(($F$136-G27)*F27,$G$140*F27), AND(D27=$A$140,C27=$B$135),SUM(($B$136-G27)*F27,$H$140*F27),AND(D27=$A$140,C27=$C$135),SUM(($C$136-G27)*F27,$I$140*F27),AND(D27=$A$141,C27=$F$135),SUM(($F$136-G27)*F27,$G$141*F27), AND(D27=$A$141,C27=$B$135),SUM(($B$136-G27)*F27,$H$141*F27),AND(D27=$A$141,C27=$C$135),SUM(($C$136-G27)*F27,$I$141*F27)),"") -> 0 | K27: =IFERROR(IFS(D27=E27,H27+J27,D27<>E27,J27),0) -> 0
C28: NIL | D28: NIL | E28: NIL | G28: =IF(OR(A28="NIL", C28="NIL", D28="NIL", E28="NIL"), 0, INDEX($B$136:$F$152, MATCH(E28, $A$136:$A$152, 0), MATCH(C28, $B$135:$F$135, 0))) -> 0 | H28: =G28*F28 -> 0 | J28: =IFERROR(IFS(A28="NIL",0,C28="NIL",0,D28="NIL",0,E28="NIL",0,AND(D28=$A$138,C28=$F$135),SUM(($F$136-G28)*F28,$G$138*F28), AND(D28=$A$138,C28=$B$135),SUM(($B$136-G28)*F28,$H$138*F28),AND(D28=$A$138,C28=$C$135),SUM(($C$136-G28)*F28,$I$138*F28),AND(D28=$A$139,C28=$F$135),SUM(($F$136-G28)*F28,$G$139*F28), AND(D28=$A$139,C28=$B$135),SUM(($B$136-G28)*F28,$H$139*F28),AND(D28=$A$139,C28=$C$135),SUM(($C$136-G28)*F28,$I$139*F28),AND(D28=$A$140,C28=$F$135),SUM(($F$136-G28)*F28,$G$140*F28), AND(D28=$A$140,C28=$B$135),SUM(($B$136-G28)*F28,$H$140*F28),AND(D28=$A$140,C28=$C$135),SUM(($C$136-G28)*F28,$I$140*F28),AND(D28=$A$141,C28=$F$135),SUM(($F$136-G28)*F28,$G$141*F28), AND(D28=$A$141,C28=$B$135),SUM(($B$136-G28)*F28,$H$141*F28),AND(D28=$A$141,C28=$C$135),SUM(($C$136-G28)*F28,$I$141*F28)),"") -> 0 | K28: =IFERROR(IFS(D28=E28,H28+J28,D28<>E28,J28),0) -> 0
A29: Prince Tyres | C29: Short video design | D29: Vishnu Kalpamangalam | E29: Ram | F29: 2 | G29: =IF(OR(A29="NIL", C29="NIL", D29="NIL", E29="NIL"), 0, INDEX($B$136:$F$152, MATCH(E29, $A$136:$A$152, 0), MATCH(C29, $B$135:$F$135, 0))) -> 200 | H29: =G29*F29 -> 400 | J29: =IFERROR(IFS(A29="NIL",0,C29="NIL",0,D29="NIL",0,E29="NIL",0,AND(D29=$A$138,C29=$F$135),SUM(($F$136-G29)*F29,$G$138*F29), AND(D29=$A$138,C29=$B$135),SUM(($B$136-G29)*F29,$H$138*F29),AND(D29=$A$138,C29=$C$135),SUM(($C$136-G29)*F29,$I$138*F29),AND(D29=$A$139,C29=$F$135),SUM(($F$136-G29)*F29,$G$139*F29), AND(D29=$A$139,C29=$B$135),SUM(($B$136-G29)*F29,$H$139*F29),AND(D29=$A$139,C29=$C$135),SUM(($C$136-G29)*F29,$I$139*F29),AND(D29=$A$140,C29=$F$135),SUM(($F$136-G29)*F29,$G$140*F29), AND(D29=$A$140,C29=$B$135),SUM(($B$136-G29)*F29,$H$140*F29),AND(D29=$A$140,C29=$C$135),SUM(($C$136-G29)*F29,$I$140*F29),AND(D29=$A$141,C29=$F$135),SUM(($F$136-G29)*F29,$G$141*F29), AND(D29=$A$141,C29=$B$135),SUM(($B$136-G29)*F29,$H$141*F29),AND(D29=$A$141,C29=$C$135),SUM(($C$136-G29)*F29,$I$141*F29)),"") -> 537.5 | K29: =IFERROR(IFS(D29=E29,H29+J29,D29<>E29,J29),0) -> 537.5 | L29: =SUM(VLOOKUP(A29,$A$165:$C$178,2,False)*25%,VLOOKUP(A29,$A$165:$C$178,3,False)*25%) -> 187.5
C30: NIL | D30: NIL | E30: NIL | G30: =IF(OR(A30="NIL", C30="NIL", D30="NIL", E30="NIL"), 0, INDEX($B$136:$F$152, MATCH(E30, $A$136:$A$152, 0), MATCH(C30, $B$135:$F$135, 0))) -> 0 | H30: =G30*F30 -> 0 | J30: =IFERROR(IFS(A30="NIL",0,C30="NIL",0,D30="NIL",0,E30="NIL",0,AND(D30=$A$138,C30=$F$135),SUM(($F$136-G30)*F30,$G$138*F30), AND(D30=$A$138,C30=$B$135),SUM(($B$136-G30)*F30,$H$138*F30),AND(D30=$A$138,C30=$C$135),SUM(($C$136-G30)*F30,$I$138*F30),AND(D30=$A$139,C30=$F$135),SUM(($F$136-G30)*F30,$G$139*F30), AND(D30=$A$139,C30=$B$135),SUM(($B$136-G30)*F30,$H$139*F30),AND(D30=$A$139,C30=$C$135),SUM(($C$136-G30)*F30,$I$139*F30),AND(D30=$A$140,C30=$F$135),SUM(($F$136-G30)*F30,$G$140*F30), AND(D30=$A$140,C30=$B$135),SUM(($B$136-G30)*F30,$H$140*F30),AND(D30=$A$140,C30=$C$135),SUM(($C$136-G30)*F30,$I$140*F30),AND(D30=$A$141,C30=$F$135),SUM(($F$136-G30)*F30,$G$141*F30), AND(D30=$A$141,C30=$B$135),SUM(($B$136-G30)*F30,$H$141*F30),AND(D30=$A$141,C30=$C$135),SUM(($C$136-G30)*F30,$I$141*F30)),"") -> 0 | K30: =IFERROR(IFS(D30=E30,H30+J30,D30<>E30,J30),0) -> 0
C31: NIL | D31: NIL | E31: NIL | G31: =IF(OR(A31="NIL", C31="NIL", D31="NIL", E31="NIL"), 0, INDEX($B$136:$F$152, MATCH(E31, $A$136:$A$152, 0), MATCH(C31, $B$135:$F$135, 0))) -> 0 | H31: =G31*F31 -> 0 | J31: =IFERROR(IFS(A31="NIL",0,C31="NIL",0,D31="NIL",0,E31="NIL",0,AND(D31=$A$138,C31=$F$135),SUM(($F$136-G31)*F31,$G$138*F31), AND(D31=$A$138,C31=$B$135),SUM(($B$136-G31)*F31,$H$138*F31),AND(D31=$A$138,C31=$C$135),SUM(($C$136-G31)*F31,$I$138*F31),AND(D31=$A$139,C31=$F$135),SUM(($F$136-G31)*F31,$G$139*F31), AND(D31=$A$139,C31=$B$135),SUM(($B$136-G31)*F31,$H$139*F31),AND(D31=$A$139,C31=$C$135),SUM(($C$136-G31)*F31,$I$139*F31),AND(D31=$A$140,C31=$F$135),SUM(($F$136-G31)*F31,$G$140*F31), AND(D31=$A$140,C31=$B$135),SUM(($B$136-G31)*F31,$H$140*F31),AND(D31=$A$140,C31=$C$135),SUM(($C$136-G31)*F31,$I$140*F31),AND(D31=$A$141,C31=$F$135),SUM(($F$136-G31)*F31,$G$141*F31), AND(D31=$A$141,C31=$B$135),SUM(($B$136-G31)*F31,$H$141*F31),AND(D31=$A$141,C31=$C$135),SUM(($C$136-G31)*F31,$I$141*F31)),"") -> 0 | K31: =IFERROR(IFS(D31=E31,H31+J31,D31<>E31,J31),0) -> 0
C32: NIL | D32: NIL | E32: NIL | G32: =IF(OR(A32="NIL", C32="NIL", D32="NIL", E32="NIL"), 0, INDEX($B$136:$F$152, MATCH(E32, $A$136:$A$152, 0), MATCH(C32, $B$135:$F$135, 0))) -> 0 | H32: =G32*F32 -> 0 | J32: =IFERROR(IFS(A32="NIL",0,C32="NIL",0,D32="NIL",0,E32="NIL",0,AND(D32=$A$138,C32=$F$135),SUM(($F$136-G32)*F32,$G$138*F32), AND(D32=$A$138,C32=$B$135),SUM(($B$136-G32)*F32,$H$138*F32),AND(D32=$A$138,C32=$C$135),SUM(($C$136-G32)*F32,$I$138*F32),AND(D32=$A$139,C32=$F$135),SUM(($F$136-G32)*F32,$G$139*F32), AND(D32=$A$139,C32=$B$135),SUM(($B$136-G32)*F32,$H$139*F32),AND(D32=$A$139,C32=$C$135),SUM(($C$136-G32)*F32,$I$139*F32),AND(D32=$A$140,C32=$F$135),SUM(($F$136-G32)*F32,$G$140*F32), AND(D32=$A$140,C32=$B$135),SUM(($B$136-G32)*F32,$H$140*F32),AND(D32=$A$140,C32=$C$135),SUM(($C$136-G32)*F32,$I$140*F32),AND(D32=$A$141,C32=$F$135),SUM(($F$136-G32)*F32,$G$141*F32), AND(D32=$A$141,C32=$B$135),SUM(($B$136-G32)*F32,$H$141*F32),AND(D32=$A$141,C32=$C$135),SUM(($C$136-G32)*F32,$I$141*F32)),"") -> 0 | K32: =IFERROR(IFS(D32=E32,H32+J32,D32<>E32,J32),0) -> 0
C33: NIL | D33: NIL | E33: NIL | G33: =IF(OR(A33="NIL", C33="NIL", D33="NIL", E33="NIL"), 0, INDEX($B$136:$F$152, MATCH(E33, $A$136:$A$152, 0), MATCH(C33, $B$135:$F$135, 0))) -> 0 | H33: =G33*F33 -> 0 | J33: =IFERROR(IFS(A33="NIL",0,C33="NIL",0,D33="NIL",0,E33="NIL",0,AND(D33=$A$138,C33=$F$135),SUM(($F$136-G33)*F33,$G$138*F33), AND(D33=$A$138,C33=$B$135),SUM(($B$136-G33)*F33,$H$138*F33),AND(D33=$A$138,C33=$C$135),SUM(($C$136-G33)*F33,$I$138*F33),AND(D33=$A$139,C33=$F$135),SUM(($F$136-G33)*F33,$G$139*F33), AND(D33=$A$139,C33=$B$135),SUM(($B$136-G33)*F33,$H$139*F33),AND(D33=$A$139,C33=$C$135),SUM(($C$136-G33)*F33,$I$139*F33),AND(D33=$A$140,C33=$F$135),SUM(($F$136-G33)*F33,$G$140*F33), AND(D33=$A$140,C33=$B$135),SUM(($B$136-G33)*F33,$H$140*F33),AND(D33=$A$140,C33=$C$135),SUM(($C$136-G33)*F33,$I$140*F33),AND(D33=$A$141,C33=$F$135),SUM(($F$136-G33)*F33,$G$141*F33), AND(D33=$A$141,C33=$B$135),SUM(($B$136-G33)*F33,$H$141*F33),AND(D33=$A$141,C33=$C$135),SUM(($C$136-G33)*F33,$I$141*F33)),"") -> 0 | K33: =IFERROR(IFS(D33=E33,H33+J33,D33<>E33,J33),0) -> 0
C34: NIL | D34: NIL | E34: NIL | G34: =IF(OR(A34="NIL", C34="NIL", D34="NIL", E34="NIL"), 0, INDEX($B$136:$F$152, MATCH(E34, $A$136:$A$152, 0), MATCH(C34, $B$135:$F$135, 0))) -> 0 | H34: =G34*F34 -> 0 | J34: =IFERROR(IFS(A34="NIL",0,C34="NIL",0,D34="NIL",0,E34="NIL",0,AND(D34=$A$138,C34=$F$135),SUM(($F$136-G34)*F34,$G$138*F34), AND(D34=$A$138,C34=$B$135),SUM(($B$136-G34)*F34,$H$138*F34),AND(D34=$A$138,C34=$C$135),SUM(($C$136-G34)*F34,$I$138*F34),AND(D34=$A$139,C34=$F$135),SUM(($F$136-G34)*F34,$G$139*F34), AND(D34=$A$139,C34=$B$135),SUM(($B$136-G34)*F34,$H$139*F34),AND(D34=$A$139,C34=$C$135),SUM(($C$136-G34)*F34,$I$139*F34),AND(D34=$A$140,C34=$F$135),SUM(($F$136-G34)*F34,$G$140*F34), AND(D34=$A$140,C34=$B$135),SUM(($B$136-G34)*F34,$H$140*F34),AND(D34=$A$140,C34=$C$135),SUM(($C$136-G34)*F34,$I$140*F34),AND(D34=$A$141,C34=$F$135),SUM(($F$136-G34)*F34,$G$141*F34), AND(D34=$A$141,C34=$B$135),SUM(($B$136-G34)*F34,$H$141*F34),AND(D34=$A$141,C34=$C$135),SUM(($C$136-G34)*F34,$I$141*F34)),"") -> 0 | K34: =IFERROR(IFS(D34=E34,H34+J34,D34<>E34,J34),0) -> 0
C35: NIL | D35: NIL | E35: NIL | G35: =IF(OR(A35="NIL", C35="NIL", D35="NIL", E35="NIL"), 0, INDEX($B$136:$F$152, MATCH(E35, $A$136:$A$152, 0), MATCH(C35, $B$135:$F$135, 0))) -> 0 | H35: =G35*F35 -> 0 | J35: =IFERROR(IFS(A35="NIL",0,C35="NIL",0,D35="NIL",0,E35="NIL",0,AND(D35=$A$138,C35=$F$135),SUM(($F$136-G35)*F35,$G$138*F35), AND(D35=$A$138,C35=$B$135),SUM(($B$136-G35)*F35,$H$138*F35),AND(D35=$A$138,C35=$C$135),SUM(($C$136-G35)*F35,$I$138*F35),AND(D35=$A$139,C35=$F$135),SUM(($F$136-G35)*F35,$G$139*F35), AND(D35=$A$139,C35=$B$135),SUM(($B$136-G35)*F35,$H$139*F35),AND(D35=$A$139,C35=$C$135),SUM(($C$136-G35)*F35,$I$139*F35),AND(D35=$A$140,C35=$F$135),SUM(($F$136-G35)*F35,$G$140*F35), AND(D35=$A$140,C35=$B$135),SUM(($B$136-G35)*F35,$H$140*F35),AND(D35=$A$140,C35=$C$135),SUM(($C$136-G35)*F35,$I$140*F35),AND(D35=$A$141,C35=$F$135),SUM(($F$136-G35)*F35,$G$141*F35), AND(D35=$A$141,C35=$B$135),SUM(($B$136-G35)*F35,$H$141*F35),AND(D35=$A$141,C35=$C$135),SUM(($C$136-G35)*F35,$I$141*F35)),"") -> 0 | K35: =IFERROR(IFS(D35=E35,H35+J35,D35<>E35,J35),0) -> 0
C36: NIL | D36: NIL | E36: NIL | G36: =IF(OR(A36="NIL", C36="NIL", D36="NIL", E36="NIL"), 0, INDEX($B$136:$F$152, MATCH(E36, $A$136:$A$152, 0), MATCH(C36, $B$135:$F$135, 0))) -> 0 | H36: =G36*F36 -> 0 | J36: =IFERROR(IFS(A36="NIL",0,C36="NIL",0,D36="NIL",0,E36="NIL",0,AND(D36=$A$138,C36=$F$135),SUM(($F$136-G36)*F36,$G$138*F36), AND(D36=$A$138,C36=$B$135),SUM(($B$136-G36)*F36,$H$138*F36),AND(D36=$A$138,C36=$C$135),SUM(($C$136-G36)*F36,$I$138*F36),AND(D36=$A$139,C36=$F$135),SUM(($F$136-G36)*F36,$G$139*F36), AND(D36=$A$139,C36=$B$135),SUM(($B$136-G36)*F36,$H$139*F36),AND(D36=$A$139,C36=$C$135),SUM(($C$136-G36)*F36,$I$139*F36),AND(D36=$A$140,C36=$F$135),SUM(($F$136-G36)*F36,$G$140*F36), AND(D36=$A$140,C36=$B$135),SUM(($B$136-G36)*F36,$H$140*F36),AND(D36=$A$140,C36=$C$135),SUM(($C$136-G36)*F36,$I$140*F36),AND(D36=$A$141,C36=$F$135),SUM(($F$136-G36)*F36,$G$141*F36), AND(D36=$A$141,C36=$B$135),SUM(($B$136-G36)*F36,$H$141*F36),AND(D36=$A$141,C36=$C$135),SUM(($C$136-G36)*F36,$I$141*F36)),"") -> 0 | K36: =IFERROR(IFS(D36=E36,H36+J36,D36<>E36,J36),0) -> 0
C37: NIL | D37: NIL | E37: NIL | G37: =IF(OR(A37="NIL", C37="NIL", D37="NIL", E37="NIL"), 0, INDEX($B$136:$F$152, MATCH(E37, $A$136:$A$152, 0), MATCH(C37, $B$135:$F$135, 0))) -> 0 | H37: =G37*F37 -> 0 | J37: =IFERROR(IFS(A37="NIL",0,C37="NIL",0,D37="NIL",0,E37="NIL",0,AND(D37=$A$138,C37=$F$135),SUM(($F$136-G37)*F37,$G$138*F37), AND(D37=$A$138,C37=$B$135),SUM(($B$136-G37)*F37,$H$138*F37),AND(D37=$A$138,C37=$C$135),SUM(($C$136-G37)*F37,$I$138*F37),AND(D37=$A$139,C37=$F$135),SUM(($F$136-G37)*F37,$G$139*F37), AND(D37=$A$139,C37=$B$135),SUM(($B$136-G37)*F37,$H$139*F37),AND(D37=$A$139,C37=$C$135),SUM(($C$136-G37)*F37,$I$139*F37),AND(D37=$A$140,C37=$F$135),SUM(($F$136-G37)*F37,$G$140*F37), AND(D37=$A$140,C37=$B$135),SUM(($B$136-G37)*F37,$H$140*F37),AND(D37=$A$140,C37=$C$135),SUM(($C$136-G37)*F37,$I$140*F37),AND(D37=$A$141,C37=$F$135),SUM(($F$136-G37)*F37,$G$141*F37), AND(D37=$A$141,C37=$B$135),SUM(($B$136-G37)*F37,$H$141*F37),AND(D37=$A$141,C37=$C$135),SUM(($C$136-G37)*F37,$I$141*F37)),"") -> 0 | K37: =IFERROR(IFS(D37=E37,H37+J37,D37<>E37,J37),0) -> 0
C38: NIL | D38: NIL | E38: NIL | G38: =IF(OR(A38="NIL", C38="NIL", D38="NIL", E38="NIL"), 0, INDEX($B$136:$F$152, MATCH(E38, $A$136:$A$152, 0), MATCH(C38, $B$135:$F$135, 0))) -> 0 | H38: =G38*F38 -> 0 | J38: =IFERROR(IFS(A38="NIL",0,C38="NIL",0,D38="NIL",0,E38="NIL",0,AND(D38=$A$138,C38=$F$135),SUM(($F$136-G38)*F38,$G$138*F38), AND(D38=$A$138,C38=$B$135),SUM(($B$136-G38)*F38,$H$138*F38),AND(D38=$A$138,C38=$C$135),SUM(($C$136-G38)*F38,$I$138*F38),AND(D38=$A$139,C38=$F$135),SUM(($F$136-G38)*F38,$G$139*F38), AND(D38=$A$139,C38=$B$135),SUM(($B$136-G38)*F38,$H$139*F38),AND(D38=$A$139,C38=$C$135),SUM(($C$136-G38)*F38,$I$139*F38),AND(D38=$A$140,C38=$F$135),SUM(($F$136-G38)*F38,$G$140*F38), AND(D38=$A$140,C38=$B$135),SUM(($B$136-G38)*F38,$H$140*F38),AND(D38=$A$140,C38=$C$135),SUM(($C$136-G38)*F38,$I$140*F38),AND(D38=$A$141,C38=$F$135),SUM(($F$136-G38)*F38,$G$141*F38), AND(D38=$A$141,C38=$B$135),SUM(($B$136-G38)*F38,$H$141*F38),AND(D38=$A$141,C38=$C$135),SUM(($C$136-G38)*F38,$I$141*F38)),"") -> 0 | K38: =IFERROR(IFS(D38=E38,H38+J38,D38<>E38,J38),0) -> 0
C39: NIL | D39: NIL | E39: NIL | G39: =IF(OR(A39="NIL", C39="NIL", D39="NIL", E39="NIL"), 0, INDEX($B$136:$F$152, MATCH(E39, $A$136:$A$152, 0), MATCH(C39, $B$135:$F$135, 0))) -> 0 | H39: =G39*F39 -> 0 | J39: =IFERROR(IFS(A39="NIL",0,C39="NIL",0,D39="NIL",0,E39="NIL",0,AND(D39=$A$138,C39=$F$135),SUM(($F$136-G39)*F39,$G$138*F39), AND(D39=$A$138,C39=$B$135),SUM(($B$136-G39)*F39,$H$138*F39),AND(D39=$A$138,C39=$C$135),SUM(($C$136-G39)*F39,$I$138*F39),AND(D39=$A$139,C39=$F$135),SUM(($F$136-G39)*F39,$G$139*F39), AND(D39=$A$139,C39=$B$135),SUM(($B$136-G39)*F39,$H$139*F39),AND(D39=$A$139,C39=$C$135),SUM(($C$136-G39)*F39,$I$139*F39),AND(D39=$A$140,C39=$F$135),SUM(($F$136-G39)*F39,$G$140*F39), AND(D39=$A$140,C39=$B$135),SUM(($B$136-G39)*F39,$H$140*F39),AND(D39=$A$140,C39=$C$135),SUM(($C$136-G39)*F39,$I$140*F39),AND(D39=$A$141,C39=$F$135),SUM(($F$136-G39)*F39,$G$141*F39), AND(D39=$A$141,C39=$B$135),SUM(($B$136-G39)*F39,$H$141*F39),AND(D39=$A$141,C39=$C$135),SUM(($C$136-G39)*F39,$I$141*F39)),"") -> 0 | K39: =IFERROR(IFS(D39=E39,H39+J39,D39<>E39,J39),0) -> 0
C40: NIL | D40: NIL | E40: NIL | G40: =IF(OR(A40="NIL", C40="NIL", D40="NIL", E40="NIL"), 0, INDEX($B$136:$F$152, MATCH(E40, $A$136:$A$152, 0), MATCH(C40, $B$135:$F$135, 0))) -> 0 | H40: =G40*F40 -> 0 | J40: =IFERROR(IFS(A40="NIL",0,C40="NIL",0,D40="NIL",0,E40="NIL",0,AND(D40=$A$138,C40=$F$135),SUM(($F$136-G40)*F40,$G$138*F40), AND(D40=$A$138,C40=$B$135),SUM(($B$136-G40)*F40,$H$138*F40),AND(D40=$A$138,C40=$C$135),SUM(($C$136-G40)*F40,$I$138*F40),AND(D40=$A$139,C40=$F$135),SUM(($F$136-G40)*F40,$G$139*F40), AND(D40=$A$139,C40=$B$135),SUM(($B$136-G40)*F40,$H$139*F40),AND(D40=$A$139,C40=$C$135),SUM(($C$136-G40)*F40,$I$139*F40),AND(D40=$A$140,C40=$F$135),SUM(($F$136-G40)*F40,$G$140*F40), AND(D40=$A$140,C40=$B$135),SUM(($B$136-G40)*F40,$H$140*F40),AND(D40=$A$140,C40=$C$135),SUM(($C$136-G40)*F40,$I$140*F40),AND(D40=$A$141,C40=$F$135),SUM(($F$136-G40)*F40,$G$141*F40), AND(D40=$A$141,C40=$B$135),SUM(($B$136-G40)*F40,$H$141*F40),AND(D40=$A$141,C40=$C$135),SUM(($C$136-G40)*F40,$I$141*F40)),"") -> 0 | K40: =IFERROR(IFS(D40=E40,H40+J40,D40<>E40,J40),0) -> 0
A41: Sony Tyres | C41: NIL | D41: NIL | E41: NIL | G41: =IF(OR(A41="NIL", C41="NIL", D41="NIL", E41="NIL"), 0, INDEX($B$136:$F$152, MATCH(E41, $A$136:$A$152, 0), MATCH(C41, $B$135:$F$135, 0))) -> 0 | H41: =G41*F41 -> 0 | J41: =IFERROR(IFS(A41="NIL",0,C41="NIL",0,D41="NIL",0,E41="NIL",0,AND(D41=$A$138,C41=$F$135),SUM(($F$136-G41)*F41,$G$138*F41), AND(D41=$A$138,C41=$B$135),SUM(($B$136-G41)*F41,$H$138*F41),AND(D41=$A$138,C41=$C$135),SUM(($C$136-G41)*F41,$I$138*F41),AND(D41=$A$139,C41=$F$135),SUM(($F$136-G41)*F41,$G$139*F41), AND(D41=$A$139,C41=$B$135),SUM(($B$136-G41)*F41,$H$139*F41),AND(D41=$A$139,C41=$C$135),SUM(($C$136-G41)*F41,$I$139*F41),AND(D41=$A$140,C41=$F$135),SUM(($F$136-G41)*F41,$G$140*F41), AND(D41=$A$140,C41=$B$135),SUM(($B$136-G41)*F41,$H$140*F41),AND(D41=$A$140,C41=$C$135),SUM(($C$136-G41)*F41,$I$140*F41),AND(D41=$A$141,C41=$F$135),SUM(($F$136-G41)*F41,$G$141*F41), AND(D41=$A$141,C41=$B$135),SUM(($B$136-G41)*F41,$H$141*F41),AND(D41=$A$141,C41=$C$135),SUM(($C$136-G41)*F41,$I$141*F41)),"") -> 0 | K41: =IFERROR(IFS(D41=E41,H41+J41,D41<>E41,J41),0) -> 0 | L41: =SUM(VLOOKUP(A41,$A$165:$C$178,2,False)*25%,VLOOKUP(A41,$A$165:$C$178,3,False)*25%) -> 1875
C42: NIL | D42: NIL | E42: NIL | G42: =IF(OR(A42="NIL", C42="NIL", D42="NIL", E42="NIL"), 0, INDEX($B$136:$F$152, MATCH(E42, $A$136:$A$152, 0), MATCH(C42, $B$135:$F$135, 0))) -> 0 | H42: =G42*F42 -> 0 | J42: =IFERROR(IFS(A42="NIL",0,C42="NIL",0,D42="NIL",0,E42="NIL",0,AND(D42=$A$138,C42=$F$135),SUM(($F$136-G42)*F42,$G$138*F42), AND(D42=$A$138,C42=$B$135),SUM(($B$136-G42)*F42,$H$138*F42),AND(D42=$A$138,C42=$C$135),SUM(($C$136-G42)*F42,$I$138*F42),AND(D42=$A$139,C42=$F$135),SUM(($F$136-G42)*F42,$G$139*F42), AND(D42=$A$139,C42=$B$135),SUM(($B$136-G42)*F42,$H$139*F42),AND(D42=$A$139,C42=$C$135),SUM(($C$136-G42)*F42,$I$139*F42),AND(D42=$A$140,C42=$F$135),SUM(($F$136-G42)*F42,$G$140*F42), AND(D42=$A$140,C42=$B$135),SUM(($B$136-G42)*F42,$H$140*F42),AND(D42=$A$140,C42=$C$135),SUM(($C$136-G42)*F42,$I$140*F42),AND(D42=$A$141,C42=$F$135),SUM(($F$136-G42)*F42,$G$141*F42), AND(D42=$A$141,C42=$B$135),SUM(($B$136-G42)*F42,$H$141*F42),AND(D42=$A$141,C42=$C$135),SUM(($C$136-G42)*F42,$I$141*F42)),"") -> 0 | K42: =IFERROR(IFS(D42=E42,H42+J42,D42<>E42,J42),0) -> 0
C43: NIL | D43: NIL | E43: NIL | G43: =IF(OR(A43="NIL", C43="NIL", D43="NIL", E43="NIL"), 0, INDEX($B$136:$F$152, MATCH(E43, $A$136:$A$152, 0), MATCH(C43, $B$135:$F$135, 0))) -> 0 | H43: =G43*F43 -> 0 | J43: =IFERROR(IFS(A43="NIL",0,C43="NIL",0,D43="NIL",0,E43="NIL",0,AND(D43=$A$138,C43=$F$135),SUM(($F$136-G43)*F43,$G$138*F43), AND(D43=$A$138,C43=$B$135),SUM(($B$136-G43)*F43,$H$138*F43),AND(D43=$A$138,C43=$C$135),SUM(($C$136-G43)*F43,$I$138*F43),AND(D43=$A$139,C43=$F$135),SUM(($F$136-G43)*F43,$G$139*F43), AND(D43=$A$139,C43=$B$135),SUM(($B$136-G43)*F43,$H$139*F43),AND(D43=$A$139,C43=$C$135),SUM(($C$136-G43)*F43,$I$139*F43),AND(D43=$A$140,C43=$F$135),SUM(($F$136-G43)*F43,$G$140*F43), AND(D43=$A$140,C43=$B$135),SUM(($B$136-G43)*F43,$H$140*F43),AND(D43=$A$140,C43=$C$135),SUM(($C$136-G43)*F43,$I$140*F43),AND(D43=$A$141,C43=$F$135),SUM(($F$136-G43)*F43,$G$141*F43), AND(D43=$A$141,C43=$B$135),SUM(($B$136-G43)*F43,$H$141*F43),AND(D43=$A$141,C43=$C$135),SUM(($C$136-G43)*F43,$I$141*F43)),"") -> 0 | K43: =IFERROR(IFS(D43=E43,H43+J43,D43<>E43,J43),0) -> 0
C44: NIL | D44: NIL | E44: NIL | G44: =IF(OR(A44="NIL", C44="NIL", D44="NIL", E44="NIL"), 0, INDEX($B$136:$F$152, MATCH(E44, $A$136:$A$152, 0), MATCH(C44, $B$135:$F$135, 0))) -> 0 | H44: =G44*F44 -> 0 | J44: =IFERROR(IFS(A44="NIL",0,C44="NIL",0,D44="NIL",0,E44="NIL",0,AND(D44=$A$138,C44=$F$135),SUM(($F$136-G44)*F44,$G$138*F44), AND(D44=$A$138,C44=$B$135),SUM(($B$136-G44)*F44,$H$138*F44),AND(D44=$A$138,C44=$C$135),SUM(($C$136-G44)*F44,$I$138*F44),AND(D44=$A$139,C44=$F$135),SUM(($F$136-G44)*F44,$G$139*F44), AND(D44=$A$139,C44=$B$135),SUM(($B$136-G44)*F44,$H$139*F44),AND(D44=$A$139,C44=$C$135),SUM(($C$136-G44)*F44,$I$139*F44),AND(D44=$A$140,C44=$F$135),SUM(($F$136-G44)*F44,$G$140*F44), AND(D44=$A$140,C44=$B$135),SUM(($B$136-G44)*F44,$H$140*F44),AND(D44=$A$140,C44=$C$135),SUM(($C$136-G44)*F44,$I$140*F44),AND(D44=$A$141,C44=$F$135),SUM(($F$136-G44)*F44,$G$141*F44), AND(D44=$A$141,C44=$B$135),SUM(($B$136-G44)*F44,$H$141*F44),AND(D44=$A$141,C44=$C$135),SUM(($C$136-G44)*F44,$I$141*F44)),"") -> 0 | K44: =IFERROR(IFS(D44=E44,H44+J44,D44<>E44,J44),0) -> 0
C45: Poster Design | D45: Nebil Divay | E45: Ram | F45: 1 | G45: =IF(OR(A45="NIL", C45="NIL", D45="NIL", E45="NIL"), 0, INDEX($B$136:$F$152, MATCH(E45, $A$136:$A$152, 0), MATCH(C45, $B$135:$F$135, 0))) -> 100 | H45: =G45*F45 -> 100 | J45: =IFERROR(IFS(A45="NIL",0,C45="NIL",0,D45="NIL",0,E45="NIL",0,AND(D45=$A$138,C45=$F$135),SUM(($F$136-G45)*F45,$G$138*F45), AND(D45=$A$138,C45=$B$135),SUM(($B$136-G45)*F45,$H$138*F45),AND(D45=$A$138,C45=$C$135),SUM(($C$136-G45)*F45,$I$138*F45),AND(D45=$A$139,C45=$F$135),SUM(($F$136-G45)*F45,$G$139*F45), AND(D45=$A$139,C45=$B$135),SUM(($B$136-G45)*F45,$H$139*F45),AND(D45=$A$139,C45=$C$135),SUM(($C$136-G45)*F45,$I$139*F45),AND(D45=$A$140,C45=$F$135),SUM(($F$136-G45)*F45,$G$140*F45), AND(D45=$A$140,C45=$B$135),SUM(($B$136-G45)*F45,$H$140*F45),AND(D45=$A$140,C45=$C$135),SUM(($C$136-G45)*F45,$I$140*F45),AND(D45=$A$141,C45=$F$135),SUM(($F$136-G45)*F45,$G$141*F45), AND(D45=$A$141,C45=$B$135),SUM(($B$136-G45)*F45,$H$141*F45),AND(D45=$A$141,C45=$C$135),SUM(($C$136-G45)*F45,$I$141*F45)),"") -> 126 | K45: =IFERROR(IFS(D45=E45,H45+J45,D45<>E45,J45),0) -> 126
C46: NIL | D46: NIL | E46: NIL | G46: =IF(OR(A46="NIL", C46="NIL", D46="NIL", E46="NIL"), 0, INDEX($B$136:$F$152, MATCH(E46, $A$136:$A$152, 0), MATCH(C46, $B$135:$F$135, 0))) -> 0 | H46: =G46*F46 -> 0 | J46: =IFERROR(IFS(A46="NIL",0,C46="NIL",0,D46="NIL",0,E46="NIL",0,AND(D46=$A$138,C46=$F$135),SUM(($F$136-G46)*F46,$G$138*F46), AND(D46=$A$138,C46=$B$135),SUM(($B$136-G46)*F46,$H$138*F46),AND(D46=$A$138,C46=$C$135),SUM(($C$136-G46)*F46,$I$138*F46),AND(D46=$A$139,C46=$F$135),SUM(($F$136-G46)*F46,$G$139*F46), AND(D46=$A$139,C46=$B$135),SUM(($B$136-G46)*F46,$H$139*F46),AND(D46=$A$139,C46=$C$135),SUM(($C$136-G46)*F46,$I$139*F46),AND(D46=$A$140,C46=$F$135),SUM(($F$136-G46)*F46,$G$140*F46), AND(D46=$A$140,C46=$B$135),SUM(($B$136-G46)*F46,$H$140*F46),AND(D46=$A$140,C46=$C$135),SUM(($C$136-G46)*F46,$I$140*F46),AND(D46=$A$141,C46=$F$135),SUM(($F$136-G46)*F46,$G$141*F46), AND(D46=$A$141,C46=$B$135),SUM(($B$136-G46)*F46,$H$141*F46),AND(D46=$A$141,C46=$C$135),SUM(($C$136-G46)*F46,$I$141*F46)),"") -> 0 | K46: =IFERROR(IFS(D46=E46,H46+J46,D46<>E46,J46),0) -> 0
C47: NIL | D47: NIL | E47: NIL | G47: =IF(OR(A47="NIL", C47="NIL", D47="NIL", E47="NIL"), 0, INDEX($B$136:$F$152, MATCH(E47, $A$136:$A$152, 0), MATCH(C47, $B$135:$F$135, 0))) -> 0 | H47: =G47*F47 -> 0 | J47: =IFERROR(IFS(A47="NIL",0,C47="NIL",0,D47="NIL",0,E47="NIL",0,AND(D47=$A$138,C47=$F$135),SUM(($F$136-G47)*F47,$G$138*F47), AND(D47=$A$138,C47=$B$135),SUM(($B$136-G47)*F47,$H$138*F47),AND(D47=$A$138,C47=$C$135),SUM(($C$136-G47)*F47,$I$138*F47),AND(D47=$A$139,C47=$F$135),SUM(($F$136-G47)*F47,$G$139*F47), AND(D47=$A$139,C47=$B$135),SUM(($B$136-G47)*F47,$H$139*F47),AND(D47=$A$139,C47=$C$135),SUM(($C$136-G47)*F47,$I$139*F47),AND(D47=$A$140,C47=$F$135),SUM(($F$136-G47)*F47,$G$140*F47), AND(D47=$A$140,C47=$B$135),SUM(($B$136-G47)*F47,$H$140*F47),AND(D47=$A$140,C47=$C$135),SUM(($C$136-G47)*F47,$I$140*F47),AND(D47=$A$141,C47=$F$135),SUM(($F$136-G47)*F47,$G$141*F47), AND(D47=$A$141,C47=$B$135),SUM(($B$136-G47)*F47,$H$141*F47),AND(D47=$A$141,C47=$C$135),SUM(($C$136-G47)*F47,$I$141*F47)),"") -> 0 | K47: =IFERROR(IFS(D47=E47,H47+J47,D47<>E47,J47),0) -> 0
C48: NIL | D48: NIL | E48: NIL | G48: =IF(OR(A48="NIL", C48="NIL", D48="NIL", E48="NIL"), 0, INDEX($B$136:$F$152, MATCH(E48, $A$136:$A$152, 0), MATCH(C48, $B$135:$F$135, 0))) -> 0 | H48: =G48*F48 -> 0 | J48: =IFERROR(IFS(A48="NIL",0,C48="NIL",0,D48="NIL",0,E48="NIL",0,AND(D48=$A$138,C48=$F$135),SUM(($F$136-G48)*F48,$G$138*F48), AND(D48=$A$138,C48=$B$135),SUM(($B$136-G48)*F48,$H$138*F48),AND(D48=$A$138,C48=$C$135),SUM(($C$136-G48)*F48,$I$138*F48),AND(D48=$A$139,C48=$F$135),SUM(($F$136-G48)*F48,$G$139*F48), AND(D48=$A$139,C48=$B$135),SUM(($B$136-G48)*F48,$H$139*F48),AND(D48=$A$139,C48=$C$135),SUM(($C$136-G48)*F48,$I$139*F48),AND(D48=$A$140,C48=$F$135),SUM(($F$136-G48)*F48,$G$140*F48), AND(D48=$A$140,C48=$B$135),SUM(($B$136-G48)*F48,$H$140*F48),AND(D48=$A$140,C48=$C$135),SUM(($C$136-G48)*F48,$I$140*F48),AND(D48=$A$141,C48=$F$135),SUM(($F$136-G48)*F48,$G$141*F48), AND(D48=$A$141,C48=$B$135),SUM(($B$136-G48)*F48,$H$141*F48),AND(D48=$A$141,C48=$C$135),SUM(($C$136-G48)*F48,$I$141*F48)),"") -> 0 | K48: =IFERROR(IFS(D48=E48,H48+J48,D48<>E48,J48),0) -> 0
C49: NIL | D49: NIL | E49: NIL | G49: =IF(OR(A49="NIL", C49="NIL", D49="NIL", E49="NIL"), 0, INDEX($B$136:$F$152, MATCH(E49, $A$136:$A$152, 0), MATCH(C49, $B$135:$F$135, 0))) -> 0 | H49: =G49*F49 -> 0 | J49: =IFERROR(IFS(A49="NIL",0,C49="NIL",0,D49="NIL",0,E49="NIL",0,AND(D49=$A$138,C49=$F$135),SUM(($F$136-G49)*F49,$G$138*F49), AND(D49=$A$138,C49=$B$135),SUM(($B$136-G49)*F49,$H$138*F49),AND(D49=$A$138,C49=$C$135),SUM(($C$136-G49)*F49,$I$138*F49),AND(D49=$A$139,C49=$F$135),SUM(($F$136-G49)*F49,$G$139*F49), AND(D49=$A$139,C49=$B$135),SUM(($B$136-G49)*F49,$H$139*F49),AND(D49=$A$139,C49=$C$135),SUM(($C$136-G49)*F49,$I$139*F49),AND(D49=$A$140,C49=$F$135),SUM(($F$136-G49)*F49,$G$140*F49), AND(D49=$A$140,C49=$B$135),SUM(($B$136-G49)*F49,$H$140*F49),AND(D49=$A$140,C49=$C$135),SUM(($C$136-G49)*F49,$I$140*F49),AND(D49=$A$141,C49=$F$135),SUM(($F$136-G49)*F49,$G$141*F49), AND(D49=$A$141,C49=$B$135),SUM(($B$136-G49)*F49,$H$141*F49),AND(D49=$A$141,C49=$C$135),SUM(($C$136-G49)*F49,$I$141*F49)),"") -> 0 | K49: =IFERROR(IFS(D49=E49,H49+J49,D49<>E49,J49),0) -> 0
C50: NIL | D50: NIL | E50: NIL | G50: =IF(OR(A50="NIL", C50="NIL", D50="NIL", E50="NIL"), 0, INDEX($B$136:$F$152, MATCH(E50, $A$136:$A$152, 0), MATCH(C50, $B$135:$F$135, 0))) -> 0 | H50: =G50*F50 -> 0 | J50: =IFERROR(IFS(A50="NIL",0,C50="NIL",0,D50="NIL",0,E50="NIL",0,AND(D50=$A$138,C50=$F$135),SUM(($F$136-G50)*F50,$G$138*F50), AND(D50=$A$138,C50=$B$135),SUM(($B$136-G50)*F50,$H$138*F50),AND(D50=$A$138,C50=$C$135),SUM(($C$136-G50)*F50,$I$138*F50),AND(D50=$A$139,C50=$F$135),SUM(($F$136-G50)*F50,$G$139*F50), AND(D50=$A$139,C50=$B$135),SUM(($B$136-G50)*F50,$H$139*F50),AND(D50=$A$139,C50=$C$135),SUM(($C$136-G50)*F50,$I$139*F50),AND(D50=$A$140,C50=$F$135),SUM(($F$136-G50)*F50,$G$140*F50), AND(D50=$A$140,C50=$B$135),SUM(($B$136-G50)*F50,$H$140*F50),AND(D50=$A$140,C50=$C$135),SUM(($C$136-G50)*F50,$I$140*F50),AND(D50=$A$141,C50=$F$135),SUM(($F$136-G50)*F50,$G$141*F50), AND(D50=$A$141,C50=$B$135),SUM(($B$136-G50)*F50,$H$141*F50),AND(D50=$A$141,C50=$C$135),SUM(($C$136-G50)*F50,$I$141*F50)),"") -> 0 | K50: =IFERROR(IFS(D50=E50,H50+J50,D50<>E50,J50),0) -> 0
C51: NIL | D51: NIL | E51: NIL | G51: =IF(OR(A51="NIL", C51="NIL", D51="NIL", E51="NIL"), 0, INDEX($B$136:$F$152, MATCH(E51, $A$136:$A$152, 0), MATCH(C51, $B$135:$F$135, 0))) -> 0 | H51: =G51*F51 -> 0 | J51: =IFERROR(IFS(A51="NIL",0,C51="NIL",0,D51="NIL",0,E51="NIL",0,AND(D51=$A$138,C51=$F$135),SUM(($F$136-G51)*F51,$G$138*F51), AND(D51=$A$138,C51=$B$135),SUM(($B$136-G51)*F51,$H$138*F51),AND(D51=$A$138,C51=$C$135),SUM(($C$136-G51)*F51,$I$138*F51),AND(D51=$A$139,C51=$F$135),SUM(($F$136-G51)*F51,$G$139*F51), AND(D51=$A$139,C51=$B$135),SUM(($B$136-G51)*F51,$H$139*F51),AND(D51=$A$139,C51=$C$135),SUM(($C$136-G51)*F51,$I$139*F51),AND(D51=$A$140,C51=$F$135),SUM(($F$136-G51)*F51,$G$140*F51), AND(D51=$A$140,C51=$B$135),SUM(($B$136-G51)*F51,$H$140*F51),AND(D51=$A$140,C51=$C$135),SUM(($C$136-G51)*F51,$I$140*F51),AND(D51=$A$141,C51=$F$135),SUM(($F$136-G51)*F51,$G$141*F51), AND(D51=$A$141,C51=$B$135),SUM(($B$136-G51)*F51,$H$141*F51),AND(D51=$A$141,C51=$C$135),SUM(($C$136-G51)*F51,$I$141*F51)),"") -> 0 | K51: =IFERROR(IFS(D51=E51,H51+J51,D51<>E51,J51),0) -> 0
C52: NIL | D52: NIL | E52: NIL | G52: =IF(OR(A52="NIL", C52="NIL", D52="NIL", E52="NIL"), 0, INDEX($B$136:$F$152, MATCH(E52, $A$136:$A$152, 0), MATCH(C52, $B$135:$F$135, 0))) -> 0 | H52: =G52*F52 -> 0 | J52: =IFERROR(IFS(A52="NIL",0,C52="NIL",0,D52="NIL",0,E52="NIL",0,AND(D52=$A$138,C52=$F$135),SUM(($F$136-G52)*F52,$G$138*F52), AND(D52=$A$138,C52=$B$135),SUM(($B$136-G52)*F52,$H$138*F52),AND(D52=$A$138,C52=$C$135),SUM(($C$136-G52)*F52,$I$138*F52),AND(D52=$A$139,C52=$F$135),SUM(($F$136-G52)*F52,$G$139*F52), AND(D52=$A$139,C52=$B$135),SUM(($B$136-G52)*F52,$H$139*F52),AND(D52=$A$139,C52=$C$135),SUM(($C$136-G52)*F52,$I$139*F52),AND(D52=$A$140,C52=$F$135),SUM(($F$136-G52)*F52,$G$140*F52), AND(D52=$A$140,C52=$B$135),SUM(($B$136-G52)*F52,$H$140*F52),AND(D52=$A$140,C52=$C$135),SUM(($C$136-G52)*F52,$I$140*F52),AND(D52=$A$141,C52=$F$135),SUM(($F$136-G52)*F52,$G$141*F52), AND(D52=$A$141,C52=$B$135),SUM(($B$136-G52)*F52,$H$141*F52),AND(D52=$A$141,C52=$C$135),SUM(($C$136-G52)*F52,$I$141*F52)),"") -> 0 | K52: =IFERROR(IFS(D52=E52,H52+J52,D52<>E52,J52),0) -> 0
C53: NIL | D53: NIL | E53: NIL | G53: =IF(OR(A53="NIL", C53="NIL", D53="NIL", E53="NIL"), 0, INDEX($B$136:$F$152, MATCH(E53, $A$136:$A$152, 0), MATCH(C53, $B$135:$F$135, 0))) -> 0 | H53: =G53*F53 -> 0 | J53: =IFERROR(IFS(A53="NIL",0,C53="NIL",0,D53="NIL",0,E53="NIL",0,AND(D53=$A$138,C53=$F$135),SUM(($F$136-G53)*F53,$G$138*F53), AND(D53=$A$138,C53=$B$135),SUM(($B$136-G53)*F53,$H$138*F53),AND(D53=$A$138,C53=$C$135),SUM(($C$136-G53)*F53,$I$138*F53),AND(D53=$A$139,C53=$F$135),SUM(($F$136-G53)*F53,$G$139*F53), AND(D53=$A$139,C53=$B$135),SUM(($B$136-G53)*F53,$H$139*F53),AND(D53=$A$139,C53=$C$135),SUM(($C$136-G53)*F53,$I$139*F53),AND(D53=$A$140,C53=$F$135),SUM(($F$136-G53)*F53,$G$140*F53), AND(D53=$A$140,C53=$B$135),SUM(($B$136-G53)*F53,$H$140*F53),AND(D53=$A$140,C53=$C$135),SUM(($C$136-G53)*F53,$I$140*F53),AND(D53=$A$141,C53=$F$135),SUM(($F$136-G53)*F53,$G$141*F53), AND(D53=$A$141,C53=$B$135),SUM(($B$136-G53)*F53,$H$141*F53),AND(D53=$A$141,C53=$C$135),SUM(($C$136-G53)*F53,$I$141*F53)),"") -> 0 | K53: =IFERROR(IFS(D53=E53,H53+J53,D53<>E53,J53),0) -> 0
A54: Prince Tyres | C54: NIL | D54: NIL | E54: NIL | G54: =IF(OR(A54="NIL", C54="NIL", D54="NIL", E54="NIL"), 0, INDEX($B$136:$F$152, MATCH(E54, $A$136:$A$152, 0), MATCH(C54, $B$135:$F$135, 0))) -> 0 | H54: =G54*F54 -> 0 | J54: =IFERROR(IFS(A54="NIL",0,C54="NIL",0,D54="NIL",0,E54="NIL",0,AND(D54=$A$138,C54=$F$135),SUM(($F$136-G54)*F54,$G$138*F54), AND(D54=$A$138,C54=$B$135),SUM(($B$136-G54)*F54,$H$138*F54),AND(D54=$A$138,C54=$C$135),SUM(($C$136-G54)*F54,$I$138*F54),AND(D54=$A$139,C54=$F$135),SUM(($F$136-G54)*F54,$G$139*F54), AND(D54=$A$139,C54=$B$135),SUM(($B$136-G54)*F54,$H$139*F54),AND(D54=$A$139,C54=$C$135),SUM(($C$136-G54)*F54,$I$139*F54),AND(D54=$A$140,C54=$F$135),SUM(($F$136-G54)*F54,$G$140*F54), AND(D54=$A$140,C54=$B$135),SUM(($B$136-G54)*F54,$H$140*F54),AND(D54=$A$140,C54=$C$135),SUM(($C$136-G54)*F54,$I$140*F54),AND(D54=$A$141,C54=$F$135),SUM(($F$136-G54)*F54,$G$141*F54), AND(D54=$A$141,C54=$B$135),SUM(($B$136-G54)*F54,$H$141*F54),AND(D54=$A$141,C54=$C$135),SUM(($C$136-G54)*F54,$I$141*F54)),"") -> 0 | K54: =IFERROR(IFS(D54=E54,H54+J54,D54<>E54,J54),0) -> 0 | L54: =SUM(VLOOKUP(A54,$A$165:$C$178,2,False)*25%,VLOOKUP(A54,$A$165:$C$178,3,False)*25%) -> 187.5
C55: NIL | D55: NIL | E55: NIL | G55: =IF(OR(A55="NIL", C55="NIL", D55="NIL", E55="NIL"), 0, INDEX($B$136:$F$152, MATCH(E55, $A$136:$A$152, 0), MATCH(C55, $B$135:$F$135, 0))) -> 0 | H55: =G55*F55 -> 0 | J55: =IFERROR(IFS(A55="NIL",0,C55="NIL",0,D55="NIL",0,E55="NIL",0,AND(D55=$A$138,C55=$F$135),SUM(($F$136-G55)*F55,$G$138*F55), AND(D55=$A$138,C55=$B$135),SUM(($B$136-G55)*F55,$H$138*F55),AND(D55=$A$138,C55=$C$135),SUM(($C$136-G55)*F55,$I$138*F55),AND(D55=$A$139,C55=$F$135),SUM(($F$136-G55)*F55,$G$139*F55), AND(D55=$A$139,C55=$B$135),SUM(($B$136-G55)*F55,$H$139*F55),AND(D55=$A$139,C55=$C$135),SUM(($C$136-G55)*F55,$I$139*F55),AND(D55=$A$140,C55=$F$135),SUM(($F$136-G55)*F55,$G$140*F55), AND(D55=$A$140,C55=$B$135),SUM(($B$136-G55)*F55,$H$140*F55),AND(D55=$A$140,C55=$C$135),SUM(($C$136-G55)*F55,$I$140*F55),AND(D55=$A$141,C55=$F$135),SUM(($F$136-G55)*F55,$G$141*F55), AND(D55=$A$141,C55=$B$135),SUM(($B$136-G55)*F55,$H$141*F55),AND(D55=$A$141,C55=$C$135),SUM(($C$136-G55)*F55,$I$141*F55)),"") -> 0 | K55: =IFERROR(IFS(D55=E55,H55+J55,D55<>E55,J55),0) -> 0
C56: NIL | D56: NIL | E56: NIL | G56: =IF(OR(A56="NIL", C56="NIL", D56="NIL", E56="NIL"), 0, INDEX($B$136:$F$152, MATCH(E56, $A$136:$A$152, 0), MATCH(C56, $B$135:$F$135, 0))) -> 0 | H56: =G56*F56 -> 0 | J56: =IFERROR(IFS(A56="NIL",0,C56="NIL",0,D56="NIL",0,E56="NIL",0,AND(D56=$A$138,C56=$F$135),SUM(($F$136-G56)*F56,$G$138*F56), AND(D56=$A$138,C56=$B$135),SUM(($B$136-G56)*F56,$H$138*F56),AND(D56=$A$138,C56=$C$135),SUM(($C$136-G56)*F56,$I$138*F56),AND(D56=$A$139,C56=$F$135),SUM(($F$136-G56)*F56,$G$139*F56), AND(D56=$A$139,C56=$B$135),SUM(($B$136-G56)*F56,$H$139*F56),AND(D56=$A$139,C56=$C$135),SUM(($C$136-G56)*F56,$I$139*F56),AND(D56=$A$140,C56=$F$135),SUM(($F$136-G56)*F56,$G$140*F56), AND(D56=$A$140,C56=$B$135),SUM(($B$136-G56)*F56,$H$140*F56),AND(D56=$A$140,C56=$C$135),SUM(($C$136-G56)*F56,$I$140*F56),AND(D56=$A$141,C56=$F$135),SUM(($F$136-G56)*F56,$G$141*F56), AND(D56=$A$141,C56=$B$135),SUM(($B$136-G56)*F56,$H$141*F56),AND(D56=$A$141,C56=$C$135),SUM(($C$136-G56)*F56,$I$141*F56)),"") -> 0 | K56: =IFERROR(IFS(D56=E56,H56+J56,D56<>E56,J56),0) -> 0
C57: NIL | D57: NIL | E57: NIL | G57: =IF(OR(A57="NIL", C57="NIL", D57="NIL", E57="NIL"), 0, INDEX($B$136:$F$152, MATCH(E57, $A$136:$A$152, 0), MATCH(C57, $B$135:$F$135, 0))) -> 0 | H57: =G57*F57 -> 0 | J57: =IFERROR(IFS(A57="NIL",0,C57="NIL",0,D57="NIL",0,E57="NIL",0,AND(D57=$A$138,C57=$F$135),SUM(($F$136-G57)*F57,$G$138*F57), AND(D57=$A$138,C57=$B$135),SUM(($B$136-G57)*F57,$H$138*F57),AND(D57=$A$138,C57=$C$135),SUM(($C$136-G57)*F57,$I$138*F57),AND(D57=$A$139,C57=$F$135),SUM(($F$136-G57)*F57,$G$139*F57), AND(D57=$A$139,C57=$B$135),SUM(($B$136-G57)*F57,$H$139*F57),AND(D57=$A$139,C57=$C$135),SUM(($C$136-G57)*F57,$I$139*F57),AND(D57=$A$140,C57=$F$135),SUM(($F$136-G57)*F57,$G$140*F57), AND(D57=$A$140,C57=$B$135),SUM(($B$136-G57)*F57,$H$140*F57),AND(D57=$A$140,C57=$C$135),SUM(($C$136-G57)*F57,$I$140*F57),AND(D57=$A$141,C57=$F$135),SUM(($F$136-G57)*F57,$G$141*F57), AND(D57=$A$141,C57=$B$135),SUM(($B$136-G57)*F57,$H$141*F57),AND(D57=$A$141,C57=$C$135),SUM(($C$136-G57)*F57,$I$141*F57)),"") -> 0 | K57: =IFERROR(IFS(D57=E57,H57+J57,D57<>E57,J57),0) -> 0
C58: NIL | D58: NIL | E58: NIL | G58: =IF(OR(A58="NIL", C58="NIL", D58="NIL", E58="NIL"), 0, INDEX($B$136:$F$152, MATCH(E58, $A$136:$A$152, 0), MATCH(C58, $B$135:$F$135, 0))) -> 0 | H58: =G58*F58 -> 0 | J58: =IFERROR(IFS(A58="NIL",0,C58="NIL",0,D58="NIL",0,E58="NIL",0,AND(D58=$A$138,C58=$F$135),SUM(($F$136-G58)*F58,$G$138*F58), AND(D58=$A$138,C58=$B$135),SUM(($B$136-G58)*F58,$H$138*F58),AND(D58=$A$138,C58=$C$135),SUM(($C$136-G58)*F58,$I$138*F58),AND(D58=$A$139,C58=$F$135),SUM(($F$136-G58)*F58,$G$139*F58), AND(D58=$A$139,C58=$B$135),SUM(($B$136-G58)*F58,$H$139*F58),AND(D58=$A$139,C58=$C$135),SUM(($C$136-G58)*F58,$I$139*F58),AND(D58=$A$140,C58=$F$135),SUM(($F$136-G58)*F58,$G$140*F58), AND(D58=$A$140,C58=$B$135),SUM(($B$136-G58)*F58,$H$140*F58),AND(D58=$A$140,C58=$C$135),SUM(($C$136-G58)*F58,$I$140*F58),AND(D58=$A$141,C58=$F$135),SUM(($F$136-G58)*F58,$G$141*F58), AND(D58=$A$141,C58=$B$135),SUM(($B$136-G58)*F58,$H$141*F58),AND(D58=$A$141,C58=$C$135),SUM(($C$136-G58)*F58,$I$141*F58)),"") -> 0 | K58: =IFERROR(IFS(D58=E58,H58+J58,D58<>E58,J58),0) -> 0
C59: NIL | D59: NIL | E59: Ram | G59: =IF(OR(A59="NIL", C59="NIL", D59="NIL", E59="NIL"), 0, INDEX($B$136:$F$152, MATCH(E59, $A$136:$A$152, 0), MATCH(C59, $B$135:$F$135, 0))) -> 0 | H59: =G59*F59 -> 0 | J59: =IFERROR(IFS(A59="NIL",0,C59="NIL",0,D59="NIL",0,E59="NIL",0,AND(D59=$A$138,C59=$F$135),SUM(($F$136-G59)*F59,$G$138*F59), AND(D59=$A$138,C59=$B$135),SUM(($B$136-G59)*F59,$H$138*F59),AND(D59=$A$138,C59=$C$135),SUM(($C$136-G59)*F59,$I$138*F59),AND(D59=$A$139,C59=$F$135),SUM(($F$136-G59)*F59,$G$139*F59), AND(D59=$A$139,C59=$B$135),SUM(($B$136-G59)*F59,$H$139*F59),AND(D59=$A$139,C59=$C$135),SUM(($C$136-G59)*F59,$I$139*F59),AND(D59=$A$140,C59=$F$135),SUM(($F$136-G59)*F59,$G$140*F59), AND(D59=$A$140,C59=$B$135),SUM(($B$136-G59)*F59,$H$140*F59),AND(D59=$A$140,C59=$C$135),SUM(($C$136-G59)*F59,$I$140*F59),AND(D59=$A$141,C59=$F$135),SUM(($F$136-G59)*F59,$G$141*F59), AND(D59=$A$141,C59=$B$135),SUM(($B$136-G59)*F59,$H$141*F59),AND(D59=$A$141,C59=$C$135),SUM(($C$136-G59)*F59,$I$141*F59)),"") -> 0 | K59: =IFERROR(IFS(D59=E59,H59+J59,D59<>E59,J59),0) -> 0
C60: NIL | D60: NIL | E60: NIL | G60: =IF(OR(A60="NIL", C60="NIL", D60="NIL", E60="NIL"), 0, INDEX($B$136:$F$152, MATCH(E60, $A$136:$A$152, 0), MATCH(C60, $B$135:$F$135, 0))) -> 0 | H60: =G60*F60 -> 0 | J60: =IFERROR(IFS(A60="NIL",0,C60="NIL",0,D60="NIL",0,E60="NIL",0,AND(D60=$A$138,C60=$F$135),SUM(($F$136-G60)*F60,$G$138*F60), AND(D60=$A$138,C60=$B$135),SUM(($B$136-G60)*F60,$H$138*F60),AND(D60=$A$138,C60=$C$135),SUM(($C$136-G60)*F60,$I$138*F60),AND(D60=$A$139,C60=$F$135),SUM(($F$136-G60)*F60,$G$139*F60), AND(D60=$A$139,C60=$B$135),SUM(($B$136-G60)*F60,$H$139*F60),AND(D60=$A$139,C60=$C$135),SUM(($C$136-G60)*F60,$I$139*F60),AND(D60=$A$140,C60=$F$135),SUM(($F$136-G60)*F60,$G$140*F60), AND(D60=$A$140,C60=$B$135),SUM(($B$136-G60)*F60,$H$140*F60),AND(D60=$A$140,C60=$C$135),SUM(($C$136-G60)*F60,$I$140*F60),AND(D60=$A$141,C60=$F$135),SUM(($F$136-G60)*F60,$G$141*F60), AND(D60=$A$141,C60=$B$135),SUM(($B$136-G60)*F60,$H$141*F60),AND(D60=$A$141,C60=$C$135),SUM(($C$136-G60)*F60,$I$141*F60)),"") -> 0 | K60: =IFERROR(IFS(D60=E60,H60+J60,D60<>E60,J60),0) -> 0
C61: NIL | D61: NIL | E61: NIL | G61: =IF(OR(A61="NIL", C61="NIL", D61="NIL", E61="NIL"), 0, INDEX($B$136:$F$152, MATCH(E61, $A$136:$A$152, 0), MATCH(C61, $B$135:$F$135, 0))) -> 0 | H61: =G61*F61 -> 0 | J61: =IFERROR(IFS(A61="NIL",0,C61="NIL",0,D61="NIL",0,E61="NIL",0,AND(D61=$A$138,C61=$F$135),SUM(($F$136-G61)*F61,$G$138*F61), AND(D61=$A$138,C61=$B$135),SUM(($B$136-G61)*F61,$H$138*F61),AND(D61=$A$138,C61=$C$135),SUM(($C$136-G61)*F61,$I$138*F61),AND(D61=$A$139,C61=$F$135),SUM(($F$136-G61)*F61,$G$139*F61), AND(D61=$A$139,C61=$B$135),SUM(($B$136-G61)*F61,$H$139*F61),AND(D61=$A$139,C61=$C$135),SUM(($C$136-G61)*F61,$I$139*F61),AND(D61=$A$140,C61=$F$135),SUM(($F$136-G61)*F61,$G$140*F61), AND(D61=$A$140,C61=$B$135),SUM(($B$136-G61)*F61,$H$140*F61),AND(D61=$A$140,C61=$C$135),SUM(($C$136-G61)*F61,$I$140*F61),AND(D61=$A$141,C61=$F$135),SUM(($F$136-G61)*F61,$G$141*F61), AND(D61=$A$141,C61=$B$135),SUM(($B$136-G61)*F61,$H$141*F61),AND(D61=$A$141,C61=$C$135),SUM(($C$136-G61)*F61,$I$141*F61)),"") -> 0 | K61: =IFERROR(IFS(D61=E61,H61+J61,D61<>E61,J61),0) -> 0
C62: NIL | D62: NIL | E62: NIL | G62: =IF(OR(A62="NIL", C62="NIL", D62="NIL", E62="NIL"), 0, INDEX($B$136:$F$152, MATCH(E62, $A$136:$A$152, 0), MATCH(C62, $B$135:$F$135, 0))) -> 0 | H62: =G62*F62 -> 0 | J62: =IFERROR(IFS(A62="NIL",0,C62="NIL",0,D62="NIL",0,E62="NIL",0,AND(D62=$A$138,C62=$F$135),SUM(($F$136-G62)*F62,$G$138*F62), AND(D62=$A$138,C62=$B$135),SUM(($B$136-G62)*F62,$H$138*F62),AND(D62=$A$138,C62=$C$135),SUM(($C$136-G62)*F62,$I$138*F62),AND(D62=$A$139,C62=$F$135),SUM(($F$136-G62)*F62,$G$139*F62), AND(D62=$A$139,C62=$B$135),SUM(($B$136-G62)*F62,$H$139*F62),AND(D62=$A$139,C62=$C$135),SUM(($C$136-G62)*F62,$I$139*F62),AND(D62=$A$140,C62=$F$135),SUM(($F$136-G62)*F62,$G$140*F62), AND(D62=$A$140,C62=$B$135),SUM(($B$136-G62)*F62,$H$140*F62),AND(D62=$A$140,C62=$C$135),SUM(($C$136-G62)*F62,$I$140*F62),AND(D62=$A$141,C62=$F$135),SUM(($F$136-G62)*F62,$G$141*F62), AND(D62=$A$141,C62=$B$135),SUM(($B$136-G62)*F62,$H$141*F62),AND(D62=$A$141,C62=$C$135),SUM(($C$136-G62)*F62,$I$141*F62)),"") -> 0 | K62: =IFERROR(IFS(D62=E62,H62+J62,D62<>E62,J62),0) -> 0
C63: NIL | D63: NIL | E63: NIL | G63: =IF(OR(A63="NIL", C63="NIL", D63="NIL", E63="NIL"), 0, INDEX($B$136:$F$152, MATCH(E63, $A$136:$A$152, 0), MATCH(C63, $B$135:$F$135, 0))) -> 0 | H63: =G63*F63 -> 0 | J63: =IFERROR(IFS(A63="NIL",0,C63="NIL",0,D63="NIL",0,E63="NIL",0,AND(D63=$A$138,C63=$F$135),SUM(($F$136-G63)*F63,$G$138*F63), AND(D63=$A$138,C63=$B$135),SUM(($B$136-G63)*F63,$H$138*F63),AND(D63=$A$138,C63=$C$135),SUM(($C$136-G63)*F63,$I$138*F63),AND(D63=$A$139,C63=$F$135),SUM(($F$136-G63)*F63,$G$139*F63), AND(D63=$A$139,C63=$B$135),SUM(($B$136-G63)*F63,$H$139*F63),AND(D63=$A$139,C63=$C$135),SUM(($C$136-G63)*F63,$I$139*F63),AND(D63=$A$140,C63=$F$135),SUM(($F$136-G63)*F63,$G$140*F63), AND(D63=$A$140,C63=$B$135),SUM(($B$136-G63)*F63,$H$140*F63),AND(D63=$A$140,C63=$C$135),SUM(($C$136-G63)*F63,$I$140*F63),AND(D63=$A$141,C63=$F$135),SUM(($F$136-G63)*F63,$G$141*F63), AND(D63=$A$141,C63=$B$135),SUM(($B$136-G63)*F63,$H$141*F63),AND(D63=$A$141,C63=$C$135),SUM(($C$136-G63)*F63,$I$141*F63)),"") -> 0 | K63: =IFERROR(IFS(D63=E63,H63+J63,D63<>E63,J63),0) -> 0
C64: NIL | D64: NIL | E64: NIL | G64: =IF(OR(A64="NIL", C64="NIL", D64="NIL", E64="NIL"), 0, INDEX($B$136:$F$152, MATCH(E64, $A$136:$A$152, 0), MATCH(C64, $B$135:$F$135, 0))) -> 0 | H64: =G64*F64 -> 0 | J64: =IFERROR(IFS(A64="NIL",0,C64="NIL",0,D64="NIL",0,E64="NIL",0,AND(D64=$A$138,C64=$F$135),SUM(($F$136-G64)*F64,$G$138*F64), AND(D64=$A$138,C64=$B$135),SUM(($B$136-G64)*F64,$H$138*F64),AND(D64=$A$138,C64=$C$135),SUM(($C$136-G64)*F64,$I$138*F64),AND(D64=$A$139,C64=$F$135),SUM(($F$136-G64)*F64,$G$139*F64), AND(D64=$A$139,C64=$B$135),SUM(($B$136-G64)*F64,$H$139*F64),AND(D64=$A$139,C64=$C$135),SUM(($C$136-G64)*F64,$I$139*F64),AND(D64=$A$140,C64=$F$135),SUM(($F$136-G64)*F64,$G$140*F64), AND(D64=$A$140,C64=$B$135),SUM(($B$136-G64)*F64,$H$140*F64),AND(D64=$A$140,C64=$C$135),SUM(($C$136-G64)*F64,$I$140*F64),AND(D64=$A$141,C64=$F$135),SUM(($F$136-G64)*F64,$G$141*F64), AND(D64=$A$141,C64=$B$135),SUM(($B$136-G64)*F64,$H$141*F64),AND(D64=$A$141,C64=$C$135),SUM(($C$136-G64)*F64,$I$141*F64)),"") -> 0 | K64: =IFERROR(IFS(D64=E64,H64+J64,D64<>E64,J64),0) -> 0
C65: NIL | D65: NIL | E65: NIL | G65: =IF(OR(A65="NIL", C65="NIL", D65="NIL", E65="NIL"), 0, INDEX($B$136:$F$152, MATCH(E65, $A$136:$A$152, 0), MATCH(C65, $B$135:$F$135, 0))) -> 0 | H65: =G65*F65 -> 0 | J65: =IFERROR(IFS(A65="NIL",0,C65="NIL",0,D65="NIL",0,E65="NIL",0,AND(D65=$A$138,C65=$F$135),SUM(($F$136-G65)*F65,$G$138*F65), AND(D65=$A$138,C65=$B$135),SUM(($B$136-G65)*F65,$H$138*F65),AND(D65=$A$138,C65=$C$135),SUM(($C$136-G65)*F65,$I$138*F65),AND(D65=$A$139,C65=$F$135),SUM(($F$136-G65)*F65,$G$139*F65), AND(D65=$A$139,C65=$B$135),SUM(($B$136-G65)*F65,$H$139*F65),AND(D65=$A$139,C65=$C$135),SUM(($C$136-G65)*F65,$I$139*F65),AND(D65=$A$140,C65=$F$135),SUM(($F$136-G65)*F65,$G$140*F65), AND(D65=$A$140,C65=$B$135),SUM(($B$136-G65)*F65,$H$140*F65),AND(D65=$A$140,C65=$C$135),SUM(($C$136-G65)*F65,$I$140*F65),AND(D65=$A$141,C65=$F$135),SUM(($F$136-G65)*F65,$G$141*F65), AND(D65=$A$141,C65=$B$135),SUM(($B$136-G65)*F65,$H$141*F65),AND(D65=$A$141,C65=$C$135),SUM(($C$136-G65)*F65,$I$141*F65)),"") -> 0 | K65: =IFERROR(IFS(D65=E65,H65+J65,D65<>E65,J65),0) -> 0
A66: NIL | C66: NIL | D66: NIL | E66: NIL | G66: =IF(OR(A66="NIL", C66="NIL", D66="NIL", E66="NIL"), 0, INDEX($B$136:$F$152, MATCH(E66, $A$136:$A$152, 0), MATCH(C66, $B$135:$F$135, 0))) -> 0 | H66: =G66*F66 -> 0 | J66: =IFERROR(IFS(A66="NIL",0,C66="NIL",0,D66="NIL",0,E66="NIL",0,AND(D66=$A$138,C66=$F$135),SUM(($F$136-G66)*F66,$G$138*F66), AND(D66=$A$138,C66=$B$135),SUM(($B$136-G66)*F66,$H$138*F66),AND(D66=$A$138,C66=$C$135),SUM(($C$136-G66)*F66,$I$138*F66),AND(D66=$A$139,C66=$F$135),SUM(($F$136-G66)*F66,$G$139*F66), AND(D66=$A$139,C66=$B$135),SUM(($B$136-G66)*F66,$H$139*F66),AND(D66=$A$139,C66=$C$135),SUM(($C$136-G66)*F66,$I$139*F66),AND(D66=$A$140,C66=$F$135),SUM(($F$136-G66)*F66,$G$140*F66), AND(D66=$A$140,C66=$B$135),SUM(($B$136-G66)*F66,$H$140*F66),AND(D66=$A$140,C66=$C$135),SUM(($C$136-G66)*F66,$I$140*F66),AND(D66=$A$141,C66=$F$135),SUM(($F$136-G66)*F66,$G$141*F66), AND(D66=$A$141,C66=$B$135),SUM(($B$136-G66)*F66,$H$141*F66),AND(D66=$A$141,C66=$C$135),SUM(($C$136-G66)*F66,$I$141*F66)),"") -> 0 | K66: =IFERROR(IFS(D66=E66,H66+J66,D66<>E66,J66),0) -> 0 | L66: =SUM(VLOOKUP(A66,$A$165:$C$178,2,False)*25%,VLOOKUP(A66,$A$165:$C$178,3,False)*25%) -> #N/A
C67: NIL | D67: NIL | E67: NIL | G67: =IF(OR(A67="NIL", C67="NIL", D67="NIL", E67="NIL"), 0, INDEX($B$136:$F$152, MATCH(E67, $A$136:$A$152, 0), MATCH(C67, $B$135:$F$135, 0))) -> 0 | H67: =G67*F67 -> 0 | J67: =IFERROR(IFS(A67="NIL",0,C67="NIL",0,D67="NIL",0,E67="NIL",0,AND(D67=$A$138,C67=$F$135),SUM(($F$136-G67)*F67,$G$138*F67), AND(D67=$A$138,C67=$B$135),SUM(($B$136-G67)*F67,$H$138*F67),AND(D67=$A$138,C67=$C$135),SUM(($C$136-G67)*F67,$I$138*F67),AND(D67=$A$139,C67=$F$135),SUM(($F$136-G67)*F67,$G$139*F67), AND(D67=$A$139,C67=$B$135),SUM(($B$136-G67)*F67,$H$139*F67),AND(D67=$A$139,C67=$C$135),SUM(($C$136-G67)*F67,$I$139*F67),AND(D67=$A$140,C67=$F$135),SUM(($F$136-G67)*F67,$G$140*F67), AND(D67=$A$140,C67=$B$135),SUM(($B$136-G67)*F67,$H$140*F67),AND(D67=$A$140,C67=$C$135),SUM(($C$136-G67)*F67,$I$140*F67),AND(D67=$A$141,C67=$F$135),SUM(($F$136-G67)*F67,$G$141*F67), AND(D67=$A$141,C67=$B$135),SUM(($B$136-G67)*F67,$H$141*F67),AND(D67=$A$141,C67=$C$135),SUM(($C$136-G67)*F67,$I$141*F67)),"") -> 0 | K67: =IFERROR(IFS(D67=E67,H67+J67,D67<>E67,J67),0) -> 0
C68: NIL | D68: NIL | E68: NIL | G68: =IF(OR(A68="NIL", C68="NIL", D68="NIL", E68="NIL"), 0, INDEX($B$136:$F$152, MATCH(E68, $A$136:$A$152, 0), MATCH(C68, $B$135:$F$135, 0))) -> 0 | H68: =G68*F68 -> 0 | J68: =IFERROR(IFS(A68="NIL",0,C68="NIL",0,D68="NIL",0,E68="NIL",0,AND(D68=$A$138,C68=$F$135),SUM(($F$136-G68)*F68,$G$138*F68), AND(D68=$A$138,C68=$B$135),SUM(($B$136-G68)*F68,$H$138*F68),AND(D68=$A$138,C68=$C$135),SUM(($C$136-G68)*F68,$I$138*F68),AND(D68=$A$139,C68=$F$135),SUM(($F$136-G68)*F68,$G$139*F68), AND(D68=$A$139,C68=$B$135),SUM(($B$136-G68)*F68,$H$139*F68),AND(D68=$A$139,C68=$C$135),SUM(($C$136-G68)*F68,$I$139*F68),AND(D68=$A$140,C68=$F$135),SUM(($F$136-G68)*F68,$G$140*F68), AND(D68=$A$140,C68=$B$135),SUM(($B$136-G68)*F68,$H$140*F68),AND(D68=$A$140,C68=$C$135),SUM(($C$136-G68)*F68,$I$140*F68),AND(D68=$A$141,C68=$F$135),SUM(($F$136-G68)*F68,$G$141*F68), AND(D68=$A$141,C68=$B$135),SUM(($B$136-G68)*F68,$H$141*F68),AND(D68=$A$141,C68=$C$135),SUM(($C$136-G68)*F68,$I$141*F68)),"") -> 0 | K68: =IFERROR(IFS(D68=E68,H68+J68,D68<>E68,J68),0) -> 0
C69: NIL | D69: NIL | E69: NIL | G69: =IF(OR(A69="NIL", C69="NIL", D69="NIL", E69="NIL"), 0, INDEX($B$136:$F$152, MATCH(E69, $A$136:$A$152, 0), MATCH(C69, $B$135:$F$135, 0))) -> 0 | H69: =G69*F69 -> 0 | J69: =IFERROR(IFS(A69="NIL",0,C69="NIL",0,D69="NIL",0,E69="NIL",0,AND(D69=$A$138,C69=$F$135),SUM(($F$136-G69)*F69,$G$138*F69), AND(D69=$A$138,C69=$B$135),SUM(($B$136-G69)*F69,$H$138*F69),AND(D69=$A$138,C69=$C$135),SUM(($C$136-G69)*F69,$I$138*F69),AND(D69=$A$139,C69=$F$135),SUM(($F$136-G69)*F69,$G$139*F69), AND(D69=$A$139,C69=$B$135),SUM(($B$136-G69)*F69,$H$139*F69),AND(D69=$A$139,C69=$C$135),SUM(($C$136-G69)*F69,$I$139*F69),AND(D69=$A$140,C69=$F$135),SUM(($F$136-G69)*F69,$G$140*F69), AND(D69=$A$140,C69=$B$135),SUM(($B$136-G69)*F69,$H$140*F69),AND(D69=$A$140,C69=$C$135),SUM(($C$136-G69)*F69,$I$140*F69),AND(D69=$A$141,C69=$F$135),SUM(($F$136-G69)*F69,$G$141*F69), AND(D69=$A$141,C69=$B$135),SUM(($B$136-G69)*F69,$H$141*F69),AND(D69=$A$141,C69=$C$135),SUM(($C$136-G69)*F69,$I$141*F69)),"") -> 0 | K69: =IFERROR(IFS(D69=E69,H69+J69,D69<>E69,J69),0) -> 0
C70: NIL | D70: NIL | E70: NIL | G70: =IF(OR(A70="NIL", C70="NIL", D70="NIL", E70="NIL"), 0, INDEX($B$136:$F$152, MATCH(E70, $A$136:$A$152, 0), MATCH(C70, $B$135:$F$135, 0))) -> 0 | H70: =G70*F70 -> 0 | J70: =IFERROR(IFS(A70="NIL",0,C70="NIL",0,D70="NIL",0,E70="NIL",0,AND(D70=$A$138,C70=$F$135),SUM(($F$136-G70)*F70,$G$138*F70), AND(D70=$A$138,C70=$B$135),SUM(($B$136-G70)*F70,$H$138*F70),AND(D70=$A$138,C70=$C$135),SUM(($C$136-G70)*F70,$I$138*F70),AND(D70=$A$139,C70=$F$135),SUM(($F$136-G70)*F70,$G$139*F70), AND(D70=$A$139,C70=$B$135),SUM(($B$136-G70)*F70,$H$139*F70),AND(D70=$A$139,C70=$C$135),SUM(($C$136-G70)*F70,$I$139*F70),AND(D70=$A$140,C70=$F$135),SUM(($F$136-G70)*F70,$G$140*F70), AND(D70=$A$140,C70=$B$135),SUM(($B$136-G70)*F70,$H$140*F70),AND(D70=$A$140,C70=$C$135),SUM(($C$136-G70)*F70,$I$140*F70),AND(D70=$A$141,C70=$F$135),SUM(($F$136-G70)*F70,$G$141*F70), AND(D70=$A$141,C70=$B$135),SUM(($B$136-G70)*F70,$H$141*F70),AND(D70=$A$141,C70=$C$135),SUM(($C$136-G70)*F70,$I$141*F70)),"") -> 0 | K70: =IFERROR(IFS(D70=E70,H70+J70,D70<>E70,J70),0) -> 0
C71: NIL | D71: NIL | E71: NIL | G71: =IF(OR(A71="NIL", C71="NIL", D71="NIL", E71="NIL"), 0, INDEX($B$136:$F$152, MATCH(E71, $A$136:$A$152, 0), MATCH(C71, $B$135:$F$135, 0))) -> 0 | H71: =G71*F71 -> 0 | J71: =IFERROR(IFS(A71="NIL",0,C71="NIL",0,D71="NIL",0,E71="NIL",0,AND(D71=$A$138,C71=$F$135),SUM(($F$136-G71)*F71,$G$138*F71), AND(D71=$A$138,C71=$B$135),SUM(($B$136-G71)*F71,$H$138*F71),AND(D71=$A$138,C71=$C$135),SUM(($C$136-G71)*F71,$I$138*F71),AND(D71=$A$139,C71=$F$135),SUM(($F$136-G71)*F71,$G$139*F71), AND(D71=$A$139,C71=$B$135),SUM(($B$136-G71)*F71,$H$139*F71),AND(D71=$A$139,C71=$C$135),SUM(($C$136-G71)*F71,$I$139*F71),AND(D71=$A$140,C71=$F$135),SUM(($F$136-G71)*F71,$G$140*F71), AND(D71=$A$140,C71=$B$135),SUM(($B$136-G71)*F71,$H$140*F71),AND(D71=$A$140,C71=$C$135),SUM(($C$136-G71)*F71,$I$140*F71),AND(D71=$A$141,C71=$F$135),SUM(($F$136-G71)*F71,$G$141*F71), AND(D71=$A$141,C71=$B$135),SUM(($B$136-G71)*F71,$H$141*F71),AND(D71=$A$141,C71=$C$135),SUM(($C$136-G71)*F71,$I$141*F71)),"") -> 0 | K71: =IFERROR(IFS(D71=E71,H71+J71,D71<>E71,J71),0) -> 0
C72: NIL | D72: NIL | E72: NIL | G72: =IF(OR(A72="NIL", C72="NIL", D72="NIL", E72="NIL"), 0, INDEX($B$136:$F$152, MATCH(E72, $A$136:$A$152, 0), MATCH(C72, $B$135:$F$135, 0))) -> 0 | H72: =G72*F72 -> 0 | J72: =IFERROR(IFS(A72="NIL",0,C72="NIL",0,D72="NIL",0,E72="NIL",0,AND(D72=$A$138,C72=$F$135),SUM(($F$136-G72)*F72,$G$138*F72), AND(D72=$A$138,C72=$B$135),SUM(($B$136-G72)*F72,$H$138*F72),AND(D72=$A$138,C72=$C$135),SUM(($C$136-G72)*F72,$I$138*F72),AND(D72=$A$139,C72=$F$135),SUM(($F$136-G72)*F72,$G$139*F72), AND(D72=$A$139,C72=$B$135),SUM(($B$136-G72)*F72,$H$139*F72),AND(D72=$A$139,C72=$C$135),SUM(($C$136-G72)*F72,$I$139*F72),AND(D72=$A$140,C72=$F$135),SUM(($F$136-G72)*F72,$G$140*F72), AND(D72=$A$140,C72=$B$135),SUM(($B$136-G72)*F72,$H$140*F72),AND(D72=$A$140,C72=$C$135),SUM(($C$136-G72)*F72,$I$140*F72),AND(D72=$A$141,C72=$F$135),SUM(($F$136-G72)*F72,$G$141*F72), AND(D72=$A$141,C72=$B$135),SUM(($B$136-G72)*F72,$H$141*F72),AND(D72=$A$141,C72=$C$135),SUM(($C$136-G72)*F72,$I$141*F72)),"") -> 0 | K72: =IFERROR(IFS(D72=E72,H72+J72,D72<>E72,J72),0) -> 0
C73: NIL | D73: NIL | E73: NIL | G73: =IF(OR(A73="NIL", C73="NIL", D73="NIL", E73="NIL"), 0, INDEX($B$136:$F$152, MATCH(E73, $A$136:$A$152, 0), MATCH(C73, $B$135:$F$135, 0))) -> 0 | H73: =G73*F73 -> 0 | J73: =IFERROR(IFS(A73="NIL",0,C73="NIL",0,D73="NIL",0,E73="NIL",0,AND(D73=$A$138,C73=$F$135),SUM(($F$136-G73)*F73,$G$138*F73), AND(D73=$A$138,C73=$B$135),SUM(($B$136-G73)*F73,$H$138*F73),AND(D73=$A$138,C73=$C$135),SUM(($C$136-G73)*F73,$I$138*F73),AND(D73=$A$139,C73=$F$135),SUM(($F$136-G73)*F73,$G$139*F73), AND(D73=$A$139,C73=$B$135),SUM(($B$136-G73)*F73,$H$139*F73),AND(D73=$A$139,C73=$C$135),SUM(($C$136-G73)*F73,$I$139*F73),AND(D73=$A$140,C73=$F$135),SUM(($F$136-G73)*F73,$G$140*F73), AND(D73=$A$140,C73=$B$135),SUM(($B$136-G73)*F73,$H$140*F73),AND(D73=$A$140,C73=$C$135),SUM(($C$136-G73)*F73,$I$140*F73),AND(D73=$A$141,C73=$F$135),SUM(($F$136-G73)*F73,$G$141*F73), AND(D73=$A$141,C73=$B$135),SUM(($B$136-G73)*F73,$H$141*F73),AND(D73=$A$141,C73=$C$135),SUM(($C$136-G73)*F73,$I$141*F73)),"") -> 0 | K73: =IFERROR(IFS(D73=E73,H73+J73,D73<>E73,J73),0) -> 0
C74: NIL | D74: NIL | E74: NIL | G74: =IF(OR(A74="NIL", C74="NIL", D74="NIL", E74="NIL"), 0, INDEX($B$136:$F$152, MATCH(E74, $A$136:$A$152, 0), MATCH(C74, $B$135:$F$135, 0))) -> 0 | H74: =G74*F74 -> 0 | J74: =IFERROR(IFS(A74="NIL",0,C74="NIL",0,D74="NIL",0,E74="NIL",0,AND(D74=$A$138,C74=$F$135),SUM(($F$136-G74)*F74,$G$138*F74), AND(D74=$A$138,C74=$B$135),SUM(($B$136-G74)*F74,$H$138*F74),AND(D74=$A$138,C74=$C$135),SUM(($C$136-G74)*F74,$I$138*F74),AND(D74=$A$139,C74=$F$135),SUM(($F$136-G74)*F74,$G$139*F74), AND(D74=$A$139,C74=$B$135),SUM(($B$136-G74)*F74,$H$139*F74),AND(D74=$A$139,C74=$C$135),SUM(($C$136-G74)*F74,$I$139*F74),AND(D74=$A$140,C74=$F$135),SUM(($F$136-G74)*F74,$G$140*F74), AND(D74=$A$140,C74=$B$135),SUM(($B$136-G74)*F74,$H$140*F74),AND(D74=$A$140,C74=$C$135),SUM(($C$136-G74)*F74,$I$140*F74),AND(D74=$A$141,C74=$F$135),SUM(($F$136-G74)*F74,$G$141*F74), AND(D74=$A$141,C74=$B$135),SUM(($B$136-G74)*F74,$H$141*F74),AND(D74=$A$141,C74=$C$135),SUM(($C$136-G74)*F74,$I$141*F74)),"") -> 0 | K74: =IFERROR(IFS(D74=E74,H74+J74,D74<>E74,J74),0) -> 0
C75: NIL | D75: NIL | E75: NIL | G75: =IF(OR(A75="NIL", C75="NIL", D75="NIL", E75="NIL"), 0, INDEX($B$136:$F$152, MATCH(E75, $A$136:$A$152, 0), MATCH(C75, $B$135:$F$135, 0))) -> 0 | H75: =G75*F75 -> 0 | J75: =IFERROR(IFS(A75="NIL",0,C75="NIL",0,D75="NIL",0,E75="NIL",0,AND(D75=$A$138,C75=$F$135),SUM(($F$136-G75)*F75,$G$138*F75), AND(D75=$A$138,C75=$B$135),SUM(($B$136-G75)*F75,$H$138*F75),AND(D75=$A$138,C75=$C$135),SUM(($C$136-G75)*F75,$I$138*F75),AND(D75=$A$139,C75=$F$135),SUM(($F$136-G75)*F75,$G$139*F75), AND(D75=$A$139,C75=$B$135),SUM(($B$136-G75)*F75,$H$139*F75),AND(D75=$A$139,C75=$C$135),SUM(($C$136-G75)*F75,$I$139*F75),AND(D75=$A$140,C75=$F$135),SUM(($F$136-G75)*F75,$G$140*F75), AND(D75=$A$140,C75=$B$135),SUM(($B$136-G75)*F75,$H$140*F75),AND(D75=$A$140,C75=$C$135),SUM(($C$136-G75)*F75,$I$140*F75),AND(D75=$A$141,C75=$F$135),SUM(($F$136-G75)*F75,$G$141*F75), AND(D75=$A$141,C75=$B$135),SUM(($B$136-G75)*F75,$H$141*F75),AND(D75=$A$141,C75=$C$135),SUM(($C$136-G75)*F75,$I$141*F75)),"") -> 0 | K75: =IFERROR(IFS(D75=E75,H75+J75,D75<>E75,J75),0) -> 0
C76: NIL | D76: NIL | E76: NIL | G76: =IF(OR(A76="NIL", C76="NIL", D76="NIL", E76="NIL"), 0, INDEX($B$136:$F$152, MATCH(E76, $A$136:$A$152, 0), MATCH(C76, $B$135:$F$135, 0))) -> 0 | H76: =G76*F76 -> 0 | J76: =IFERROR(IFS(A76="NIL",0,C76="NIL",0,D76="NIL",0,E76="NIL",0,AND(D76=$A$138,C76=$F$135),SUM(($F$136-G76)*F76,$G$138*F76), AND(D76=$A$138,C76=$B$135),SUM(($B$136-G76)*F76,$H$138*F76),AND(D76=$A$138,C76=$C$135),SUM(($C$136-G76)*F76,$I$138*F76),AND(D76=$A$139,C76=$F$135),SUM(($F$136-G76)*F76,$G$139*F76), AND(D76=$A$139,C76=$B$135),SUM(($B$136-G76)*F76,$H$139*F76),AND(D76=$A$139,C76=$C$135),SUM(($C$136-G76)*F76,$I$139*F76),AND(D76=$A$140,C76=$F$135),SUM(($F$136-G76)*F76,$G$140*F76), AND(D76=$A$140,C76=$B$135),SUM(($B$136-G76)*F76,$H$140*F76),AND(D76=$A$140,C76=$C$135),SUM(($C$136-G76)*F76,$I$140*F76),AND(D76=$A$141,C76=$F$135),SUM(($F$136-G76)*F76,$G$141*F76), AND(D76=$A$141,C76=$B$135),SUM(($B$136-G76)*F76,$H$141*F76),AND(D76=$A$141,C76=$C$135),SUM(($C$136-G76)*F76,$I$141*F76)),"") -> 0 | K76: =IFERROR(IFS(D76=E76,H76+J76,D76<>E76,J76),0) -> 0
C77: NIL | D77: NIL | E77: NIL | G77: =IF(OR(A77="NIL", C77="NIL", D77="NIL", E77="NIL"), 0, INDEX($B$136:$F$152, MATCH(E77, $A$136:$A$152, 0), MATCH(C77, $B$135:$F$135, 0))) -> 0 | H77: =G77*F77 -> 0 | J77: =IFERROR(IFS(A77="NIL",0,C77="NIL",0,D77="NIL",0,E77="NIL",0,AND(D77=$A$138,C77=$F$135),SUM(($F$136-G77)*F77,$G$138*F77), AND(D77=$A$138,C77=$B$135),SUM(($B$136-G77)*F77,$H$138*F77),AND(D77=$A$138,C77=$C$135),SUM(($C$136-G77)*F77,$I$138*F77),AND(D77=$A$139,C77=$F$135),SUM(($F$136-G77)*F77,$G$139*F77), AND(D77=$A$139,C77=$B$135),SUM(($B$136-G77)*F77,$H$139*F77),AND(D77=$A$139,C77=$C$135),SUM(($C$136-G77)*F77,$I$139*F77),AND(D77=$A$140,C77=$F$135),SUM(($F$136-G77)*F77,$G$140*F77), AND(D77=$A$140,C77=$B$135),SUM(($B$136-G77)*F77,$H$140*F77),AND(D77=$A$140,C77=$C$135),SUM(($C$136-G77)*F77,$I$140*F77),AND(D77=$A$141,C77=$F$135),SUM(($F$136-G77)*F77,$G$141*F77), AND(D77=$A$141,C77=$B$135),SUM(($B$136-G77)*F77,$H$141*F77),AND(D77=$A$141,C77=$C$135),SUM(($C$136-G77)*F77,$I$141*F77)),"") -> 0 | K77: =IFERROR(IFS(D77=E77,H77+J77,D77<>E77,J77),0) -> 0
C78: NIL | D78: NIL | E78: NIL | G78: =IF(OR(A78="NIL", C78="NIL", D78="NIL", E78="NIL"), 0, INDEX($B$136:$F$152, MATCH(E78, $A$136:$A$152, 0), MATCH(C78, $B$135:$F$135, 0))) -> 0 | H78: =G78*F78 -> 0 | J78: =IFERROR(IFS(A78="NIL",0,C78="NIL",0,D78="NIL",0,E78="NIL",0,AND(D78=$A$138,C78=$F$135),SUM(($F$136-G78)*F78,$G$138*F78), AND(D78=$A$138,C78=$B$135),SUM(($B$136-G78)*F78,$H$138*F78),AND(D78=$A$138,C78=$C$135),SUM(($C$136-G78)*F78,$I$138*F78),AND(D78=$A$139,C78=$F$135),SUM(($F$136-G78)*F78,$G$139*F78), AND(D78=$A$139,C78=$B$135),SUM(($B$136-G78)*F78,$H$139*F78),AND(D78=$A$139,C78=$C$135),SUM(($C$136-G78)*F78,$I$139*F78),AND(D78=$A$140,C78=$F$135),SUM(($F$136-G78)*F78,$G$140*F78), AND(D78=$A$140,C78=$B$135),SUM(($B$136-G78)*F78,$H$140*F78),AND(D78=$A$140,C78=$C$135),SUM(($C$136-G78)*F78,$I$140*F78),AND(D78=$A$141,C78=$F$135),SUM(($F$136-G78)*F78,$G$141*F78), AND(D78=$A$141,C78=$B$135),SUM(($B$136-G78)*F78,$H$141*F78),AND(D78=$A$141,C78=$C$135),SUM(($C$136-G78)*F78,$I$141*F78)),"") -> 0 | K78: =IFERROR(IFS(D78=E78,H78+J78,D78<>E78,J78),0) -> 0
A79: NIL | C79: NIL | D79: NIL | E79: NIL | G79: =IF(OR(A79="NIL", C79="NIL", D79="NIL", E79="NIL"), 0, INDEX($B$136:$F$152, MATCH(E79, $A$136:$A$152, 0), MATCH(C79, $B$135:$F$135, 0))) -> 0 | H79: =G79*F79 -> 0 | J79: =IFERROR(IFS(A79="NIL",0,C79="NIL",0,D79="NIL",0,E79="NIL",0,AND(D79=$A$138,C79=$F$135),SUM(($F$136-G79)*F79,$G$138*F79), AND(D79=$A$138,C79=$B$135),SUM(($B$136-G79)*F79,$H$138*F79),AND(D79=$A$138,C79=$C$135),SUM(($C$136-G79)*F79,$I$138*F79),AND(D79=$A$139,C79=$F$135),SUM(($F$136-G79)*F79,$G$139*F79), AND(D79=$A$139,C79=$B$135),SUM(($B$136-G79)*F79,$H$139*F79),AND(D79=$A$139,C79=$C$135),SUM(($C$136-G79)*F79,$I$139*F79),AND(D79=$A$140,C79=$F$135),SUM(($F$136-G79)*F79,$G$140*F79), AND(D79=$A$140,C79=$B$135),SUM(($B$136-G79)*F79,$H$140*F79),AND(D79=$A$140,C79=$C$135),SUM(($C$136-G79)*F79,$I$140*F79),AND(D79=$A$141,C79=$F$135),SUM(($F$136-G79)*F79,$G$141*F79), AND(D79=$A$141,C79=$B$135),SUM(($B$136-G79)*F79,$H$141*F79),AND(D79=$A$141,C79=$C$135),SUM(($C$136-G79)*F79,$I$141*F79)),"") -> 0 | K79: =IFERROR(IFS(D79=E79,H79+J79,D79<>E79,J79),0) -> 0 | L79: =SUM(VLOOKUP(A79,$A$165:$C$178,2,False)*25%,VLOOKUP(A79,$A$165:$C$178,3,False)*25%) -> #N/A
C80: NIL | D80: NIL | E80: NIL | G80: =IF(OR(A80="NIL", C80="NIL", D80="NIL", E80="NIL"), 0, INDEX($B$136:$F$152, MATCH(E80, $A$136:$A$152, 0), MATCH(C80, $B$135:$F$135, 0))) -> 0 | H80: =G80*F80 -> 0 | J80: =IFERROR(IFS(A80="NIL",0,C80="NIL",0,D80="NIL",0,E80="NIL",0,AND(D80=$A$138,C80=$F$135),SUM(($F$136-G80)*F80,$G$138*F80), AND(D80=$A$138,C80=$B$135),SUM(($B$136-G80)*F80,$H$138*F80),AND(D80=$A$138,C80=$C$135),SUM(($C$136-G80)*F80,$I$138*F80),AND(D80=$A$139,C80=$F$135),SUM(($F$136-G80)*F80,$G$139*F80), AND(D80=$A$139,C80=$B$135),SUM(($B$136-G80)*F80,$H$139*F80),AND(D80=$A$139,C80=$C$135),SUM(($C$136-G80)*F80,$I$139*F80),AND(D80=$A$140,C80=$F$135),SUM(($F$136-G80)*F80,$G$140*F80), AND(D80=$A$140,C80=$B$135),SUM(($B$136-G80)*F80,$H$140*F80),AND(D80=$A$140,C80=$C$135),SUM(($C$136-G80)*F80,$I$140*F80),AND(D80=$A$141,C80=$F$135),SUM(($F$136-G80)*F80,$G$141*F80), AND(D80=$A$141,C80=$B$135),SUM(($B$136-G80)*F80,$H$141*F80),AND(D80=$A$141,C80=$C$135),SUM(($C$136-G80)*F80,$I$141*F80)),"") -> 0 | K80: =IFERROR(IFS(D80=E80,H80+J80,D80<>E80,J80),0) -> 0
C81: NIL | D81: NIL | E81: NIL | G81: =IF(OR(A81="NIL", C81="NIL", D81="NIL", E81="NIL"), 0, INDEX($B$136:$F$152, MATCH(E81, $A$136:$A$152, 0), MATCH(C81, $B$135:$F$135, 0))) -> 0 | H81: =G81*F81 -> 0 | J81: =IFERROR(IFS(A81="NIL",0,C81="NIL",0,D81="NIL",0,E81="NIL",0,AND(D81=$A$138,C81=$F$135),SUM(($F$136-G81)*F81,$G$138*F81), AND(D81=$A$138,C81=$B$135),SUM(($B$136-G81)*F81,$H$138*F81),AND(D81=$A$138,C81=$C$135),SUM(($C$136-G81)*F81,$I$138*F81),AND(D81=$A$139,C81=$F$135),SUM(($F$136-G81)*F81,$G$139*F81), AND(D81=$A$139,C81=$B$135),SUM(($B$136-G81)*F81,$H$139*F81),AND(D81=$A$139,C81=$C$135),SUM(($C$136-G81)*F81,$I$139*F81),AND(D81=$A$140,C81=$F$135),SUM(($F$136-G81)*F81,$G$140*F81), AND(D81=$A$140,C81=$B$135),SUM(($B$136-G81)*F81,$H$140*F81),AND(D81=$A$140,C81=$C$135),SUM(($C$136-G81)*F81,$I$140*F81),AND(D81=$A$141,C81=$F$135),SUM(($F$136-G81)*F81,$G$141*F81), AND(D81=$A$141,C81=$B$135),SUM(($B$136-G81)*F81,$H$141*F81),AND(D81=$A$141,C81=$C$135),SUM(($C$136-G81)*F81,$I$141*F81)),"") -> 0 | K81: =IFERROR(IFS(D81=E81,H81+J81,D81<>E81,J81),0) -> 0
C82: NIL | D82: NIL | E82: NIL | G82: =IF(OR(A82="NIL", C82="NIL", D82="NIL", E82="NIL"), 0, INDEX($B$136:$F$152, MATCH(E82, $A$136:$A$152, 0), MATCH(C82, $B$135:$F$135, 0))) -> 0 | H82: =G82*F82 -> 0 | J82: =IFERROR(IFS(A82="NIL",0,C82="NIL",0,D82="NIL",0,E82="NIL",0,AND(D82=$A$138,C82=$F$135),SUM(($F$136-G82)*F82,$G$138*F82), AND(D82=$A$138,C82=$B$135),SUM(($B$136-G82)*F82,$H$138*F82),AND(D82=$A$138,C82=$C$135),SUM(($C$136-G82)*F82,$I$138*F82),AND(D82=$A$139,C82=$F$135),SUM(($F$136-G82)*F82,$G$139*F82), AND(D82=$A$139,C82=$B$135),SUM(($B$136-G82)*F82,$H$139*F82),AND(D82=$A$139,C82=$C$135),SUM(($C$136-G82)*F82,$I$139*F82),AND(D82=$A$140,C82=$F$135),SUM(($F$136-G82)*F82,$G$140*F82), AND(D82=$A$140,C82=$B$135),SUM(($B$136-G82)*F82,$H$140*F82),AND(D82=$A$140,C82=$C$135),SUM(($C$136-G82)*F82,$I$140*F82),AND(D82=$A$141,C82=$F$135),SUM(($F$136-G82)*F82,$G$141*F82), AND(D82=$A$141,C82=$B$135),SUM(($B$136-G82)*F82,$H$141*F82),AND(D82=$A$141,C82=$C$135),SUM(($C$136-G82)*F82,$I$141*F82)),"") -> 0 | K82: =IFERROR(IFS(D82=E82,H82+J82,D82<>E82,J82),0) -> 0
C83: NIL | D83: NIL | E83: NIL | G83: =IF(OR(A83="NIL", C83="NIL", D83="NIL", E83="NIL"), 0, INDEX($B$136:$F$152, MATCH(E83, $A$136:$A$152, 0), MATCH(C83, $B$135:$F$135, 0))) -> 0 | H83: =G83*F83 -> 0 | J83: =IFERROR(IFS(A83="NIL",0,C83="NIL",0,D83="NIL",0,E83="NIL",0,AND(D83=$A$138,C83=$F$135),SUM(($F$136-G83)*F83,$G$138*F83), AND(D83=$A$138,C83=$B$135),SUM(($B$136-G83)*F83,$H$138*F83),AND(D83=$A$138,C83=$C$135),SUM(($C$136-G83)*F83,$I$138*F83),AND(D83=$A$139,C83=$F$135),SUM(($F$136-G83)*F83,$G$139*F83), AND(D83=$A$139,C83=$B$135),SUM(($B$136-G83)*F83,$H$139*F83),AND(D83=$A$139,C83=$C$135),SUM(($C$136-G83)*F83,$I$139*F83),AND(D83=$A$140,C83=$F$135),SUM(($F$136-G83)*F83,$G$140*F83), AND(D83=$A$140,C83=$B$135),SUM(($B$136-G83)*F83,$H$140*F83),AND(D83=$A$140,C83=$C$135),SUM(($C$136-G83)*F83,$I$140*F83),AND(D83=$A$141,C83=$F$135),SUM(($F$136-G83)*F83,$G$141*F83), AND(D83=$A$141,C83=$B$135),SUM(($B$136-G83)*F83,$H$141*F83),AND(D83=$A$141,C83=$C$135),SUM(($C$136-G83)*F83,$I$141*F83)),"") -> 0 | K83: =IFERROR(IFS(D83=E83,H83+J83,D83<>E83,J83),0) -> 0
C84: NIL | D84: NIL | E84: NIL | G84: =IF(OR(A84="NIL", C84="NIL", D84="NIL", E84="NIL"), 0, INDEX($B$136:$F$152, MATCH(E84, $A$136:$A$152, 0), MATCH(C84, $B$135:$F$135, 0))) -> 0 | H84: =G84*F84 -> 0 | J84: =IFERROR(IFS(A84="NIL",0,C84="NIL",0,D84="NIL",0,E84="NIL",0,AND(D84=$A$138,C84=$F$135),SUM(($F$136-G84)*F84,$G$138*F84), AND(D84=$A$138,C84=$B$135),SUM(($B$136-G84)*F84,$H$138*F84),AND(D84=$A$138,C84=$C$135),SUM(($C$136-G84)*F84,$I$138*F84),AND(D84=$A$139,C84=$F$135),SUM(($F$136-G84)*F84,$G$139*F84), AND(D84=$A$139,C84=$B$135),SUM(($B$136-G84)*F84,$H$139*F84),AND(D84=$A$139,C84=$C$135),SUM(($C$136-G84)*F84,$I$139*F84),AND(D84=$A$140,C84=$F$135),SUM(($F$136-G84)*F84,$G$140*F84), AND(D84=$A$140,C84=$B$135),SUM(($B$136-G84)*F84,$H$140*F84),AND(D84=$A$140,C84=$C$135),SUM(($C$136-G84)*F84,$I$140*F84),AND(D84=$A$141,C84=$F$135),SUM(($F$136-G84)*F84,$G$141*F84), AND(D84=$A$141,C84=$B$135),SUM(($B$136-G84)*F84,$H$141*F84),AND(D84=$A$141,C84=$C$135),SUM(($C$136-G84)*F84,$I$141*F84)),"") -> 0 | K84: =IFERROR(IFS(D84=E84,H84+J84,D84<>E84,J84),0) -> 0
C85: NIL | D85: NIL | E85: Ram | G85: =IF(OR(A85="NIL", C85="NIL", D85="NIL", E85="NIL"), 0, INDEX($B$136:$F$152, MATCH(E85, $A$136:$A$152, 0), MATCH(C85, $B$135:$F$135, 0))) -> 0 | H85: =G85*F85 -> 0 | J85: =IFERROR(IFS(A85="NIL",0,C85="NIL",0,D85="NIL",0,E85="NIL",0,AND(D85=$A$138,C85=$F$135),SUM(($F$136-G85)*F85,$G$138*F85), AND(D85=$A$138,C85=$B$135),SUM(($B$136-G85)*F85,$H$138*F85),AND(D85=$A$138,C85=$C$135),SUM(($C$136-G85)*F85,$I$138*F85),AND(D85=$A$139,C85=$F$135),SUM(($F$136-G85)*F85,$G$139*F85), AND(D85=$A$139,C85=$B$135),SUM(($B$136-G85)*F85,$H$139*F85),AND(D85=$A$139,C85=$C$135),SUM(($C$136-G85)*F85,$I$139*F85),AND(D85=$A$140,C85=$F$135),SUM(($F$136-G85)*F85,$G$140*F85), AND(D85=$A$140,C85=$B$135),SUM(($B$136-G85)*F85,$H$140*F85),AND(D85=$A$140,C85=$C$135),SUM(($C$136-G85)*F85,$I$140*F85),AND(D85=$A$141,C85=$F$135),SUM(($F$136-G85)*F85,$G$141*F85), AND(D85=$A$141,C85=$B$135),SUM(($B$136-G85)*F85,$H$141*F85),AND(D85=$A$141,C85=$C$135),SUM(($C$136-G85)*F85,$I$141*F85)),"") -> 0 | K85: =IFERROR(IFS(D85=E85,H85+J85,D85<>E85,J85),0) -> 0
C86: NIL | D86: NIL | E86: NIL | G86: =IF(OR(A86="NIL", C86="NIL", D86="NIL", E86="NIL"), 0, INDEX($B$136:$F$152, MATCH(E86, $A$136:$A$152, 0), MATCH(C86, $B$135:$F$135, 0))) -> 0 | H86: =G86*F86 -> 0 | J86: =IFERROR(IFS(A86="NIL",0,C86="NIL",0,D86="NIL",0,E86="NIL",0,AND(D86=$A$138,C86=$F$135),SUM(($F$136-G86)*F86,$G$138*F86), AND(D86=$A$138,C86=$B$135),SUM(($B$136-G86)*F86,$H$138*F86),AND(D86=$A$138,C86=$C$135),SUM(($C$136-G86)*F86,$I$138*F86),AND(D86=$A$139,C86=$F$135),SUM(($F$136-G86)*F86,$G$139*F86), AND(D86=$A$139,C86=$B$135),SUM(($B$136-G86)*F86,$H$139*F86),AND(D86=$A$139,C86=$C$135),SUM(($C$136-G86)*F86,$I$139*F86),AND(D86=$A$140,C86=$F$135),SUM(($F$136-G86)*F86,$G$140*F86), AND(D86=$A$140,C86=$B$135),SUM(($B$136-G86)*F86,$H$140*F86),AND(D86=$A$140,C86=$C$135),SUM(($C$136-G86)*F86,$I$140*F86),AND(D86=$A$141,C86=$F$135),SUM(($F$136-G86)*F86,$G$141*F86), AND(D86=$A$141,C86=$B$135),SUM(($B$136-G86)*F86,$H$141*F86),AND(D86=$A$141,C86=$C$135),SUM(($C$136-G86)*F86,$I$141*F86)),"") -> 0 | K86: =IFERROR(IFS(D86=E86,H86+J86,D86<>E86,J86),0) -> 0
C87: NIL | D87: NIL | E87: NIL | G87: =IF(OR(A87="NIL", C87="NIL", D87="NIL", E87="NIL"), 0, INDEX($B$136:$F$152, MATCH(E87, $A$136:$A$152, 0), MATCH(C87, $B$135:$F$135, 0))) -> 0 | H87: =G87*F87 -> 0 | J87: =IFERROR(IFS(A87="NIL",0,C87="NIL",0,D87="NIL",0,E87="NIL",0,AND(D87=$A$138,C87=$F$135),SUM(($F$136-G87)*F87,$G$138*F87), AND(D87=$A$138,C87=$B$135),SUM(($B$136-G87)*F87,$H$138*F87),AND(D87=$A$138,C87=$C$135),SUM(($C$136-G87)*F87,$I$138*F87),AND(D87=$A$139,C87=$F$135),SUM(($F$136-G87)*F87,$G$139*F87), AND(D87=$A$139,C87=$B$135),SUM(($B$136-G87)*F87,$H$139*F87),AND(D87=$A$139,C87=$C$135),SUM(($C$136-G87)*F87,$I$139*F87),AND(D87=$A$140,C87=$F$135),SUM(($F$136-G87)*F87,$G$140*F87), AND(D87=$A$140,C87=$B$135),SUM(($B$136-G87)*F87,$H$140*F87),AND(D87=$A$140,C87=$C$135),SUM(($C$136-G87)*F87,$I$140*F87),AND(D87=$A$141,C87=$F$135),SUM(($F$136-G87)*F87,$G$141*F87), AND(D87=$A$141,C87=$B$135),SUM(($B$136-G87)*F87,$H$141*F87),AND(D87=$A$141,C87=$C$135),SUM(($C$136-G87)*F87,$I$141*F87)),"") -> 0 | K87: =IFERROR(IFS(D87=E87,H87+J87,D87<>E87,J87),0) -> 0
C88: NIL | D88: NIL | E88: NIL | G88: =IF(OR(A88="NIL", C88="NIL", D88="NIL", E88="NIL"), 0, INDEX($B$136:$F$152, MATCH(E88, $A$136:$A$152, 0), MATCH(C88, $B$135:$F$135, 0))) -> 0 | H88: =G88*F88 -> 0 | J88: =IFERROR(IFS(A88="NIL",0,C88="NIL",0,D88="NIL",0,E88="NIL",0,AND(D88=$A$138,C88=$F$135),SUM(($F$136-G88)*F88,$G$138*F88), AND(D88=$A$138,C88=$B$135),SUM(($B$136-G88)*F88,$H$138*F88),AND(D88=$A$138,C88=$C$135),SUM(($C$136-G88)*F88,$I$138*F88),AND(D88=$A$139,C88=$F$135),SUM(($F$136-G88)*F88,$G$139*F88), AND(D88=$A$139,C88=$B$135),SUM(($B$136-G88)*F88,$H$139*F88),AND(D88=$A$139,C88=$C$135),SUM(($C$136-G88)*F88,$I$139*F88),AND(D88=$A$140,C88=$F$135),SUM(($F$136-G88)*F88,$G$140*F88), AND(D88=$A$140,C88=$B$135),SUM(($B$136-G88)*F88,$H$140*F88),AND(D88=$A$140,C88=$C$135),SUM(($C$136-G88)*F88,$I$140*F88),AND(D88=$A$141,C88=$F$135),SUM(($F$136-G88)*F88,$G$141*F88), AND(D88=$A$141,C88=$B$135),SUM(($B$136-G88)*F88,$H$141*F88),AND(D88=$A$141,C88=$C$135),SUM(($C$136-G88)*F88,$I$141*F88)),"") -> 0 | K88: =IFERROR(IFS(D88=E88,H88+J88,D88<>E88,J88),0) -> 0
C89: NIL | D89: NIL | E89: NIL | G89: =IF(OR(A89="NIL", C89="NIL", D89="NIL", E89="NIL"), 0, INDEX($B$136:$F$152, MATCH(E89, $A$136:$A$152, 0), MATCH(C89, $B$135:$F$135, 0))) -> 0 | H89: =G89*F89 -> 0 | J89: =IFERROR(IFS(A89="NIL",0,C89="NIL",0,D89="NIL",0,E89="NIL",0,AND(D89=$A$138,C89=$F$135),SUM(($F$136-G89)*F89,$G$138*F89), AND(D89=$A$138,C89=$B$135),SUM(($B$136-G89)*F89,$H$138*F89),AND(D89=$A$138,C89=$C$135),SUM(($C$136-G89)*F89,$I$138*F89),AND(D89=$A$139,C89=$F$135),SUM(($F$136-G89)*F89,$G$139*F89), AND(D89=$A$139,C89=$B$135),SUM(($B$136-G89)*F89,$H$139*F89),AND(D89=$A$139,C89=$C$135),SUM(($C$136-G89)*F89,$I$139*F89),AND(D89=$A$140,C89=$F$135),SUM(($F$136-G89)*F89,$G$140*F89), AND(D89=$A$140,C89=$B$135),SUM(($B$136-G89)*F89,$H$140*F89),AND(D89=$A$140,C89=$C$135),SUM(($C$136-G89)*F89,$I$140*F89),AND(D89=$A$141,C89=$F$135),SUM(($F$136-G89)*F89,$G$141*F89), AND(D89=$A$141,C89=$B$135),SUM(($B$136-G89)*F89,$H$141*F89),AND(D89=$A$141,C89=$C$135),SUM(($C$136-G89)*F89,$I$141*F89)),"") -> 0 | K89: =IFERROR(IFS(D89=E89,H89+J89,D89<>E89,J89),0) -> 0
C90: NIL | D90: NIL | E90: NIL | G90: =IF(OR(A90="NIL", C90="NIL", D90="NIL", E90="NIL"), 0, INDEX($B$136:$F$152, MATCH(E90, $A$136:$A$152, 0), MATCH(C90, $B$135:$F$135, 0))) -> 0 | H90: =G90*F90 -> 0 | J90: =IFERROR(IFS(A90="NIL",0,C90="NIL",0,D90="NIL",0,E90="NIL",0,AND(D90=$A$138,C90=$F$135),SUM(($F$136-G90)*F90,$G$138*F90), AND(D90=$A$138,C90=$B$135),SUM(($B$136-G90)*F90,$H$138*F90),AND(D90=$A$138,C90=$C$135),SUM(($C$136-G90)*F90,$I$138*F90),AND(D90=$A$139,C90=$F$135),SUM(($F$136-G90)*F90,$G$139*F90), AND(D90=$A$139,C90=$B$135),SUM(($B$136-G90)*F90,$H$139*F90),AND(D90=$A$139,C90=$C$135),SUM(($C$136-G90)*F90,$I$139*F90),AND(D90=$A$140,C90=$F$135),SUM(($F$136-G90)*F90,$G$140*F90), AND(D90=$A$140,C90=$B$135),SUM(($B$136-G90)*F90,$H$140*F90),AND(D90=$A$140,C90=$C$135),SUM(($C$136-G90)*F90,$I$140*F90),AND(D90=$A$141,C90=$F$135),SUM(($F$136-G90)*F90,$G$141*F90), AND(D90=$A$141,C90=$B$135),SUM(($B$136-G90)*F90,$H$141*F90),AND(D90=$A$141,C90=$C$135),SUM(($C$136-G90)*F90,$I$141*F90)),"") -> 0 | K90: =IFERROR(IFS(D90=E90,H90+J90,D90<>E90,J90),0) -> 0
C91: NIL | D91: NIL | E91: NIL | G91: =IF(OR(A91="NIL", C91="NIL", D91="NIL", E91="NIL"), 0, INDEX($B$136:$F$152, MATCH(E91, $A$136:$A$152, 0), MATCH(C91, $B$135:$F$135, 0))) -> 0 | H91: =G91*F91 -> 0 | J91: =IFERROR(IFS(A91="NIL",0,C91="NIL",0,D91="NIL",0,E91="NIL",0,AND(D91=$A$138,C91=$F$135),SUM(($F$136-G91)*F91,$G$138*F91), AND(D91=$A$138,C91=$B$135),SUM(($B$136-G91)*F91,$H$138*F91),AND(D91=$A$138,C91=$C$135),SUM(($C$136-G91)*F91,$I$138*F91),AND(D91=$A$139,C91=$F$135),SUM(($F$136-G91)*F91,$G$139*F91), AND(D91=$A$139,C91=$B$135),SUM(($B$136-G91)*F91,$H$139*F91),AND(D91=$A$139,C91=$C$135),SUM(($C$136-G91)*F91,$I$139*F91),AND(D91=$A$140,C91=$F$135),SUM(($F$136-G91)*F91,$G$140*F91), AND(D91=$A$140,C91=$B$135),SUM(($B$136-G91)*F91,$H$140*F91),AND(D91=$A$140,C91=$C$135),SUM(($C$136-G91)*F91,$I$140*F91),AND(D91=$A$141,C91=$F$135),SUM(($F$136-G91)*F91,$G$141*F91), AND(D91=$A$141,C91=$B$135),SUM(($B$136-G91)*F91,$H$141*F91),AND(D91=$A$141,C91=$C$135),SUM(($C$136-G91)*F91,$I$141*F91)),"") -> 0 | K91: =IFERROR(IFS(D91=E91,H91+J91,D91<>E91,J91),0) -> 0
A92: Sony Tyres | B92: 45462 | C92: Poster Design | D92: Vishnu Kalpamangalam | E92: Vishnu Kalpamangalam | F92: 2 | G92: =IF(OR(A92="NIL", C92="NIL", D92="NIL", E92="NIL"), 0, INDEX($B$136:$F$152, MATCH(E92, $A$136:$A$152, 0), MATCH(C92, $B$135:$F$135, 0))) -> 140 | H92: =G92*F92 -> 280 | J92: =IFERROR(IFS(A92="NIL",0,C92="NIL",0,D92="NIL",0,E92="NIL",0,AND(D92=$A$138,C92=$F$135),SUM(($F$136-G92)*F92,$G$138*F92), AND(D92=$A$138,C92=$B$135),SUM(($B$136-G92)*F92,$H$138*F92),AND(D92=$A$138,C92=$C$135),SUM(($C$136-G92)*F92,$I$138*F92),AND(D92=$A$139,C92=$F$135),SUM(($F$136-G92)*F92,$G$139*F92), AND(D92=$A$139,C92=$B$135),SUM(($B$136-G92)*F92,$H$139*F92),AND(D92=$A$139,C92=$C$135),SUM(($C$136-G92)*F92,$I$139*F92),AND(D92=$A$140,C92=$F$135),SUM(($F$136-G92)*F92,$G$140*F92), AND(D92=$A$140,C92=$B$135),SUM(($B$136-G92)*F92,$H$140*F92),AND(D92=$A$140,C92=$C$135),SUM(($C$136-G92)*F92,$I$140*F92),AND(D92=$A$141,C92=$F$135),SUM(($F$136-G92)*F92,$G$141*F92), AND(D92=$A$141,C92=$B$135),SUM(($B$136-G92)*F92,$H$141*F92),AND(D92=$A$141,C92=$C$135),SUM(($C$136-G92)*F92,$I$141*F92)),"") -> 172 | K92: =IFERROR(IFS(D92=E92,H92+J92,D92<>E92,J92),0) -> 452 | L92: =SUM(VLOOKUP(A92,$A$165:$C$178,2,False)*25%,VLOOKUP(A92,$A$165:$C$178,3,False)*25%) -> 1875
C93: NIL | D93: NIL | E93: NIL | G93: =IF(OR(A93="NIL", C93="NIL", D93="NIL", E93="NIL"), 0, INDEX($B$136:$F$152, MATCH(E93, $A$136:$A$152, 0), MATCH(C93, $B$135:$F$135, 0))) -> 0 | H93: =G93*F93 -> 0 | J93: =IFERROR(IFS(A93="NIL",0,C93="NIL",0,D93="NIL",0,E93="NIL",0,AND(D93=$A$138,C93=$F$135),SUM(($F$136-G93)*F93,$G$138*F93), AND(D93=$A$138,C93=$B$135),SUM(($B$136-G93)*F93,$H$138*F93),AND(D93=$A$138,C93=$C$135),SUM(($C$136-G93)*F93,$I$138*F93),AND(D93=$A$139,C93=$F$135),SUM(($F$136-G93)*F93,$G$139*F93), AND(D93=$A$139,C93=$B$135),SUM(($B$136-G93)*F93,$H$139*F93),AND(D93=$A$139,C93=$C$135),SUM(($C$136-G93)*F93,$I$139*F93),AND(D93=$A$140,C93=$F$135),SUM(($F$136-G93)*F93,$G$140*F93), AND(D93=$A$140,C93=$B$135),SUM(($B$136-G93)*F93,$H$140*F93),AND(D93=$A$140,C93=$C$135),SUM(($C$136-G93)*F93,$I$140*F93),AND(D93=$A$141,C93=$F$135),SUM(($F$136-G93)*F93,$G$141*F93), AND(D93=$A$141,C93=$B$135),SUM(($B$136-G93)*F93,$H$141*F93),AND(D93=$A$141,C93=$C$135),SUM(($C$136-G93)*F93,$I$141*F93)),"") -> 0 | K93: =IFERROR(IFS(D93=E93,H93+J93,D93<>E93,J93),0) -> 0
C94: NIL | D94: NIL | E94: NIL | G94: =IF(OR(A94="NIL", C94="NIL", D94="NIL", E94="NIL"), 0, INDEX($B$136:$F$152, MATCH(E94, $A$136:$A$152, 0), MATCH(C94, $B$135:$F$135, 0))) -> 0 | H94: =G94*F94 -> 0 | J94: =IFERROR(IFS(A94="NIL",0,C94="NIL",0,D94="NIL",0,E94="NIL",0,AND(D94=$A$138,C94=$F$135),SUM(($F$136-G94)*F94,$G$138*F94), AND(D94=$A$138,C94=$B$135),SUM(($B$136-G94)*F94,$H$138*F94),AND(D94=$A$138,C94=$C$135),SUM(($C$136-G94)*F94,$I$138*F94),AND(D94=$A$139,C94=$F$135),SUM(($F$136-G94)*F94,$G$139*F94), AND(D94=$A$139,C94=$B$135),SUM(($B$136-G94)*F94,$H$139*F94),AND(D94=$A$139,C94=$C$135),SUM(($C$136-G94)*F94,$I$139*F94),AND(D94=$A$140,C94=$F$135),SUM(($F$136-G94)*F94,$G$140*F94), AND(D94=$A$140,C94=$B$135),SUM(($B$136-G94)*F94,$H$140*F94),AND(D94=$A$140,C94=$C$135),SUM(($C$136-G94)*F94,$I$140*F94),AND(D94=$A$141,C94=$F$135),SUM(($F$136-G94)*F94,$G$141*F94), AND(D94=$A$141,C94=$B$135),SUM(($B$136-G94)*F94,$H$141*F94),AND(D94=$A$141,C94=$C$135),SUM(($C$136-G94)*F94,$I$141*F94)),"") -> 0 | K94: =IFERROR(IFS(D94=E94,H94+J94,D94<>E94,J94),0) -> 0
B95: 45468 | C95: Short video design | D95: Vishnu Kalpamangalam | E95: Achu | F95: 4 | G95: =IF(OR(A95="NIL", C95="NIL", D95="NIL", E95="NIL"), 0, INDEX($B$136:$F$152, MATCH(E95, $A$136:$A$152, 0), MATCH(C95, $B$135:$F$135, 0))) -> 35 | H95: =G95*F95 -> 140 | I95: 45968 | J95: =IFERROR(IFS(A95="NIL",0,C95="NIL",0,D95="NIL",0,E95="NIL",0,AND(D95=$A$138,C95=$F$135),SUM(($F$136-G95)*F95,$G$138*F95), AND(D95=$A$138,C95=$B$135),SUM(($B$136-G95)*F95,$H$138*F95),AND(D95=$A$138,C95=$C$135),SUM(($C$136-G95)*F95,$I$138*F95),AND(D95=$A$139,C95=$F$135),SUM(($F$136-G95)*F95,$G$139*F95), AND(D95=$A$139,C95=$B$135),SUM(($B$136-G95)*F95,$H$139*F95),AND(D95=$A$139,C95=$C$135),SUM(($C$136-G95)*F95,$I$139*F95),AND(D95=$A$140,C95=$F$135),SUM(($F$136-G95)*F95,$G$140*F95), AND(D95=$A$140,C95=$B$135),SUM(($B$136-G95)*F95,$H$140*F95),AND(D95=$A$140,C95=$C$135),SUM(($C$136-G95)*F95,$I$140*F95),AND(D95=$A$141,C95=$F$135),SUM(($F$136-G95)*F95,$G$141*F95), AND(D95=$A$141,C95=$B$135),SUM(($B$136-G95)*F95,$H$141*F95),AND(D95=$A$141,C95=$C$135),SUM(($C$136-G95)*F95,$I$141*F95)),"") -> 1735 | K95: =IFERROR(IFS(D95=E95,H95+J95,D95<>E95,J95),0) -> 1735
C96: NIL | D96: NIL | E96: NIL | G96: =IF(OR(A96="NIL", C96="NIL", D96="NIL", E96="NIL"), 0, INDEX($B$136:$F$152, MATCH(E96, $A$136:$A$152, 0), MATCH(C96, $B$135:$F$135, 0))) -> 0 | H96: =G96*F96 -> 0 | J96: =IFERROR(IFS(A96="NIL",0,C96="NIL",0,D96="NIL",0,E96="NIL",0,AND(D96=$A$138,C96=$F$135),SUM(($F$136-G96)*F96,$G$138*F96), AND(D96=$A$138,C96=$B$135),SUM(($B$136-G96)*F96,$H$138*F96),AND(D96=$A$138,C96=$C$135),SUM(($C$136-G96)*F96,$I$138*F96),AND(D96=$A$139,C96=$F$135),SUM(($F$136-G96)*F96,$G$139*F96), AND(D96=$A$139,C96=$B$135),SUM(($B$136-G96)*F96,$H$139*F96),AND(D96=$A$139,C96=$C$135),SUM(($C$136-G96)*F96,$I$139*F96),AND(D96=$A$140,C96=$F$135),SUM(($F$136-G96)*F96,$G$140*F96), AND(D96=$A$140,C96=$B$135),SUM(($B$136-G96)*F96,$H$140*F96),AND(D96=$A$140,C96=$C$135),SUM(($C$136-G96)*F96,$I$140*F96),AND(D96=$A$141,C96=$F$135),SUM(($F$136-G96)*F96,$G$141*F96), AND(D96=$A$141,C96=$B$135),SUM(($B$136-G96)*F96,$H$141*F96),AND(D96=$A$141,C96=$C$135),SUM(($C$136-G96)*F96,$I$141*F96)),"") -> 0 | K96: =IFERROR(IFS(D96=E96,H96+J96,D96<>E96,J96),0) -> 0
C97: NIL | D97: NIL | E97: NIL | G97: =IF(OR(A97="NIL", C97="NIL", D97="NIL", E97="NIL"), 0, INDEX($B$136:$F$152, MATCH(E97, $A$136:$A$152, 0), MATCH(C97, $B$135:$F$135, 0))) -> 0 | H97: =G97*F97 -> 0 | J97: =IFERROR(IFS(A97="NIL",0,C97="NIL",0,D97="NIL",0,E97="NIL",0,AND(D97=$A$138,C97=$F$135),SUM(($F$136-G97)*F97,$G$138*F97), AND(D97=$A$138,C97=$B$135),SUM(($B$136-G97)*F97,$H$138*F97),AND(D97=$A$138,C97=$C$135),SUM(($C$136-G97)*F97,$I$138*F97),AND(D97=$A$139,C97=$F$135),SUM(($F$136-G97)*F97,$G$139*F97), AND(D97=$A$139,C97=$B$135),SUM(($B$136-G97)*F97,$H$139*F97),AND(D97=$A$139,C97=$C$135),SUM(($C$136-G97)*F97,$I$139*F97),AND(D97=$A$140,C97=$F$135),SUM(($F$136-G97)*F97,$G$140*F97), AND(D97=$A$140,C97=$B$135),SUM(($B$136-G97)*F97,$H$140*F97),AND(D97=$A$140,C97=$C$135),SUM(($C$136-G97)*F97,$I$140*F97),AND(D97=$A$141,C97=$F$135),SUM(($F$136-G97)*F97,$G$141*F97), AND(D97=$A$141,C97=$B$135),SUM(($B$136-G97)*F97,$H$141*F97),AND(D97=$A$141,C97=$C$135),SUM(($C$136-G97)*F97,$I$141*F97)),"") -> 0 | K97: =IFERROR(IFS(D97=E97,H97+J97,D97<>E97,J97),0) -> 0
C98: NIL | D98: NIL | E98: NIL | G98: =IF(OR(A98="NIL", C98="NIL", D98="NIL", E98="NIL"), 0, INDEX($B$136:$F$152, MATCH(E98, $A$136:$A$152, 0), MATCH(C98, $B$135:$F$135, 0))) -> 0 | H98: =G98*F98 -> 0 | J98: =IFERROR(IFS(A98="NIL",0,C98="NIL",0,D98="NIL",0,E98="NIL",0,AND(D98=$A$138,C98=$F$135),SUM(($F$136-G98)*F98,$G$138*F98), AND(D98=$A$138,C98=$B$135),SUM(($B$136-G98)*F98,$H$138*F98),AND(D98=$A$138,C98=$C$135),SUM(($C$136-G98)*F98,$I$138*F98),AND(D98=$A$139,C98=$F$135),SUM(($F$136-G98)*F98,$G$139*F98), AND(D98=$A$139,C98=$B$135),SUM(($B$136-G98)*F98,$H$139*F98),AND(D98=$A$139,C98=$C$135),SUM(($C$136-G98)*F98,$I$139*F98),AND(D98=$A$140,C98=$F$135),SUM(($F$136-G98)*F98,$G$140*F98), AND(D98=$A$140,C98=$B$135),SUM(($B$136-G98)*F98,$H$140*F98),AND(D98=$A$140,C98=$C$135),SUM(($C$136-G98)*F98,$I$140*F98),AND(D98=$A$141,C98=$F$135),SUM(($F$136-G98)*F98,$G$141*F98), AND(D98=$A$141,C98=$B$135),SUM(($B$136-G98)*F98,$H$141*F98),AND(D98=$A$141,C98=$C$135),SUM(($C$136-G98)*F98,$I$141*F98)),"") -> 0 | K98: =IFERROR(IFS(D98=E98,H98+J98,D98<>E98,J98),0) -> 0
C99: NIL | D99: NIL | E99: NIL | G99: =IF(OR(A99="NIL", C99="NIL", D99="NIL", E99="NIL"), 0, INDEX($B$136:$F$152, MATCH(E99, $A$136:$A$152, 0), MATCH(C99, $B$135:$F$135, 0))) -> 0 | H99: =G99*F99 -> 0 | J99: =IFERROR(IFS(A99="NIL",0,C99="NIL",0,D99="NIL",0,E99="NIL",0,AND(D99=$A$138,C99=$F$135),SUM(($F$136-G99)*F99,$G$138*F99), AND(D99=$A$138,C99=$B$135),SUM(($B$136-G99)*F99,$H$138*F99),AND(D99=$A$138,C99=$C$135),SUM(($C$136-G99)*F99,$I$138*F99),AND(D99=$A$139,C99=$F$135),SUM(($F$136-G99)*F99,$G$139*F99), AND(D99=$A$139,C99=$B$135),SUM(($B$136-G99)*F99,$H$139*F99),AND(D99=$A$139,C99=$C$135),SUM(($C$136-G99)*F99,$I$139*F99),AND(D99=$A$140,C99=$F$135),SUM(($F$136-G99)*F99,$G$140*F99), AND(D99=$A$140,C99=$B$135),SUM(($B$136-G99)*F99,$H$140*F99),AND(D99=$A$140,C99=$C$135),SUM(($C$136-G99)*F99,$I$140*F99),AND(D99=$A$141,C99=$F$135),SUM(($F$136-G99)*F99,$G$141*F99), AND(D99=$A$141,C99=$B$135),SUM(($B$136-G99)*F99,$H$141*F99),AND(D99=$A$141,C99=$C$135),SUM(($C$136-G99)*F99,$I$141*F99)),"") -> 0 | K99: =IFERROR(IFS(D99=E99,H99+J99,D99<>E99,J99),0) -> 0
C100: NIL | D100: NIL | E100: NIL | G100: =IF(OR(A100="NIL", C100="NIL", D100="NIL", E100="NIL"), 0, INDEX($B$136:$F$152, MATCH(E100, $A$136:$A$152, 0), MATCH(C100, $B$135:$F$135, 0))) -> 0 | H100: =G100*F100 -> 0 | J100: =IFERROR(IFS(A100="NIL",0,C100="NIL",0,D100="NIL",0,E100="NIL",0,AND(D100=$A$138,C100=$F$135),SUM(($F$136-G100)*F100,$G$138*F100), AND(D100=$A$138,C100=$B$135),SUM(($B$136-G100)*F100,$H$138*F100),AND(D100=$A$138,C100=$C$135),SUM(($C$136-G100)*F100,$I$138*F100),AND(D100=$A$139,C100=$F$135),SUM(($F$136-G100)*F100,$G$139*F100), AND(D100=$A$139,C100=$B$135),SUM(($B$136-G100)*F100,$H$139*F100),AND(D100=$A$139,C100=$C$135),SUM(($C$136-G100)*F100,$I$139*F100),AND(D100=$A$140,C100=$F$135),SUM(($F$136-G100)*F100,$G$140*F100), AND(D100=$A$140,C100=$B$135),SUM(($B$136-G100)*F100,$H$140*F100),AND(D100=$A$140,C100=$C$135),SUM(($C$136-G100)*F100,$I$140*F100),AND(D100=$A$141,C100=$F$135),SUM(($F$136-G100)*F100,$G$141*F100), AND(D100=$A$141,C100=$B$135),SUM(($B$136-G100)*F100,$H$141*F100),AND(D100=$A$141,C100=$C$135),SUM(($C$136-G100)*F100,$I$141*F100)),"") -> 0 | K100: =IFERROR(IFS(D100=E100,H100+J100,D100<>E100,J100),0) -> 0
...

Sheet Ram
A1: RAM WORKSHEET
A2: Date Assigned | B2: Last Date | C2: Assigned by | D2: Company | E2: Task | F2: Qty | G2: Amount | H2: Total | I2: Grand Total
A3: =IF(Calculation!E3=Calculation!$A$142,Calculation!B3,"") | B3: =IF(Calculation!E3=Calculation!$A$142,Calculation!I3,"") | C3: =IF(Calculation!E3=Calculation!$A$142,Calculation!D3,"") | D3: =IF(Calculation!E3=Calculation!$A$142,Calculation!$A$3,"") | E3: =IF(Calculation!E3=Calculation!$A$142,Calculation!C3,"") | F3: =IF(Calculation!E3=Calculation!$A$142,Calculation!F3,"") | G3: =IF(Calculation!E3=Calculation!$A$142,Calculation!G3,"") | H3: =IF(Calculation!E3=Calculation!$A$142,Calculation!H3,"") | I3: =SUMIF(Calculation!E3:E125,Calculation!$A$142,Calculation!H3:H125) -> 700
A4: =IF(Calculation!E4=Calculation!$A$142,Calculation!B4,"") | B4: =IF(Calculation!E4=Calculation!$A$142,Calculation!I4,"") | C4: =IF(Calculation!E4=Calculation!$A$142,Calculation!D4,"") | D4: =IF(Calculation!E4=Calculation!$A$142,Calculation!$A$3,"") | E4: =IF(Calculation!E4=Calculation!$A$142,Calculation!C4,"") | F4: =IF(Calculation!E4=Calculation!$A$142,Calculation!F4,"") | G4: =IF(Calculation!E4=Calculation!$A$142,Calculation!G4,"") | H4: =IF(Calculation!E4=Calculation!$A$142,Calculation!H4,"")
A5: =IF(Calculation!E5=Calculation!$A$142,Calculation!B5,"") -> 45455 | B5: =IF(Calculation!E5=Calculation!$A$142,Calculation!I5,"") -> 45455 | C5: =IF(Calculation!E5=Calculation!$A$142,Calculation!D5,"") -> Anu Shigha | D5: =IF(Calculation!E5=Calculation!$A$142,Calculation!$A$3,"") -> Sony Tyres | E5: =IF(Calculation!E5=Calculation!$A$142,Calculation!C5,"") -> Poster Design | F5: =IF(Calculation!E5=Calculation!$A$142,Calculation!F5,"") -> 1 | G5: =IF(Calculation!E5=Calculation!$A$142,Calculation!G5,"") -> 100 | H5: =IF(Calculation!E5=Calculation!$A$142,Calculation!H5,"") -> 100
A6: =IF(Calculation!E6=Calculation!$A$142,Calculation!B6,"") | B6: =IF(Calculation!E6=Calculation!$A$142,Calculation!I6,"") | C6: =IF(Calculation!E6=Calculation!$A$142,Calculation!D6,"") | D6: =IF(Calculation!E6=Calculation!$A$142,Calculation!$A$3,"") | E6: =IF(Calculation!E6=Calculation!$A$142,Calculation!C6,"") | F6: =IF(Calculation!E6=Calculation!$A$142,Calculation!F6,"") | G6: =IF(Calculation!E6=Calculation!$A$142,Calculation!G6,"") | H6: =IF(Calculation!E6=Calculation!$A$142,Calculation!H6,"")
A7: =IF(Calculation!E7=Calculation!$A$142,Calculation!B7,"") | B7: =IF(Calculation!E7=Calculation!$A$142,Calculation!I7,"") | C7: =IF(Calculation!E7=Calculation!$A$142,Calculation!D7,"") | D7: =IF(Calculation!E7=Calculation!$A$142,Calculation!$A$3,"") | E7: =IF(Calculation!E7=Calculation!$A$142,Calculation!C7,"") | F7: =IF(Calculation!E7=Calculation!$A$142,Calculation!F7,"") | G7: =IF(Calculation!E7=Calculation!$A$142,Calculation!G7,"") | H7: =IF(Calculation!E7=Calculation!$A$142,Calculation!H7,"")
A8: =IF(Calculation!E8=Calculation!$A$142,Calculation!B8,"") | B8: =IF(Calculation!E8=Calculation!$A$142,Calculation!I8,"") | C8: =IF(Calculation!E8=Calculation!$A$142,Calculation!D8,"") | D8: =IF(Calculation!E8=Calculation!$A$142,Calculation!$A$3,"") | E8: =IF(Calculation!E8=Calculation!$A$142,Calculation!C8,"") | F8: =IF(Calculation!E8=Calculation!$A$142,Calculation!F8,"") | G8: =IF(Calculation!E8=Calculation!$A$142,Calculation!G8,"") | H8: =IF(Calculation!E8=Calculation!$A$142,Calculation!H8,"")
A9: =IF(Calculation!E9=Calculation!$A$142,Calculation!B9,"") | B9: =IF(Calculation!E9=Calculation!$A$142,Calculation!I9,"") | C9: =IF(Calculation!E9=Calculation!$A$142,Calculation!D9,"") | D9: =IF(Calculation!E9=Calculation!$A$142,Calculation!$A$3,"") | E9: =IF(Calculation!E9=Calculation!$A$142,Calculation!C9,"") | F9: =IF(Calculation!E9=Calculation!$A$142,Calculation!F9,"") | G9: =IF(Calculation!E9=Calculation!$A$142,Calculation!G9,"") | H9: =IF(Calculation!E9=Calculation!$A$142,Calculation!H9,"")
A10: =IF(Calculation!E10=Calculation!$A$142,Calculation!B10,"") | B10: =IF(Calculation!E10=Calculation!$A$142,Calculation!I10,"") | C10: =IF(Calculation!E10=Calculation!$A$142,Calculation!D10,"") | D10: =IF(Calculation!E10=Calculation!$A$142,Calculation!$A$3,"") | E10: =IF(Calculation!E10=Calculation!$A$142,Calculation!C10,"") | F10: =IF(Calculation!E10=Calculation!$A$142,Calculation!F10,"") | G10: =IF(Calculation!E10=Calculation!$A$142,Calculation!G10,"") | H10: =IF(Calculation!E10=Calculation!$A$142,Calculation!H10,"")
A11: =IF(Calculation!E11=Calculation!$A$142,Calculation!B11,"") | B11: =IF(Calculation!E11=Calculation!$A$142,Calculation!I11,"") | C11: =IF(Calculation!E11=Calculation!$A$142,Calculation!D11,"") | D11: =IF(Calculation!E11=Calculation!$A$142,Calculation!$A$3,"") | E11: =IF(Calculation!E11=Calculation!$A$142,Calculation!C11,"") | F11: =IF(Calculation!E11=Calculation!$A$142,Calculation!F11,"") | G11: =IF(Calculation!E11=Calculation!$A$142,Calculation!G11,"") | H11: =IF(Calculation!E11=Calculation!$A$142,Calculation!H11,"")
A12: =IF(Calculation!E12=Calculation!$A$142,Calculation!B12,"") | B12: =IF(Calculation!E12=Calculation!$A$142,Calculation!I12,"") | C12: =IF(Calculation!E12=Calculation!$A$142,Calculation!D12,"") | D12: =IF(Calculation!E12=Calculation!$A$142,Calculation!$A$3,"") | E12: =IF(Calculation!E12=Calculation!$A$142,Calculation!C12,"") | F12: =IF(Calculation!E12=Calculation!$A$142,Calculation!F12,"") | G12: =IF(Calculation!E12=Calculation!$A$142,Calculation!G12,"") | H12: =IF(Calculation!E12=Calculation!$A$142,Calculation!H12,"")
A13: =IF(Calculation!E13=Calculation!$A$142,Calculation!B13,"") | B13: =IF(Calculation!E13=Calculation!$A$142,Calculation!I13,"") | C13: =IF(Calculation!E13=Calculation!$A$142,Calculation!D13,"") | D13: =IF(Calculation!E13=Calculation!$A$142,Calculation!$A$3,"") | E13: =IF(Calculation!E13=Calculation!$A$142,Calculation!C13,"") | F13: =IF(Calculation!E13=Calculation!$A$142,Calculation!F13,"") | G13: =IF(Calculation!E13=Calculation!$A$142,Calculation!G13,"") | H13: =IF(Calculation!E13=Calculation!$A$142,Calculation!H13,"")
A14: =IF(Calculation!E14=Calculation!$A$142,Calculation!B14,"") | B14: =IF(Calculation!E14=Calculation!$A$142,Calculation!I14,"") | C14: =IF(Calculation!E14=Calculation!$A$142,Calculation!D14,"") | D14: =IF(Calculation!E14=Calculation!$A$142,Calculation!$A$3,"") | E14: =IF(Calculation!E14=Calculation!$A$142,Calculation!C14,"") | F14: =IF(Calculation!E14=Calculation!$A$142,Calculation!F14,"") | G14: =IF(Calculation!E14=Calculation!$A$142,Calculation!G14,"") | H14: =IF(Calculation!E14=Calculation!$A$142,Calculation!H14,"")
A15: =IF(Calculation!E15=Calculation!$A$142,Calculation!B15,"") | B15: =IF(Calculation!E15=Calculation!$A$142,Calculation!I15,"") | C15: =IF(Calculation!E15=Calculation!$A$142,Calculation!D15,"") | D15: =IF(Calculation!E15=Calculation!$A$142,Calculation!$A$3,"") | E15: =IF(Calculation!E15=Calculation!$A$142,Calculation!C15,"") | F15: =IF(Calculation!E15=Calculation!$A$142,Calculation!F15,"") | G15: =IF(Calculation!E15=Calculation!$A$142,Calculation!G15,"") | H15: =IF(Calculation!E15=Calculation!$A$142,Calculation!H15,"")
A16: =IF(Calculation!E16=Calculation!$A$142,Calculation!B16,"") -> 45471 | B16: =IF(Calculation!E16=Calculation!$A$142,Calculation!I16,"") -> 45986 | C16: =IF(Calculation!E16=Calculation!$A$142,Calculation!D16,"") -> Hobo | D16: =IF(Calculation!E16=Calculation!$A$142,Calculation!$A$16,"") -> Alfah Cements | E16: =IF(Calculation!E16=Calculation!$A$142,Calculation!C16,"") -> Content for Poster | F16: =IF(Calculation!E16=Calculation!$A$142,Calculation!F16,"") -> 2 | G16: =IF(Calculation!E16=Calculation!$A$142,Calculation!G16,"") -> 50 | H16: =IF(Calculation!E16=Calculation!$A$142,Calculation!H16,"") -> 100
A17: =IF(Calculation!E17=Calculation!$A$142,Calculation!B17,"") | B17: =IF(Calculation!E17=Calculation!$A$142,Calculation!I17,"") | C17: =IF(Calculation!E17=Calculation!$A$142,Calculation!D17,"") | D17: =IF(Calculation!E17=Calculation!$A$142,Calculation!$A$16,"") | E17: =IF(Calculation!E17=Calculation!$A$142,Calculation!C17,"") | F17: =IF(Calculation!E17=Calculation!$A$142,Calculation!F17,"") | G17: =IF(Calculation!E17=Calculation!$A$142,Calculation!G17,"") | H17: =IF(Calculation!E17=Calculation!$A$142,Calculation!H17,"")
A18: =IF(Calculation!E18=Calculation!$A$142,Calculation!B18,"") | B18: =IF(Calculation!E18=Calculation!$A$142,Calculation!I18,"") | C18: =IF(Calculation!E18=Calculation!$A$142,Calculation!D18,"") | D18: =IF(Calculation!E18=Calculation!$A$142,Calculation!$A$16,"") | E18: =IF(Calculation!E18=Calculation!$A$142,Calculation!C18,"") | F18: =IF(Calculation!E18=Calculation!$A$142,Calculation!F18,"") | G18: =IF(Calculation!E18=Calculation!$A$142,Calculation!G18,"") | H18: =IF(Calculation!E18=Calculation!$A$142,Calculation!H18,"")
A19: =IF(Calculation!E19=Calculation!$A$142,Calculation!B19,"") | B19: =IF(Calculation!E19=Calculation!$A$142,Calculation!I19,"") | C19: =IF(Calculation!E19=Calculation!$A$142,Calculation!D19,"") | D19: =IF(Calculation!E19=Calculation!$A$142,Calculation!$A$16,"") | E19: =IF(Calculation!E19=Calculation!$A$142,Calculation!C19,"") | F19: =IF(Calculation!E19=Calculation!$A$142,Calculation!F19,"") | G19: =IF(Calculation!E19=Calculation!$A$142,Calculation!G19,"") | H19: =IF(Calculation!E19=Calculation!$A$142,Calculation!H19,"")
A20: =IF(Calculation!E20=Calculation!$A$142,Calculation!B20,"") | B20: =IF(Calculation!E20=Calculation!$A$142,Calculation!I20,"") | C20: =IF(Calculation!E20=Calculation!$A$142,Calculation!D20,"") | D20: =IF(Calculation!E20=Calculation!$A$142,Calculation!$A$16,"") | E20: =IF(Calculation!E20=Calculation!$A$142,Calculation!C20,"") | F20: =IF(Calculation!E20=Calculation!$A$142,Calculation!F20,"") | G20: =IF(Calculation!E20=Calculation!$A$142,Calculation!G20,"") | H20: =IF(Calculation!E20=Calculation!$A$142,Calculation!H20,"")
A21: =IF(Calculation!E21=Calculation!$A$142,Calculation!B21,"") | B21: =IF(Calculation!E21=Calculation!$A$142,Calculation!I21,"") | C21: =IF(Calculation!E21=Calculation!$A$142,Calculation!D21,"") | D21: =IF(Calculation!E21=Calculation!$A$142,Calculation!$A$16,"") | E21: =IF(Calculation!E21=Calculation!$A$142,Calculation!C21,"") | F21: =IF(Calculation!E21=Calculation!$A$142,Calculation!F21,"") | G21: =IF(Calculation!E21=Calculation!$A$142,Calculation!G21,"") | H21: =IF(Calculation!E21=Calculation!$A$142,Calculation!H21,"")
A22: =IF(Calculation!E22=Calculation!$A$142,Calculation!B22,"") | B22: =IF(Calculation!E22=Calculation!$A$142,Calculation!I22,"") | C22: =IF(Calculation!E22=Calculation!$A$142,Calculation!D22,"") | D22: =IF(Calculation!E22=Calculation!$A$142,Calculation!$A$16,"") | E22: =IF(Calculation!E22=Calculation!$A$142,Calculation!C22,"") | F22: =IF(Calculation!E22=Calculation!$A$142,Calculation!F22,"") | G22: =IF(Calculation!E22=Calculation!$A$142,Calculation!G22,"") | H22: =IF(Calculation!E22=Calculation!$A$142,Calculation!H22,"")
A23: =IF(Calculation!E23=Calculation!$A$142,Calculation!B23,"") | B23: =IF(Calculation!E23=Calculation!$A$142,Calculation!I23,"") | C23: =IF(Calculation!E23=Calculation!$A$142,Calculation!D23,"") | D23: =IF(Calculation!E23=Calculation!$A$142,Calculation!$A$16,"") | E23: =IF(Calculation!E23=Calculation!$A$142,Calculation!C23,"") | F23: =IF(Calculation!E23=Calculation!$A$142,Calculation!F23,"") | G23: =IF(Calculation!E23=Calculation!$A$142,Calculation!G23,"") | H23: =IF(Calculation!E23=Calculation!$A$142,Calculation!H23,"")
A24: =IF(Calculation!E24=Calculation!$A$142,Calculation!B24,"") | B24: =IF(Calculation!E24=Calculation!$A$142,Calculation!I24,"") | C24: =IF(Calculation!E24=Calculation!$A$142,Calculation!D24,"") | D24: =IF(Calculation!E24=Calculation!$A$142,Calculation!$A$16,"") | E24: =IF(Calculation!E24=Calculation!$A$142,Calculation!C24,"") | F24: =IF(Calculation!E24=Calculation!$A$142,Calculation!F24,"") | G24: =IF(Calculation!E24=Calculation!$A$142,Calculation!G24,"") | H24: =IF(Calculation!E24=Calculation!$A$142,Calculation!H24,"")
A25: =IF(Calculation!E25=Calculation!$A$142,Calculation!B25,"") | B25: =IF(Calculation!E25=Calculation!$A$142,Calculation!I25,"") | C25: =IF(Calculation!E25=Calculation!$A$142,Calculation!D25,"") | D25: =IF(Calculation!E25=Calculation!$A$142,Calculation!$A$16,"") | E25: =IF(Calculation!E25=Calculation!$A$142,Calculation!C25,"") | F25: =IF(Calculation!E25=Calculation!$A$142,Calculation!F25,"") | G25: =IF(Calculation!E25=Calculation!$A$142,Calculation!G25,"") | H25: =IF(Calculation!E25=Calculation!$A$142,Calculation!H25,"")
A26: =IF(Calculation!E26=Calculation!$A$142,Calculation!B26,"") | B26: =IF(Calculation!E26=Calculation!$A$142,Calculation!I26,"") | C26: =IF(Calculation!E26=Calculation!$A$142,Calculation!D26,"") | D26: =IF(Calculation!E26=Calculation!$A$142,Calculation!$A$16,"") | E26: =IF(Calculation!E26=Calculation!$A$142,Calculation!C26,"") | F26: =IF(Calculation!E26=Calculation!$A$142,Calculation!F26,"") | G26: =IF(Calculation!E26=Calculation!$A$142,Calculation!G26,"") | H26: =IF(Calculation!E26=Calculation!$A$142,Calculation!H26,"")
A27: =IF(Calculation!E27=Calculation!$A$142,Calculation!B27,"") | B27: =IF(Calculation!E27=Calculation!$A$142,Calculation!I27,"") | C27: =IF(Calculation!E27=Calculation!$A$142,Calculation!D27,"") | D27: =IF(Calculation!E27=Calculation!$A$142,Calculation!$A$16,"") | E27: =IF(Calculation!E27=Calculation!$A$142,Calculation!C27,"") | F27: =IF(Calculation!E27=Calculation!$A$142,Calculation!F27,"") | G27: =IF(Calculation!E27=Calculation!$A$142,Calculation!G27,"") | H27: =IF(Calculation!E27=Calculation!$A$142,Calculation!H27,"")
A28: =IF(Calculation!E28=Calculation!$A$142,Calculation!B28,"") | B28: =IF(Calculation!E28=Calculation!$A$142,Calculation!I28,"") | C28: =IF(Calculation!E28=Calculation!$A$142,Calculation!D28,"") | D28: =IF(Calculation!E28=Calculation!$A$142,Calculation!$A$16,"") | E28: =IF(Calculation!E28=Calculation!$A$142,Calculation!C28,"") | F28: =IF(Calculation!E28=Calculation!$A$142,Calculation!F28,"") | G28: =IF(Calculation!E28=Calculation!$A$142,Calculation!G28,"") | H28: =IF(Calculation!E28=Calculation!$A$142,Calculation!H28,"")
A29: =IF(Calculation!E29=Calculation!$A$142,Calculation!B29,"") | B29: =IF(Calculation!E29=Calculation!$A$142,Calculation!I29,"") | C29: =IF(Calculation!E29=Calculation!$A$142,Calculation!D29,"") -> Vishnu Kalpamangalam | D29: =IF(Calculation!E29=Calculation!$A$142,Calculation!$A$29,"") -> Prince Tyres | E29: =IF(Calculation!E29=Calculation!$A$142,Calculation!C29,"") -> Short video design | F29: =IF(Calculation!E29=Calculation!$A$142,Calculation!F29,"") -> 2 | G29: =IF(Calculation!E29=Calculation!$A$142,Calculation!G29,"") -> 200 | H29: =IF(Calculation!E29=Calculation!$A$142,Calculation!H29,"") -> 400
A30: =IF(Calculation!E30=Calculation!$A$142,Calculation!B30,"") | B30: =IF(Calculation!E30=Calculation!$A$142,Calculation!I30,"") | C30: =IF(Calculation!E30=Calculation!$A$142,Calculation!D30,"") | D30: =IF(Calculation!E30=Calculation!$A$142,Calculation!$A$29,"") | E30: =IF(Calculation!E30=Calculation!$A$142,Calculation!C30,"") | F30: =IF(Calculation!E30=Calculation!$A$142,Calculation!F30,"") | G30: =IF(Calculation!E30=Calculation!$A$142,Calculation!G30,"") | H30: =IF(Calculation!E30=Calculation!$A$142,Calculation!H30,"")
A31: =IF(Calculation!E31=Calculation!$A$142,Calculation!B31,"") | B31: =IF(Calculation!E31=Calculation!$A$142,Calculation!I31,"") | C31: =IF(Calculation!E31=Calculation!$A$142,Calculation!D31,"") | D31: =IF(Calculation!E31=Calculation!$A$142,Calculation!$A$29,"") | E31: =IF(Calculation!E31=Calculation!$A$142,Calculation!C31,"") | F31: =IF(Calculation!E31=Calculation!$A$142,Calculation!F31,"") | G31: =IF(Calculation!E31=Calculation!$A$142,Calculation!G31,"") | H31: =IF(Calculation!E31=Calculation!$A$142,Calculation!H31,"")
A32: =IF(Calculation!E32=Calculation!$A$142,Calculation!B32,"") | B32: =IF(Calculation!E32=Calculation!$A$142,Calculation!I32,"") | C32: =IF(Calculation!E32=Calculation!$A$142,Calculation!D32,"") | D32: =IF(Calculation!E32=Calculation!$A$142,Calculation!$A$29,"") | E32: =IF(Calculation!E32=Calculation!$A$142,Calculation!C32,"") | F32: =IF(Calculation!E32=Calculation!$A$142,Calculation!F32,"") | G32: =IF(Calculation!E32=Calculation!$A$142,Calculation!G32,"") | H32: =IF(Calculation!E32=Calculation!$A$142,Calculation!H32,"")
A33: =IF(Calculation!E33=Calculation!$A$142,Calculation!B33,"") | B33: =IF(Calculation!E33=Calculation!$A$142,Calculation!I33,"") | C33: =IF(Calculation!E33=Calculation!$A$142,Calculation!D33,"") | D33: =IF(Calculation!E33=Calculation!$A$142,Calculation!$A$29,"") | E33: =IF(Calculation!E33=Calculation!$A$142,Calculation!C33,"") | F33: =IF(Calculation!E33=Calculation!$A$142,Calculation!F33,"") | G33: =IF(Calculation!E33=Calculation!$A$142,Calculation!G33,"") | H33: =IF(Calculation!E33=Calculation!$A$142,Calculation!H33,"")
A34: =IF(Calculation!E34=Calculation!$A$142,Calculation!B34,"") | B34: =IF(Calculation!E34=Calculation!$A$142,Calculation!I34,"") | C34: =IF(Calculation!E34=Calculation!$A$142,Calculation!D34,"") | D34: =IF(Calculation!E34=Calculation!$A$142,Calculation!$A$29,"") | E34: =IF(Calculation!E34=Calculation!$A$142,Calculation!C34,"") | F34: =IF(Calculation!E34=Calculation!$A$142,Calculation!F34,"") | G34: =IF(Calculation!E34=Calculation!$A$142,Calculation!G34,"") | H34: =IF(Calculation!E34=Calculation!$A$142,Calculation!H34,"")
A35: =IF(Calculation!E35=Calculation!$A$142,Calculation!B35,"") | B35: =IF(Calculation!E35=Calculation!$A$142,Calculation!I35,"") | C35: =IF(Calculation!E35=Calculation!$A$142,Calculation!D35,"") | D35: =IF(Calculation!E35=Calculation!$A$142,Calculation!$A$29,"") | E35: =IF(Calculation!E35=Calculation!$A$142,Calculation!C35,"") | F35: =IF(Calculation!E35=Calculation!$A$142,Calculation!F35,"") | G35: =IF(Calculation!E35=Calculation!$A$142,Calculation!G35,"") | H35: =IF(Calculation!E35=Calculation!$A$142,Calculation!H35,"")
A36: =IF(Calculation!E36=Calculation!$A$142,Calculation!B36,"") | B36: =IF(Calculation!E36=Calculation!$A$142,Calculation!I36,"") | C36: =IF(Calculation!E36=Calculation!$A$142,Calculation!D36,"") | D36: =IF(Calculation!E36=Calculation!$A$142,Calculation!$A$29,"") | E36: =IF(Calculation!E36=Calculation!$A$142,Calculation!C36,"") | F36: =IF(Calculation!E36=Calculation!$A$142,Calculation!F36,"") | G36: =IF(Calculation!E36=Calculation!$A$142,Calculation!G36,"") | H36: =IF(Calculation!E36=Calculation!$A$142,Calculation!H36,"")
A37: =IF(Calculation!E37=Calculation!$A$142,Calculation!B37,"") | B37: =IF(Calculation!E37=Calculation!$A$142,Calculation!I37,"") | C37: =IF(Calculation!E37=Calculation!$A$142,Calculation!D37,"") | D37: =IF(Calculation!E37=Calculation!$A$142,Calculation!$A$29,"") | E37: =IF(Calculation!E37=Calculation!$A$142,Calculation!C37,"") | F37: =IF(Calculation!E37=Calculation!$A$142,Calculation!F37,"") | G37: =IF(Calculation!E37=Calculation!$A$142,Calculation!G37,"") | H37: =IF(Calculation!E37=Calculation!$A$142,Calculation!H37,"")
A38: =IF(Calculation!E38=Calculation!$A$142,Calculation!B38,"") | B38: =IF(Calculation!E38=Calculation!$A$142,Calculation!I38,"") | C38: =IF(Calculation!E38=Calculation!$A$142,Calculation!D38,"") | D38: =IF(Calculation!E38=Calculation!$A$142,Calculation!$A$29,"") | E38: =IF(Calculation!E38=Calculation!$A$142,Calculation!C38,"") | F38: =IF(Calculation!E38=Calculation!$A$142,Calculation!F38,"") | G38: =IF(Calculation!E38=Calculation!$A$142,Calculation!G38,"") | H38: =IF(Calculation!E38=Calculation!$A$142,Calculation!H38,"")
A39: =IF(Calculation!E39=Calculation!$A$142,Calculation!B39,"") | B39: =IF(Calculation!E39=Calculation!$A$142,Calculation!I39,"") | C39: =IF(Calculation!E39=Calculation!$A$142,Calculation!D39,"") | D39: =IF(Calculation!E39=Calculation!$A$142,Calculation!$A$29,"") | E39: =IF(Calculation!E39=Calculation!$A$142,Calculation!C39,"") | F39: =IF(Calculation!E39=Calculation!$A$142,Calculation!F39,"") | G39: =IF(Calculation!E39=Calculation!$A$142,Calculation!G39,"") | H39: =IF(Calculation!E39=Calculation!$A$142,Calculation!H39,"")
A40: =IF(Calculation!E40=Calculation!$A$142,Calculation!B40,"") | B40: =IF(Calculation!E40=Calculation!$A$142,Calculation!I40,"") | C40: =IF(Calculation!E40=Calculation!$A$142,Calculation!D40,"") | D40: =IF(Calculation!E40=Calculation!$A$142,Calculation!$A$29,"") | E40: =IF(Calculation!E40=Calculation!$A$142,Calculation!C40,"") | F40: =IF(Calculation!E40=Calculation!$A$142,Calculation!F40,"") | G40: =IF(Calculation!E40=Calculation!$A$142,Calculation!G40,"") | H40: =IF(Calculation!E40=Calculation!$A$142,Calculation!H40,"")
A41: =IF(Calculation!E41=Calculation!$A$142,Calculation!B41,"") | B41: =IF(Calculation!E41=Calculation!$A$142,Calculation!I41,"") | C41: =IF(Calculation!E41=Calculation!$A$142,Calculation!D41,"") | D41: =IF(Calculation!E41=Calculation!$A$142,Calculation!$A$41,"") | E41: =IF(Calculation!E41=Calculation!$A$142,Calculation!C41,"") | F41: =IF(Calculation!E41=Calculation!$A$142,Calculation!F41,"") | G41: =IF(Calculation!E41=Calculation!$A$142,Calculation!G41,"") | H41: =IF(Calculation!E41=Calculation!$A$142,Calculation!H41,"")
A42: =IF(Calculation!E42=Calculation!$A$142,Calculation!B42,"") | B42: =IF(Calculation!E42=Calculation!$A$142,Calculation!I42,"") | C42: =IF(Calculation!E42=Calculation!$A$142,Calculation!D42,"") | D42: =IF(Calculation!E42=Calculation!$A$142,Calculation!$A$41,"") | E42: =IF(Calculation!E42=Calculation!$A$142,Calculation!C42,"") | F42: =IF(Calculation!E42=Calculation!$A$142,Calculation!F42,"") | G42: =IF(Calculation!E42=Calculation!$A$142,Calculation!G42,"") | H42: =IF(Calculation!E42=Calculation!$A$142,Calculation!H42,"")
A43: =IF(Calculation!E43=Calculation!$A$142,Calculation!B43,"") | B43: =IF(Calculation!E43=Calculation!$A$142,Calculation!I43,"") | C43: =IF(Calculation!E43=Calculation!$A$142,Calculation!D43,"") | D43: =IF(Calculation!E43=Calculation!$A$142,Calculation!$A$41,"") | E43: =IF(Calculation!E43=Calculation!$A$142,Calculation!C43,"") | F43: =IF(Calculation!E43=Calculation!$A$142,Calculation!F43,"") | G43: =IF(Calculation!E43=Calculation!$A$142,Calculation!G43,"") | H43: =IF(Calculation!E43=Calculation!$A$142,Calculation!H43,"")
A44: =IF(Calculation!E44=Calculation!$A$142,Calculation!B44,"") | B44: =IF(Calculation!E44=Calculation!$A$142,Calculation!I44,"") | C44: =IF(Calculation!E44=Calculation!$A$142,Calculation!D44,"") | D44: =IF(Calculation!E44=Calculation!$A$142,Calculation!$A$41,"") | E44: =IF(Calculation!E44=Calculation!$A$142,Calculation!C44,"") | F44: =IF(Calculation!E44=Calculation!$A$142,Calculation!F44,"") | G44: =IF(Calculation!E44=Calculation!$A$142,Calculation!G44,"") | H44: =IF(Calculation!E44=Calculation!$A$142,Calculation!H44,"")
A45: =IF(Calculation!E45=Calculation!$A$142,Calculation!B45,"") | B45: =IF(Calculation!E45=Calculation!$A$142,Calculation!I45,"") | C45: =IF(Calculation!E45=Calculation!$A$142,Calculation!D45,"") -> Nebil Divay | D45: =IF(Calculation!E45=Calculation!$A$142,Calculation!$A$41,"") -> Sony Tyres | E45: =IF(Calculation!E45=Calculation!$A$142,Calculation!C45,"") -> Poster Design | F45: =IF(Calculation!E45=Calculation!$A$142,Calculation!F45,"") -> 1 | G45: =IF(Calculation!E45=Calculation!$A$142,Calculation!G45,"") -> 100 | H45: =IF(Calculation!E45=Calculation!$A$142,Calculation!H45,"") -> 100
A46: =IF(Calculation!E46=Calculation!$A$142,Calculation!B46,"") | B46: =IF(Calculation!E46=Calculation!$A$142,Calculation!I46,"") | C46: =IF(Calculation!E46=Calculation!$A$142,Calculation!D46,"") | D46: =IF(Calculation!E46=Calculation!$A$142,Calculation!$A$41,"") | E46: =IF(Calculation!E46=Calculation!$A$142,Calculation!C46,"") | F46: =IF(Calculation!E46=Calculation!$A$142,Calculation!F46,"") | G46: =IF(Calculation!E46=Calculation!$A$142,Calculation!G46,"") | H46: =IF(Calculation!E46=Calculation!$A$142,Calculation!H46,"")
A47: =IF(Calculation!E47=Calculation!$A$142,Calculation!B47,"") | B47: =IF(Calculation!E47=Calculation!$A$142,Calculation!I47,"") | C47: =IF(Calculation!E47=Calculation!$A$142,Calculation!D47,"") | D47: =IF(Calculation!E47=Calculation!$A$142,Calculation!$A$41,"") | E47: =IF(Calculation!E47=Calculation!$A$142,Calculation!C47,"") | F47: =IF(Calculation!E47=Calculation!$A$142,Calculation!F47,"") | G47: =IF(Calculation!E47=Calculation!$A$142,Calculation!G47,"") | H47: =IF(Calculation!E47=Calculation!$A$142,Calculation!H47,"")
A48: =IF(Calculation!E48=Calculation!$A$142,Calculation!B48,"") | B48: =IF(Calculation!E48=Calculation!$A$142,Calculation!I48,"") | C48: =IF(Calculation!E48=Calculation!$A$142,Calculation!D48,"") | D48: =IF(Calculation!E48=Calculation!$A$142,Calculation!$A$41,"") | E48: =IF(Calculation!E48=Calculation!$A$142,Calculation!C48,"") | F48: =IF(Calculation!E48=Calculation!$A$142,Calculation!F48,"") | G48: =IF(Calculation!E48=Calculation!$A$142,Calculation!G48,"") | H48: =IF(Calculation!E48=Calculation!$A$142,Calculation!H48,"")
A49: =IF(Calculation!E49=Calculation!$A$142,Calculation!B49,"") | B49: =IF(Calculation!E49=Calculation!$A$142,Calculation!I49,"") | C49: =IF(Calculation!E49=Calculation!$A$142,Calculation!D49,"") | D49: =IF(Calculation!E49=Calculation!$A$142,Calculation!$A$41,"") | E49: =IF(Calculation!E49=Calculation!$A$142,Calculation!C49,"") | F49: =IF(Calculation!E49=Calculation!$A$142,Calculation!F49,"") | G49: =IF(Calculation!E49=Calculation!$A$142,Calculation!G49,"") | H49: =IF(Calculation!E49=Calculation!$A$142,Calculation!H49,"")
A50: =IF(Calculation!E50=Calculation!$A$142,Calculation!B50,"") | B50: =IF(Calculation!E50=Calculation!$A$142,Calculation!I50,"") | C50: =IF(Calculation!E50=Calculation!$A$142,Calculation!D50,"") | D50: =IF(Calculation!E50=Calculation!$A$142,Calculation!$A$41,"") | E50: =IF(Calculation!E50=Calculation!$A$142,Calculation!C50,"") | F50: =IF(Calculation!E50=Calculation!$A$142,Calculation!F50,"") | G50: =IF(Calculation!E50=Calculation!$A$142,Calculation!G50,"") | H50: =IF(Calculation!E50=Calculation!$A$142,Calculation!H50,"")
A51: =IF(Calculation!E51=Calculation!$A$142,Calculation!B51,"") | B51: =IF(Calculation!E51=Calculation!$A$142,Calculation!I51,"") | C51: =IF(Calculation!E51=Calculation!$A$142,Calculation!D51,"") | D51: =IF(Calculation!E51=Calculation!$A$142,Calculation!$A$41,"") | E51: =IF(Calculation!E51=Calculation!$A$142,Calculation!C51,"") | F51: =IF(Calculation!E51=Calculation!$A$142,Calculation!F51,"") | G51: =IF(Calculation!E51=Calculation!$A$142,Calculation!G51,"") | H51: =IF(Calculation!E51=Calculation!$A$142,Calculation!H51,"")
A52: =IF(Calculation!E52=Calculation!$A$142,Calculation!B52,"") | B52: =IF(Calculation!E52=Calculation!$A$142,Calculation!I52,"") | C52: =IF(Calculation!E52=Calculation!$A$142,Calculation!D52,"") | D52: =IF(Calculation!E52=Calculation!$A$142,Calculation!$A$41,"") | E52: =IF(Calculation!E52=Calculation!$A$142,Calculation!C52,"") | F52: =IF(Calculation!E52=Calculation!$A$142,Calculation!F52,"") | G52: =IF(Calculation!E52=Calculation!$A$142,Calculation!G52,"") | H52: =IF(Calculation!E52=Calculation!$A$142,Calculation!H52,"")
A53: =IF(Calculation!E53=Calculation!$A$142,Calculation!B53,"") | B53: =IF(Calculation!E53=Calculation!$A$142,Calculation!I53,"") | C53: =IF(Calculation!E53=Calculation!$A$142,Calculation!D53,"") | D53: =IF(Calculation!E53=Calculation!$A$142,Calculation!$A$41,"") | E53: =IF(Calculation!E53=Calculation!$A$142,Calculation!C53,"") | F53: =IF(Calculation!E53=Calculation!$A$142,Calculation!F53,"") | G53: =IF(Calculation!E53=Calculation!$A$142,Calculation!G53,"") | H53: =IF(Calculation!E53=Calculation!$A$142,Calculation!H53,"")
A54: =IF(Calculation!E54=Calculation!$A$142,Calculation!B54,"") | B54: =IF(Calculation!E54=Calculation!$A$142,Calculation!I54,"") | C54: =IF(Calculation!E54=Calculation!$A$142,Calculation!D54,"") | D54: =IF(Calculation!E54=Calculation!$A$142,Calculation!$A$54,"") | E54: =IF(Calculation!E54=Calculation!$A$142,Calculation!C54,"") | F54: =IF(Calculation!E54=Calculation!$A$142,Calculation!F54,"") | G54: =IF(Calculation!E54=Calculation!$A$142,Calculation!G54,"") | H54: =IF(Calculation!E54=Calculation!$A$142,Calculation!H54,"")
A55: =IF(Calculation!E55=Calculation!$A$142,Calculation!B55,"") | B55: =IF(Calculation!E55=Calculation!$A$142,Calculation!I55,"") | C55: =IF(Calculation!E55=Calculation!$A$142,Calculation!D55,"") | D55: =IF(Calculation!E55=Calculation!$A$142,Calculation!$A$54,"") | E55: =IF(Calculation!E55=Calculation!$A$142,Calculation!C55,"") | F55: =IF(Calculation!E55=Calculation!$A$142,Calculation!F55,"") | G55: =IF(Calculation!E55=Calculation!$A$142,Calculation!G55,"") | H55: =IF(Calculation!E55=Calculation!$A$142,Calculation!H55,"")
A56: =IF(Calculation!E56=Calculation!$A$142,Calculation!B56,"") | B56: =IF(Calculation!E56=Calculation!$A$142,Calculation!I56,"") | C56: =IF(Calculation!E56=Calculation!$A$142,Calculation!D56,"") | D56: =IF(Calculation!E56=Calculation!$A$142,Calculation!$A$54,"") | E56: =IF(Calculation!E56=Calculation!$A$142,Calculation!C56,"") | F56: =IF(Calculation!E56=Calculation!$A$142,Calculation!F56,"") | G56: =IF(Calculation!E56=Calculation!$A$142,Calculation!G56,"") | H56: =IF(Calculation!E56=Calculation!$A$142,Calculation!H56,"")
A57: =IF(Calculation!E57=Calculation!$A$142,Calculation!B57,"") | B57: =IF(Calculation!E57=Calculation!$A$142,Calculation!I57,"") | C57: =IF(Calculation!E57=Calculation!$A$142,Calculation!D57,"") | D57: =IF(Calculation!E57=Calculation!$A$142,Calculation!$A$54,"") | E57: =IF(Calculation!E57=Calculation!$A$142,Calculation!C57,"") | F57: =IF(Calculation!E57=Calculation!$A$142,Calculation!F57,"") | G57: =IF(Calculation!E57=Calculation!$A$142,Calculation!G57,"") | H57: =IF(Calculation!E57=Calculation!$A$142,Calculation!H57,"")
A58: =IF(Calculation!E58=Calculation!$A$142,Calculation!B58,"") | B58: =IF(Calculation!E58=Calculation!$A$142,Calculation!I58,"") | C58: =IF(Calculation!E58=Calculation!$A$142,Calculation!D58,"") | D58: =IF(Calculation!E58=Calculation!$A$142,Calculation!$A$54,"") | E58: =IF(Calculation!E58=Calculation!$A$142,Calculation!C58,"") | F58: =IF(Calculation!E58=Calculation!$A$142,Calculation!F58,"") | G58: =IF(Calculation!E58=Calculation!$A$142,Calculation!G58,"") | H58: =IF(Calculation!E58=Calculation!$A$142,Calculation!H58,"")
A59: =IF(Calculation!E59=Calculation!$A$142,Calculation!B59,"") | B59: =IF(Calculation!E59=Calculation!$A$142,Calculation!I59,"") | C59: =IF(Calculation!E59=Calculation!$A$142,Calculation!D59,"") -> NIL | D59: =IF(Calculation!E59=Calculation!$A$142,Calculation!$A$54,"") -> Prince Tyres | E59: =IF(Calculation!E59=Calculation!$A$142,Calculation!C59,"") -> NIL | F59: =IF(Calculation!E59=Calculation!$A$142,Calculation!F59,"") | G59: =IF(Calculation!E59=Calculation!$A$142,Calculation!G59,"") -> 0 | H59: =IF(Calculation!E59=Calculation!$A$142,Calculation!H59,"") -> 0
A60: =IF(Calculation!E60=Calculation!$A$142,Calculation!B60,"") | B60: =IF(Calculation!E60=Calculation!$A$142,Calculation!I60,"") | C60: =IF(Calculation!E60=Calculation!$A$142,Calculation!D60,"") | D60: =IF(Calculation!E60=Calculation!$A$142,Calculation!$A$54,"") | E60: =IF(Calculation!E60=Calculation!$A$142,Calculation!C60,"") | F60: =IF(Calculation!E60=Calculation!$A$142,Calculation!F60,"") | G60: =IF(Calculation!E60=Calculation!$A$142,Calculation!G60,"") | H60: =IF(Calculation!E60=Calculation!$A$142,Calculation!H60,"")
A61: =IF(Calculation!E61=Calculation!$A$142,Calculation!B61,"") | B61: =IF(Calculation!E61=Calculation!$A$142,Calculation!I61,"") | C61: =IF(Calculation!E61=Calculation!$A$142,Calculation!D61,"") | D61: =IF(Calculation!E61=Calculation!$A$142,Calculation!$A$54,"") | E61: =IF(Calculation!E61=Calculation!$A$142,Calculation!C61,"") | F61: =IF(Calculation!E61=Calculation!$A$142,Calculation!F61,"") | G61: =IF(Calculation!E61=Calculation!$A$142,Calculation!G61,"") | H61: =IF(Calculation!E61=Calculation!$A$142,Calculation!H61,"")
A62: =IF(Calculation!E62=Calculation!$A$142,Calculation!B62,"") | B62: =IF(Calculation!E62=Calculation!$A$142,Calculation!I62,"") | C62: =IF(Calculation!E62=Calculation!$A$142,Calculation!D62,"") | D62: =IF(Calculation!E62=Calculation!$A$142,Calculation!$A$54,"") | E62: =IF(Calculation!E62=Calculation!$A$142,Calculation!C62,"") | F62: =IF(Calculation!E62=Calculation!$A$142,Calculation!F62,"") | G62: =IF(Calculation!E62=Calculation!$A$142,Calculation!G62,"") | H62: =IF(Calculation!E62=Calculation!$A$142,Calculation!H62,"")
A63: =IF(Calculation!E63=Calculation!$A$142,Calculation!B63,"") | B63: =IF(Calculation!E63=Calculation!$A$142,Calculation!I63,"") | C63: =IF(Calculation!E63=Calculation!$A$142,Calculation!D63,"") | D63: =IF(Calculation!E63=Calculation!$A$142,Calculation!$A$54,"") | E63: =IF(Calculation!E63=Calculation!$A$142,Calculation!C63,"") | F63: =IF(Calculation!E63=Calculation!$A$142,Calculation!F63,"") | G63: =IF(Calculation!E63=Calculation!$A$142,Calculation!G63,"") | H63: =IF(Calculation!E63=Calculation!$A$142,Calculation!H63,"")
A64: =IF(Calculation!E64=Calculation!$A$142,Calculation!B64,"") | B64: =IF(Calculation!E64=Calculation!$A$142,Calculation!I64,"") | C64: =IF(Calculation!E64=Calculation!$A$142,Calculation!D64,"") | D64: =IF(Calculation!E64=Calculation!$A$142,Calculation!$A$54,"") | E64: =IF(Calculation!E64=Calculation!$A$142,Calculation!C64,"") | F64: =IF(Calculation!E64=Calculation!$A$142,Calculation!F64,"") | G64: =IF(Calculation!E64=Calculation!$A$142,Calculation!G64,"") | H64: =IF(Calculation!E64=Calculation!$A$142,Calculation!H64,"")
A65: =IF(Calculation!E65=Calculation!$A$142,Calculation!B65,"") | B65: =IF(Calculation!E65=Calculation!$A$142,Calculation!I65,"") | C65: =IF(Calculation!E65=Calculation!$A$142,Calculation!D65,"") | D65: =IF(Calculation!E65=Calculation!$A$142,Calculation!$A$54,"") | E65: =IF(Calculation!E65=Calculation!$A$142,Calculation!C65,"") | F65: =IF(Calculation!E65=Calculation!$A$142,Calculation!F65,"") | G65: =IF(Calculation!E65=Calculation!$A$142,Calculation!G65,"") | H65: =IF(Calculation!E65=Calculation!$A$142,Calculation!H65,"")
A66: =IF(Calculation!E66=Calculation!$A$142,Calculation!B66,"") | B66: =IF(Calculation!E66=Calculation!$A$142,Calculation!I66,"") | C66: =IF(Calculation!E66=Calculation!$A$142,Calculation!D66,"") | D66: =IF(Calculation!E66=Calculation!$A$142,Calculation!$A$66,"") | E66: =IF(Calculation!E66=Calculation!$A$142,Calculation!C66,"") | F66: =IF(Calculation!E66=Calculation!$A$142,Calculation!F66,"") | G66: =IF(Calculation!E66=Calculation!$A$142,Calculation!G66,"") | H66: =IF(Calculation!E66=Calculation!$A$142,Calculation!H66,"")
A67: =IF(Calculation!E67=Calculation!$A$142,Calculation!B67,"") | B67: =IF(Calculation!E67=Calculation!$A$142,Calculation!I67,"") | C67: =IF(Calculation!E67=Calculation!$A$142,Calculation!D67,"") | D67: =IF(Calculation!E67=Calculation!$A$142,Calculation!$A$66,"") | E67: =IF(Calculation!E67=Calculation!$A$142,Calculation!C67,"") | F67: =IF(Calculation!E67=Calculation!$A$142,Calculation!F67,"") | G67: =IF(Calculation!E67=Calculation!$A$142,Calculation!G67,"") | H67: =IF(Calculation!E67=Calculation!$A$142,Calculation!H67,"")
A68: =IF(Calculation!E68=Calculation!$A$142,Calculation!B68,"") | B68: =IF(Calculation!E68=Calculation!$A$142,Calculation!I68,"") | C68: =IF(Calculation!E68=Calculation!$A$142,Calculation!D68,"") | D68: =IF(Calculation!E68=Calculation!$A$142,Calculation!$A$66,"") | E68: =IF(Calculation!E68=Calculation!$A$142,Calculation!C68,"") | F68: =IF(Calculation!E68=Calculation!$A$142,Calculation!F68,"") | G68: =IF(Calculation!E68=Calculation!$A$142,Calculation!G68,"") | H68: =IF(Calculation!E68=Calculation!$A$142,Calculation!H68,"")
A69: =IF(Calculation!E69=Calculation!$A$142,Calculation!B69,"") | B69: =IF(Calculation!E69=Calculation!$A$142,Calculation!I69,"") | C69: =IF(Calculation!E69=Calculation!$A$142,Calculation!D69,"") | D69: =IF(Calculation!E69=Calculation!$A$142,Calculation!$A$66,"") | E69: =IF(Calculation!E69=Calculation!$A$142,Calculation!C69,"") | F69: =IF(Calculation!E69=Calculation!$A$142,Calculation!F69,"") | G69: =IF(Calculation!E69=Calculation!$A$142,Calculation!G69,"") | H69: =IF(Calculation!E69=Calculation!$A$142,Calculation!H69,"")
A70: =IF(Calculation!E70=Calculation!$A$142,Calculation!B70,"") | B70: =IF(Calculation!E70=Calculation!$A$142,Calculation!I70,"") | C70: =IF(Calculation!E70=Calculation!$A$142,Calculation!D70,"") | D70: =IF(Calculation!E70=Calculation!$A$142,Calculation!$A$66,"") | E70: =IF(Calculation!E70=Calculation!$A$142,Calculation!C70,"") | F70: =IF(Calculation!E70=Calculation!$A$142,Calculation!F70,"") | G70: =IF(Calculation!E70=Calculation!$A$142,Calculation!G70,"") | H70: =IF(Calculation!E70=Calculation!$A$142,Calculation!H70,"")
A71: =IF(Calculation!E71=Calculation!$A$142,Calculation!B71,"") | B71: =IF(Calculation!E71=Calculation!$A$142,Calculation!I71,"") | C71: =IF(Calculation!E71=Calculation!$A$142,Calculation!D71,"") | D71: =IF(Calculation!E71=Calculation!$A$142,Calculation!$A$66,"") | E71: =IF(Calculation!E71=Calculation!$A$142,Calculation!C71,"") | F71: =IF(Calculation!E71=Calculation!$A$142,Calculation!F71,"") | G71: =IF(Calculation!E71=Calculation!$A$142,Calculation!G71,"") | H71: =IF(Calculation!E71=Calculation!$A$142,Calculation!H71,"")
A72: =IF(Calculation!E72=Calculation!$A$142,Calculation!B72,"") | B72: =IF(Calculation!E72=Calculation!$A$142,Calculation!I72,"") | C72: =IF(Calculation!E72=Calculation!$A$142,Calculation!D72,"") | D72: =IF(Calculation!E72=Calculation!$A$142,Calculation!$A$66,"") | E72: =IF(Calculation!E72=Calculation!$A$142,Calculation!C72,"") | F72: =IF(Calculation!E72=Calculation!$A$142,Calculation!F72,"") | G72: =IF(Calculation!E72=Calculation!$A$142,Calculation!G72,"") | H72: =IF(Calculation!E72=Calculation!$A$142,Calculation!H72,"")
A73: =IF(Calculation!E73=Calculation!$A$142,Calculation!B73,"") | B73: =IF(Calculation!E73=Calculation!$A$142,Calculation!I73,"") | C73: =IF(Calculation!E73=Calculation!$A$142,Calculation!D73,"") | D73: =IF(Calculation!E73=Calculation!$A$142,Calculation!$A$66,"") | E73: =IF(Calculation!E73=Calculation!$A$142,Calculation!C73,"") | F73: =IF(Calculation!E73=Calculation!$A$142,Calculation!F73,"") | G73: =IF(Calculation!E73=Calculation!$A$142,Calculation!G73,"") | H73: =IF(Calculation!E73=Calculation!$A$142,Calculation!H73,"")
A74: =IF(Calculation!E74=Calculation!$A$142,Calculation!B74,"") | B74: =IF(Calculation!E74=Calculation!$A$142,Calculation!I74,"") | C74: =IF(Calculation!E74=Calculation!$A$142,Calculation!D74,"") | D74: =IF(Calculation!E74=Calculation!$A$142,Calculation!$A$66,"") | E74: =IF(Calculation!E74=Calculation!$A$142,Calculation!C74,"") | F74: =IF(Calculation!E74=Calculation!$A$142,Calculation!F74,"") | G74: =IF(Calculation!E74=Calculation!$A$142,Calculation!G74,"") | H74: =IF(Calculation!E74=Calculation!$A$142,Calculation!H74,"")
A75: =IF(Calculation!E75=Calculation!$A$142,Calculation!B75,"") | B75: =IF(Calculation!E75=Calculation!$A$142,Calculation!I75,"") | C75: =IF(Calculation!E75=Calculation!$A$142,Calculation!D75,"") | D75: =IF(Calculation!E75=Calculation!$A$142,Calculation!$A$66,"") | E75: =IF(Calculation!E75=Calculation!$A$142,Calculation!C75,"") | F75: =IF(Calculation!E75=Calculation!$A$142,Calculation!F75,"") | G75: =IF(Calculation!E75=Calculation!$A$142,Calculation!G75,"") | H75: =IF(Calculation!E75=Calculation!$A$142,Calculation!H75,"")
A76: =IF(Calculation!E76=Calculation!$A$142,Calculation!B76,"") | B76: =IF(Calculation!E76=Calculation!$A$142,Calculation!I76,"") | C76: =IF(Calculation!E76=Calculation!$A$142,Calculation!D76,"") | D76: =IF(Calculation!E76=Calculation!$A$142,Calculation!$A$66,"") | E76: =IF(Calculation!E76=Calculation!$A$142,Calculation!C76,"") | F76: =IF(Calculation!E76=Calculation!$A$142,Calculation!F76,"") | G76: =IF(Calculation!E76=Calculation!$A$142,Calculation!G76,"") | H76: =IF(Calculation!E76=Calculation!$A$142,Calculation!H76,"")
A77: =IF(Calculation!E77=Calculation!$A$142,Calculation!B77,"") | B77: =IF(Calculation!E77=Calculation!$A$142,Calculation!I77,"") | C77: =IF(Calculation!E77=Calculation!$A$142,Calculation!D77,"") | D77: =IF(Calculation!E77=Calculation!$A$142,Calculation!$A$66,"") | E77: =IF(Calculation!E77=Calculation!$A$142,Calculation!C77,"") | F77: =IF(Calculation!E77=Calculation!$A$142,Calculation!F77,"") | G77: =IF(Calculation!E77=Calculation!$A$142,Calculation!G77,"") | H77: =IF(Calculation!E77=Calculation!$A$142,Calculation!H77,"")
A78: =IF(Calculation!E78=Calculation!$A$142,Calculation!B78,"") | B78: =IF(Calculation!E78=Calculation!$A$142,Calculation!I78,"") | C78: =IF(Calculation!E78=Calculation!$A$142,Calculation!D78,"") | D78: =IF(Calculation!E78=Calculation!$A$142,Calculation!$A$66,"") | E78: =IF(Calculation!E78=Calculation!$A$142,Calculation!C78,"") | F78: =IF(Calculation!E78=Calculation!$A$142,Calculation!F78,"") | G78: =IF(Calculation!E78=Calculation!$A$142,Calculation!G78,"") | H78: =IF(Calculation!E78=Calculation!$A$142,Calculation!H78,"")
A79: =IF(Calculation!E79=Calculation!$A$142,Calculation!B79,"") | B79: =IF(Calculation!E79=Calculation!$A$142,Calculation!I79,"") | C79: =IF(Calculation!E79=Calculation!$A$142,Calculation!D79,"") | D79: =IF(Calculation!E79=Calculation!$A$142,Calculation!$A$79,"") | E79: =IF(Calculation!E79=Calculation!$A$142,Calculation!C79,"") | F79: =IF(Calculation!E79=Calculation!$A$142,Calculation!F79,"") | G79: =IF(Calculation!E79=Calculation!$A$142,Calculation!G79,"") | H79: =IF(Calculation!E79=Calculation!$A$142,Calculation!H79,"")
A80: =IF(Calculation!E80=Calculation!$A$142,Calculation!B80,"") | B80: =IF(Calculation!E80=Calculation!$A$142,Calculation!I80,"") | C80: =IF(Calculation!E80=Calculation!$A$142,Calculation!D80,"") | D80: =IF(Calculation!E80=Calculation!$A$142,Calculation!$A$79,"") | E80: =IF(Calculation!E80=Calculation!$A$142,Calculation!C80,"") | F80: =IF(Calculation!E80=Calculation!$A$142,Calculation!F80,"") | G80: =IF(Calculation!E80=Calculation!$A$142,Calculation!G80,"") | H80: =IF(Calculation!E80=Calculation!$A$142,Calculation!H80,"")
A81: =IF(Calculation!E81=Calculation!$A$142,Calculation!B81,"") | B81: =IF(Calculation!E81=Calculation!$A$142,Calculation!I81,"") | C81: =IF(Calculation!E81=Calculation!$A$142,Calculation!D81,"") | D81: =IF(Calculation!E81=Calculation!$A$142,Calculation!$A$79,"") | E81: =IF(Calculation!E81=Calculation!$A$142,Calculation!C81,"") | F81: =IF(Calculation!E81=Calculation!$A$142,Calculation!F81,"") | G81: =IF(Calculation!E81=Calculation!$A$142,Calculation!G81,"") | H81: =IF(Calculation!E81=Calculation!$A$142,Calculation!H81,"")
A82: =IF(Calculation!E82=Calculation!$A$142,Calculation!B82,"") | B82: =IF(Calculation!E82=Calculation!$A$142,Calculation!I82,"") | C82: =IF(Calculation!E82=Calculation!$A$142,Calculation!D82,"") | D82: =IF(Calculation!E82=Calculation!$A$142,Calculation!$A$79,"") | E82: =IF(Calculation!E82=Calculation!$A$142,Calculation!C82,"") | F82: =IF(Calculation!E82=Calculation!$A$142,Calculation!F82,"") | G82: =IF(Calculation!E82=Calculation!$A$142,Calculation!G82,"") | H82: =IF(Calculation!E82=Calculation!$A$142,Calculation!H82,"")
A83: =IF(Calculation!E83=Calculation!$A$142,Calculation!B83,"") | B83: =IF(Calculation!E83=Calculation!$A$142,Calculation!I83,"") | C83: =IF(Calculation!E83=Calculation!$A$142,Calculation!D83,"") | D83: =IF(Calculation!E83=Calculation!$A$142,Calculation!$A$79,"") | E83: =IF(Calculation!E83=Calculation!$A$142,Calculation!C83,"") | F83: =IF(Calculation!E83=Calculation!$A$142,Calculation!F83,"") | G83: =IF(Calculation!E83=Calculation!$A$142,Calculation!G83,"") | H83: =IF(Calculation!E83=Calculation!$A$142,Calculation!H83,"")
A84: =IF(Calculation!E84=Calculation!$A$142,Calculation!B84,"") | B84: =IF(Calculation!E84=Calculation!$A$142,Calculation!I84,"") | C84: =IF(Calculation!E84=Calculation!$A$142,Calculation!D84,"") | D84: =IF(Calculation!E84=Calculation!$A$142,Calculation!$A$79,"") | E84: =IF(Calculation!E84=Calculation!$A$142,Calculation!C84,"") | F84: =IF(Calculation!E84=Calculation!$A$142,Calculation!F84,"") | G84: =IF(Calculation!E84=Calculation!$A$142,Calculation!G84,"") | H84: =IF(Calculation!E84=Calculation!$A$142,Calculation!H84,"")
A85: =IF(Calculation!E85=Calculation!$A$142,Calculation!B85,"") | B85: =IF(Calculation!E85=Calculation!$A$142,Calculation!I85,"") | C85: =IF(Calculation!E85=Calculation!$A$142,Calculation!D85,"") -> NIL | D85: =IF(Calculation!E85=Calculation!$A$142,Calculation!$A$79,"") -> NIL | E85: =IF(Calculation!E85=Calculation!$A$142,Calculation!C85,"") -> NIL | F85: =IF(Calculation!E85=Calculation!$A$142,Calculation!F85,"") | G85: =IF(Calculation!E85=Calculation!$A$142,Calculation!G85,"") -> 0 | H85: =IF(Calculation!E85=Calculation!$A$142,Calculation!H85,"") -> 0
A86: =IF(Calculation!E86=Calculation!$A$142,Calculation!B86,"") | B86: =IF(Calculation!E86=Calculation!$A$142,Calculation!I86,"") | C86: =IF(Calculation!E86=Calculation!$A$142,Calculation!D86,"") | D86: =IF(Calculation!E86=Calculation!$A$142,Calculation!$A$79,"") | E86: =IF(Calculation!E86=Calculation!$A$142,Calculation!C86,"") | F86: =IF(Calculation!E86=Calculation!$A$142,Calculation!F86,"") | G86: =IF(Calculation!E86=Calculation!$A$142,Calculation!G86,"") | H86: =IF(Calculation!E86=Calculation!$A$142,Calculation!H86,"")
A87: =IF(Calculation!E87=Calculation!$A$142,Calculation!B87,"") | B87: =IF(Calculation!E87=Calculation!$A$142,Calculation!I87,"") | C87: =IF(Calculation!E87=Calculation!$A$142,Calculation!D87,"") | D87: =IF(Calculation!E87=Calculation!$A$142,Calculation!$A$79,"") | E87: =IF(Calculation!E87=Calculation!$A$142,Calculation!C87,"") | F87: =IF(Calculation!E87=Calculation!$A$142,Calculation!F87,"") | G87: =IF(Calculation!E87=Calculation!$A$142,Calculation!G87,"") | H87: =IF(Calculation!E87=Calculation!$A$142,Calculation!H87,"")
A88: =IF(Calculation!E88=Calculation!$A$142,Calculation!B88,"") | B88: =IF(Calculation!E88=Calculation!$A$142,Calculation!I88,"") | C88: =IF(Calculation!E88=Calculation!$A$142,Calculation!D88,"") | D88: =IF(Calculation!E88=Calculation!$A$142,Calculation!$A$79,"") | E88: =IF(Calculation!E88=Calculation!$A$142,Calculation!C88,"") | F88: =IF(Calculation!E88=Calculation!$A$142,Calculation!F88,"") | G88: =IF(Calculation!E88=Calculation!$A$142,Calculation!G88,"") | H88: =IF(Calculation!E88=Calculation!$A$142,Calculation!H88,"")
A89: =IF(Calculation!E89=Calculation!$A$142,Calculation!B89,"") | B89: =IF(Calculation!E89=Calculation!$A$142,Calculation!I89,"") | C89: =IF(Calculation!E89=Calculation!$A$142,Calculation!D89,"") | D89: =IF(Calculation!E89=Calculation!$A$142,Calculation!$A$79,"") | E89: =IF(Calculation!E89=Calculation!$A$142,Calculation!C89,"") | F89: =IF(Calculation!E89=Calculation!$A$142,Calculation!F89,"") | G89: =IF(Calculation!E89=Calculation!$A$142,Calculation!G89,"") | H89: =IF(Calculation!E89=Calculation!$A$142,Calculation!H89,"")
A90: =IF(Calculation!E90=Calculation!$A$142,Calculation!B90,"") | B90: =IF(Calculation!E90=Calculation!$A$142,Calculation!I90,"") | C90: =IF(Calculation!E90=Calculation!$A$142,Calculation!D90,"") | D90: =IF(Calculation!E90=Calculation!$A$142,Calculation!$A$79,"") | E90: =IF(Calculation!E90=Calculation!$A$142,Calculation!C90,"") | F90: =IF(Calculation!E90=Calculation!$A$142,Calculation!F90,"") | G90: =IF(Calculation!E90=Calculation!$A$142,Calculation!G90,"") | H90: =IF(Calculation!E90=Calculation!$A$142,Calculation!H90,"")
A91: =IF(Calculation!E91=Calculation!$A$142,Calculation!B91,"") | B91: =IF(Calculation!E91=Calculation!$A$142,Calculation!I91,"") | C91: =IF(Calculation!E91=Calculation!$A$142,Calculation!D91,"") | D91: =IF(Calculation!E91=Calculation!$A$142,Calculation!$A$79,"") | E91: =IF(Calculation!E91=Calculation!$A$142,Calculation!C91,"") | F91: =IF(Calculation!E91=Calculation!$A$142,Calculation!F91,"") | G91: =IF(Calculation!E91=Calculation!$A$142,Calculation!G91,"") | H91: =IF(Calculation!E91=Calculation!$A$142,Calculation!H91,"")
A92: =IF(Calculation!E92=Calculation!$A$142,Calculation!B92,"") | B92: =IF(Calculation!E92=Calculation!$A$142,Calculation!I92,"") | C92: =IF(Calculation!E92=Calculation!$A$142,Calculation!D92,"") | D92: =IF(Calculation!E92=Calculation!$A$142,Calculation!$A$92,"") | E92: =IF(Calculation!E92=Calculation!$A$142,Calculation!C92,"") | F92: =IF(Calculation!E92=Calculation!$A$142,Calculation!F92,"") | G92: =IF(Calculation!E92=Calculation!$A$142,Calculation!G92,"") | H92: =IF(Calculation!E92=Calculation!$A$142,Calculation!H92,"")
A93: =IF(Calculation!E93=Calculation!$A$142,Calculation!B93,"") | B93: =IF(Calculation!E93=Calculation!$A$142,Calculation!I93,"") | C93: =IF(Calculation!E93=Calculation!$A$142,Calculation!D93,"") | D93: =IF(Calculation!E93=Calculation!$A$142,Calculation!$A$92,"") | E93: =IF(Calculation!E93=Calculation!$A$142,Calculation!C93,"") | F93: =IF(Calculation!E93=Calculation!$A$142,Calculation!F93,"") | G93: =IF(Calculation!E93=Calculation!$A$142,Calculation!G93,"") | H93: =IF(Calculation!E93=Calculation!$A$142,Calculation!H93,"")
A94: =IF(Calculation!E94=Calculation!$A$142,Calculation!B94,"") | B94: =IF(Calculation!E94=Calculation!$A$142,Calculation!I94,"") | C94: =IF(Calculation!E94=Calculation!$A$142,Calculation!D94,"") | D94: =IF(Calculation!E94=Calculation!$A$142,Calculation!$A$92,"") | E94: =IF(Calculation!E94=Calculation!$A$142,Calculation!C94,"") | F94: =IF(Calculation!E94=Calculation!$A$142,Calculation!F94,"") | G94: =IF(Calculation!E94=Calculation!$A$142,Calculation!G94,"") | H94: =IF(Calculation!E94=Calculation!$A$142,Calculation!H94,"")
A95: =IF(Calculation!E95=Calculation!$A$142,Calculation!B95,"") | B95: =IF(Calculation!E95=Calculation!$A$142,Calculation!I95,"") | C95: =IF(Calculation!E95=Calculation!$A$142,Calculation!D95,"") | D95: =IF(Calculation!E95=Calculation!$A$142,Calculation!$A$92,"") | E95: =IF(Calculation!E95=Calculation!$A$142,Calculation!C95,"") | F95: =IF(Calculation!E95=Calculation!$A$142,Calculation!F95,"") | G95: =IF(Calculation!E95=Calculation!$A$142,Calculation!G95,"") | H95: =IF(Calculation!E95=Calculation!$A$142,Calculation!H95,"")
A96: =IF(Calculation!E96=Calculation!$A$142,Calculation!B96,"") | B96: =IF(Calculation!E96=Calculation!$A$142,Calculation!I96,"") | C96: =IF(Calculation!E96=Calculation!$A$142,Calculation!D96,"") | D96: =IF(Calculation!E96=Calculation!$A$142,Calculation!$A$92,"") | E96: =IF(Calculation!E96=Calculation!$A$142,Calculation!C96,"") | F96: =IF(Calculation!E96=Calculation!$A$142,Calculation!F96,"") | G96: =IF(Calculation!E96=Calculation!$A$142,Calculation!G96,"") | H96: =IF(Calculation!E96=Calculation!$A$142,Calculation!H96,"")
A97: =IF(Calculation!E97=Calculation!$A$142,Calculation!B97,"") | B97: =IF(Calculation!E97=Calculation!$A$142,Calculation!I97,"") | C97: =IF(Calculation!E97=Calculation!$A$142,Calculation!D97,"") | D97: =IF(Calculation!E97=Calculation!$A$142,Calculation!$A$92,"") | E97: =IF(Calculation!E97=Calculation!$A$142,Calculation!C97,"") | F97: =IF(Calculation!E97=Calculation!$A$142,Calculation!F97,"") | G97: =IF(Calculation!E97=Calculation!$A$142,Calculation!G97,"") | H97: =IF(Calculation!E97=Calculation!$A$142,Calculation!H97,"")
A98: =IF(Calculation!E98=Calculation!$A$142,Calculation!B98,"") | B98: =IF(Calculation!E98=Calculation!$A$142,Calculation!I98,"") | C98: =IF(Calculation!E98=Calculation!$A$142,Calculation!D98,"") | D98: =IF(Calculation!E98=Calculation!$A$142,Calculation!$A$92,"") | E98: =IF(Calculation!E98=Calculation!$A$142,Calculation!C98,"") | F98: =IF(Calculation!E98=Calculation!$A$142,Calculation!F98,"") | G98: =IF(Calculation!E98=Calculation!$A$142,Calculation!G98,"") | H98: =IF(Calculation!E98=Calculation!$A$142,Calculation!H98,"")
A99: =IF(Calculation!E99=Calculation!$A$142,Calculation!B99,"") | B99: =IF(Calculation!E99=Calculation!$A$142,Calculation!I99,"") | C99: =IF(Calculation!E99=Calculation!$A$142,Calculation!D99,"") | D99: =IF(Calculation!E99=Calculation!$A$142,Calculation!$A$92,"") | E99: =IF(Calculation!E99=Calculation!$A$142,Calculation!C99,"") | F99: =IF(Calculation!E99=Calculation!$A$142,Calculation!F99,"") | G99: =IF(Calculation!E99=Calculation!$A$142,Calculation!G99,"") | H99: =IF(Calculation!E99=Calculation!$A$142,Calculation!H99,"")
A100: =IF(Calculation!E100=Calculation!$A$142,Calculation!B100,"") | B100: =IF(Calculation!E100=Calculation!$A$142,Calculation!I100,"") | C100: =IF(Calculation!E100=Calculation!$A$142,Calculation!D100,"") | D100: =IF(Calculation!E100=Calculation!$A$142,Calculation!$A$92,"") | E100: =IF(Calculation!E100=Calculation!$A$142,Calculation!C100,"") | F100: =IF(Calculation!E100=Calculation!$A$142,Calculation!F100,"") | G100: =IF(Calculation!E100=Calculation!$A$142,Calculation!G100,"") | H100: =IF(Calculation!E100=Calculation!$A$142,Calculation!H100,"")
...

Sheet Finan
A1: FINAN WORKSHEET
A2: Date Assigned | B2: Last Date | C2: Assigned by | D2: Company | E2: Task | F2: Qty | G2: Amount | H2: Total | I2: Grand Total
A3: =IF(Calculation!E3=Calculation!$A$143,Calculation!B3,"") | B3: =IF(Calculation!E3=Calculation!$A$143,Calculation!I3,"") | C3: =IF(Calculation!E3=Calculation!$A$143,Calculation!D3,"") | D3: =IF(Calculation!E3=Calculation!$A$143,Calculation!$A$3,"") | E3: =IF(Calculation!E3=Calculation!$A$143,Calculation!C3,"") | F3: =IF(Calculation!E3=Calculation!$A$143,Calculation!F3,"") | G3: =IF(Calculation!E3=Calculation!$A$143,Calculation!G3,"") | H3: =IF(Calculation!E3=Calculation!$A$143,Calculation!H3,"") | I3: =SUMIF(Calculation!E3:E125,Calculation!$A$143,Calculation!H3:Z125) -> 0 | M3: Nomadism Industries
A4: =IF(Calculation!E4=Calculation!$A$143,Calculation!B4,"") | B4: =IF(Calculation!E4=Calculation!$A$143,Calculation!I4,"") | C4: =IF(Calculation!E4=Calculation!$A$143,Calculation!D4,"") | D4: =IF(Calculation!E4=Calculation!$A$143,Calculation!$A$3,"") | E4: =IF(Calculation!E4=Calculation!$A$143,Calculation!C4,"") | F4: =IF(Calculation!E4=Calculation!$A$143,Calculation!F4,"") | G4: =IF(Calculation!E4=Calculation!$A$143,Calculation!G4,"") | H4: =IF(Calculation!E4=Calculation!$A$143,Calculation!H4,"") | M4: 123 Your Street
A5: =IF(Calculation!E5=Calculation!$A$143,Calculation!B5,"") | B5: =IF(Calculation!E5=Calculation!$A$143,Calculation!I5,"") | C5: =IF(Calculation!E5=Calculation!$A$143,Calculation!D5,"") | D5: =IF(Calculation!E5=Calculation!$A$143,Calculation!$A$3,"") | E5: =IF(Calculation!E5=Calculation!$A$143,Calculation!C5,"") | F5: =IF(Calculation!E5=Calculation!$A$143,Calculation!F5,"") | G5: =IF(Calculation!E5=Calculation!$A$143,Calculation!G5,"") | H5: =IF(Calculation!E5=Calculation!$A$143,Calculation!H5,"") | M5: Your City, ST 12345
A6: =IF(Calculation!E6=Calculation!$A$143,Calculation!B6,"") | B6: =IF(Calculation!E6=Calculation!$A$143,Calculation!I6,"") | C6: =IF(Calculation!E6=Calculation!$A$143,Calculation!D6,"") | D6: =IF(Calculation!E6=Calculation!$A$143,Calculation!$A$3,"") | E6: =IF(Calculation!E6=Calculation!$A$143,Calculation!C6,"") | F6: =IF(Calculation!E6=Calculation!$A$143,Calculation!F6,"") | G6: =IF(Calculation!E6=Calculation!$A$143,Calculation!G6,"") | H6: =IF(Calculation!E6=Calculation!$A$143,Calculation!H6,"") | M6: (123) 456-7890
A7: =IF(Calculation!E7=Calculation!$A$143,Calculation!B7,"") | B7: =IF(Calculation!E7=Calculation!$A$143,Calculation!I7,"") | C7: =IF(Calculation!E7=Calculation!$A$143,Calculation!D7,"") | D7: =IF(Calculation!E7=Calculation!$A$143,Calculation!$A$3,"") | E7: =IF(Calculation!E7=Calculation!$A$143,Calculation!C7,"") | F7: =IF(Calculation!E7=Calculation!$A$143,Calculation!F7,"") | G7: =IF(Calculation!E7=Calculation!$A$143,Calculation!G7,"") | H7: =IF(Calculation!E7=Calculation!$A$143,Calculation!H7,"")
A8: =IF(Calculation!E8=Calculation!$A$143,Calculation!B8,"") | B8: =IF(Calculation!E8=Calculation!$A$143,Calculation!I8,"") | C8: =IF(Calculation!E8=Calculation!$A$142,Calculation!D8,"") | D8: =IF(Calculation!E8=Calculation!$A$143,Calculation!$A$3,"") | E8: =IF(Calculation!E8=Calculation!$A$143,Calculation!C8,"") | F8: =IF(Calculation!E8=Calculation!$A$143,Calculation!F8,"") | G8: =IF(Calculation!E8=Calculation!$A$143,Calculation!G8,"") | H8: =IF(Calculation!E8=Calculation!$A$143,Calculation!H8,"") | M8: Invoice
A9: =IF(Calculation!E9=Calculation!$A$143,Calculation!B9,"") | B9: =IF(Calculation!E9=Calculation!$A$143,Calculation!I9,"") | C9: =IF(Calculation!E9=Calculation!$A$143,Calculation!D9,"") | D9: =IF(Calculation!E9=Calculation!$A$143,Calculation!$A$3,"") | E9: =IF(Calculation!E9=Calculation!$A$143,Calculation!C9,"") | F9: =IF(Calculation!E9=Calculation!$A$143,Calculation!F9,"") | G9: =IF(Calculation!E9=Calculation!$A$143,Calculation!G9,"") | H9: =IF(Calculation!E9=Calculation!$A$143,Calculation!H9,"") | M9: Submitted on | P9: 45462
A10: =IF(Calculation!E10=Calculation!$A$143,Calculation!B10,"") | B10: =IF(Calculation!E10=Calculation!$A$143,Calculation!I10,"") | C10: =IF(Calculation!E10=Calculation!$A$143,Calculation!D10,"") | D10: =IF(Calculation!E10=Calculation!$A$143,Calculation!$A$3,"") | E10: =IF(Calculation!E10=Calculation!$A$143,Calculation!C10,"") | F10: =IF(Calculation!E10=Calculation!$A$143,Calculation!F10,"") | G10: =IF(Calculation!E10=Calculation!$A$143,Calculation!G10,"") | H10: =IF(Calculation!E10=Calculation!$A$143,Calculation!H10,"")
A11: =IF(Calculation!E11=Calculation!$A$143,Calculation!B11,"") | B11: =IF(Calculation!E11=Calculation!$A$143,Calculation!I11,"") | C11: =IF(Calculation!E11=Calculation!$A$143,Calculation!D11,"") | D11: =IF(Calculation!E11=Calculation!$A$143,Calculation!$A$3,"") | E11: =IF(Calculation!E11=Calculation!$A$143,Calculation!C11,"") | F11: =IF(Calculation!E11=Calculation!$A$143,Calculation!F11,"") | G11: =IF(Calculation!E11=Calculation!$A$143,Calculation!G11,"") | H11: =IF(Calculation!E11=Calculation!$A$143,Calculation!H11,"") | M11: Invoice for | P11: Payable to | R11: Invoice #
A12: =IF(Calculation!E12=Calculation!$A$143,Calculation!B12,"") | B12: =IF(Calculation!E12=Calculation!$A$143,Calculation!I12,"") | C12: =IF(Calculation!E12=Calculation!$A$143,Calculation!D12,"") | D12: =IF(Calculation!E12=Calculation!$A$143,Calculation!$A$3,"") | E12: =IF(Calculation!E12=Calculation!$A$143,Calculation!C12,"") | F12: =IF(Calculation!E12=Calculation!$A$143,Calculation!F12,"") | G12: =IF(Calculation!E12=Calculation!$A$143,Calculation!G12,"") | H12: =IF(Calculation!E12=Calculation!$A$143,Calculation!H12,"") | M12: =Calculation!A143 -> Finan | P12: =Calculation!A143 -> Finan | R12: 123456
A13: =IF(Calculation!E13=Calculation!$A$143,Calculation!B13,"") | B13: =IF(Calculation!E13=Calculation!$A$143,Calculation!I13,"") | C13: =IF(Calculation!E13=Calculation!$A$143,Calculation!D13,"") | D13: =IF(Calculation!E13=Calculation!$A$143,Calculation!$A$3,"") | E13: =IF(Calculation!E13=Calculation!$A$143,Calculation!C13,"") | F13: =IF(Calculation!E13=Calculation!$A$143,Calculation!F13,"") | G13: =IF(Calculation!E13=Calculation!$A$143,Calculation!G13,"") | H13: =IF(Calculation!E13=Calculation!$A$143,Calculation!H13,"") | M13: Company name
A14: =IF(Calculation!E14=Calculation!$A$143,Calculation!B14,"") | B14: =IF(Calculation!E14=Calculation!$A$143,Calculation!I14,"") | C14: =IF(Calculation!E14=Calculation!$A$143,Calculation!D14,"") | D14: =IF(Calculation!E14=Calculation!$A$143,Calculation!$A$3,"") | E14: =IF(Calculation!E14=Calculation!$A$143,Calculation!C14,"") | F14: =IF(Calculation!E14=Calculation!$A$143,Calculation!F14,"") | G14: =IF(Calculation!E14=Calculation!$A$143,Calculation!G14,"") | H14: =IF(Calculation!E14=Calculation!$A$143,Calculation!H14,"") | M14: Street address | P14: Project | R14: Due date
A15: =IF(Calculation!E15=Calculation!$A$143,Calculation!B15,"") | B15: =IF(Calculation!E15=Calculation!$A$143,Calculation!I15,"") | C15: =IF(Calculation!E15=Calculation!$A$143,Calculation!D15,"") | D15: =IF(Calculation!E15=Calculation!$A$143,Calculation!$A$3,"") | E15: =IF(Calculation!E15=Calculation!$A$143,Calculation!C15,"") | F15: =IF(Calculation!E15=Calculation!$A$143,Calculation!F15,"") | G15: =IF(Calculation!E15=Calculation!$A$143,Calculation!G15,"") | H15: =IF(Calculation!E15=Calculation!$A$143,Calculation!H15,"") | M15: City, State, Zip | P15: Project name | R15: 36531
A16: =IF(Calculation!E16=Calculation!$A$143,Calculation!B16,"") | B16: =IF(Calculation!E16=Calculation!$A$143,Calculation!I16,"") | C16: =IF(Calculation!E16=Calculation!$A$143,Calculation!D16,"") | D16: =IF(Calculation!E16=Calculation!$A$143,Calculation!$A$16,"") | E16: =IF(Calculation!E16=Calculation!$A$143,Calculation!C16,"") | F16: =IF(Calculation!E16=Calculation!$A$143,Calculation!F16,"") | G16: =IF(Calculation!E16=Calculation!$A$143,Calculation!G16,"") | H16: =IF(Calculation!E16=Calculation!$A$143,Calculation!H16,"")
A17: =IF(Calculation!E17=Calculation!$A$143,Calculation!B17,"") | B17: =IF(Calculation!E17=Calculation!$A$143,Calculation!I17,"") | C17: =IF(Calculation!E17=Calculation!$A$143,Calculation!D17,"") | D17: =IF(Calculation!E17=Calculation!$A$143,Calculation!$A$16,"") | E17: =IF(Calculation!E17=Calculation!$A$143,Calculation!C17,"") | F17: =IF(Calculation!E17=Calculation!$A$143,Calculation!F17,"") | G17: =IF(Calculation!E17=Calculation!$A$143,Calculation!G17,"") | H17: =IF(Calculation!E17=Calculation!$A$143,Calculation!H17,"")
A18: =IF(Calculation!E18=Calculation!$A$143,Calculation!B18,"") | B18: =IF(Calculation!E18=Calculation!$A$143,Calculation!I18,"") | C18: =IF(Calculation!E18=Calculation!$A$143,Calculation!D18,"") | D18: =IF(Calculation!E18=Calculation!$A$143,Calculation!$A$16,"") | E18: =IF(Calculation!E18=Calculation!$A$143,Calculation!C18,"") | F18: =IF(Calculation!E18=Calculation!$A$143,Calculation!F18,"") | G18: =IF(Calculation!E18=Calculation!$A$143,Calculation!G18,"") | H18: =IF(Calculation!E18=Calculation!$A$143,Calculation!H18,"") | M18: Description | Q18: Qty | R18: Unit price | S18: Total price
A19: =IF(Calculation!E19=Calculation!$A$143,Calculation!B19,"") | B19: =IF(Calculation!E19=Calculation!$A$143,Calculation!I19,"") | C19: =IF(Calculation!E19=Calculation!$A$143,Calculation!D19,"") | D19: =IF(Calculation!E19=Calculation!$A$143,Calculation!$A$16,"") | E19: =IF(Calculation!E19=Calculation!$A$143,Calculation!C19,"") | F19: =IF(Calculation!E19=Calculation!$A$143,Calculation!F19,"") | G19: =IF(Calculation!E19=Calculation!$A$143,Calculation!G19,"") | H19: =IF(Calculation!E19=Calculation!$A$143,Calculation!H19,"") | M19: Short Video Design | Q19: =SUMIFS(Calculation!$F$3:$F$125,Calculation!$C$3:$C$125,"Short Video Design",Calculation!$E$3:$E$125,Calculation!A143) -> 0 | R19: =(Calculation!B143) -> 100 | S19: =product(Q19,R19) -> 0
A20: =IF(Calculation!E20=Calculation!$A$143,Calculation!B20,"") | B20: =IF(Calculation!E20=Calculation!$A$143,Calculation!I20,"") | C20: =IF(Calculation!E20=Calculation!$A$143,Calculation!D20,"") | D20: =IF(Calculation!E20=Calculation!$A$143,Calculation!$A$16,"") | E20: =IF(Calculation!E20=Calculation!$A$143,Calculation!C20,"") | F20: =IF(Calculation!E20=Calculation!$A$143,Calculation!F20,"") | G20: =IF(Calculation!E20=Calculation!$A$143,Calculation!G20,"") | H20: =IF(Calculation!E20=Calculation!$A$143,Calculation!H20,"") | M20: Long Video Design | Q20: =SUMIFS(Calculation!$F$3:$F$125,Calculation!$C$3:$C$125,"Long Video Design",Calculation!$E$3:$E$125,Calculation!A143) -> 0 | R20: =(Calculation!C143) -> 200 | S20: =product(Q20,R20) -> 0
A21: =IF(Calculation!E21=Calculation!$A$143,Calculation!B21,"") | B21: =IF(Calculation!E21=Calculation!$A$143,Calculation!I21,"") | C21: =IF(Calculation!E21=Calculation!$A$143,Calculation!D21,"") | D21: =IF(Calculation!E21=Calculation!$A$143,Calculation!$A$16,"") | E21: =IF(Calculation!E21=Calculation!$A$143,Calculation!C21,"") | F21: =IF(Calculation!E21=Calculation!$A$143,Calculation!F21,"") | G21: =IF(Calculation!E21=Calculation!$A$143,Calculation!G21,"") | H21: =IF(Calculation!E21=Calculation!$A$143,Calculation!H21,"") | M21: Content for Poster | Q21: =SUMIFS(Calculation!$F$3:$F$125,Calculation!$C$3:$C$125,"Content for Poster",Calculation!$E$3:$E$125,Calculation!A143) -> 0 | R21: =(Calculation!D143) -> 25 | S21: =product(Q21,R21) -> 0
A22: =IF(Calculation!E22=Calculation!$A$143,Calculation!B22,"") | B22: =IF(Calculation!E22=Calculation!$A$143,Calculation!I22,"") | C22: =IF(Calculation!E22=Calculation!$A$143,Calculation!D22,"") | D22: =IF(Calculation!E22=Calculation!$A$143,Calculation!$A$16,"") | E22: =IF(Calculation!E22=Calculation!$A$143,Calculation!C22,"") | F22: =IF(Calculation!E22=Calculation!$A$143,Calculation!F22,"") | G22: =IF(Calculation!E22=Calculation!$A$143,Calculation!G22,"") | H22: =IF(Calculation!E22=Calculation!$A$143,Calculation!H22,"") | M22: Content for Video | Q22: =SUMIFS(Calculation!$F$3:$F$125,Calculation!$C$3:$C$125,"Content for Video",Calculation!$E$3:$E$125,Calculation!A143) -> 0 | R22: =(Calculation!E143) -> 75 | S22: =product(Q22,R22) -> 0
A23: =IF(Calculation!E23=Calculation!$A$143,Calculation!B23,"") | B23: =IF(Calculation!E23=Calculation!$A$143,Calculation!I23,"") | C23: =IF(Calculation!E23=Calculation!$A$143,Calculation!D23,"") | D23: =IF(Calculation!E23=Calculation!$A$143,Calculation!$A$16,"") | E23: =IF(Calculation!E23=Calculation!$A$143,Calculation!C23,"") | F23: =IF(Calculation!E23=Calculation!$A$143,Calculation!F23,"") | G23: =IF(Calculation!E23=Calculation!$A$143,Calculation!G23,"") | H23: =IF(Calculation!E23=Calculation!$A$143,Calculation!H23,"") | M23: Poster Design | Q23: =SUMIFS(Calculation!$F$3:$F$125,Calculation!$C$3:$C125,"Poster Design",Calculation!$E$3:$E$125,Calculation!A143) -> 1 | R23: =(Calculation!F143) -> 50 | S23: =product(Q23,R23) -> 50
A24: =IF(Calculation!E24=Calculation!$A$143,Calculation!B24,"") | B24: =IF(Calculation!E24=Calculation!$A$143,Calculation!I24,"") | C24: =IF(Calculation!E24=Calculation!$A$143,Calculation!D24,"") | D24: =IF(Calculation!E24=Calculation!$A$143,Calculation!$A$16,"") | E24: =IF(Calculation!E24=Calculation!$A$143,Calculation!C24,"") | F24: =IF(Calculation!E24=Calculation!$A$143,Calculation!F24,"") | G24: =IF(Calculation!E24=Calculation!$A$143,Calculation!G24,"") | H24: =IF(Calculation!E24=Calculation!$A$143,Calculation!H24,"") | M24: Notes: | R24: Subtotal | S24: =sum(S19:S23) -> 50
A25: =IF(Calculation!E25=Calculation!$A$143,Calculation!B25,"") | B25: =IF(Calculation!E25=Calculation!$A$143,Calculation!I25,"") | C25: =IF(Calculation!E25=Calculation!$A$143,Calculation!D25,"") | D25: =IF(Calculation!E25=Calculation!$A$143,Calculation!$A$16,"") | E25: =IF(Calculation!E25=Calculation!$A$143,Calculation!C25,"") | F25: =IF(Calculation!E25=Calculation!$A$143,Calculation!F25,"") | G25: =IF(Calculation!E25=Calculation!$A$143,Calculation!G25,"") | H25: =IF(Calculation!E25=Calculation!$A$143,Calculation!H25,"") | R25: Adjustments | S25: 0
A26: =IF(Calculation!E26=Calculation!$A$143,Calculation!B26,"") | B26: =IF(Calculation!E26=Calculation!$A$143,Calculation!I26,"") | C26: =IF(Calculation!E26=Calculation!$A$143,Calculation!D26,"") | D26: =IF(Calculation!E26=Calculation!$A$143,Calculation!$A$16,"") | E26: =IF(Calculation!E26=Calculation!$A$143,Calculation!C26,"") | F26: =IF(Calculation!E26=Calculation!$A$143,Calculation!F26,"") | G26: =IF(Calculation!E26=Calculation!$A$143,Calculation!G26,"") | H26: =IF(Calculation!E26=Calculation!$A$143,Calculation!H26,"") | R26: =sum(S24,S25) -> 50
A27: =IF(Calculation!E27=Calculation!$A$143,Calculation!B27,"") | B27: =IF(Calculation!E27=Calculation!$A$143,Calculation!I27,"") | C27: =IF(Calculation!E27=Calculation!$A$143,Calculation!D27,"") | D27: =IF(Calculation!E27=Calculation!$A$143,Calculation!$A$16,"") | E27: =IF(Calculation!E27=Calculation!$A$143,Calculation!C27,"") | F27: =IF(Calculation!E27=Calculation!$A$143,Calculation!F27,"") | G27: =IF(Calculation!E27=Calculation!$A$143,Calculation!G27,"") | H27: =IF(Calculation!E27=Calculation!$A$143,Calculation!H27,"")
A28: =IF(Calculation!E28=Calculation!$A$143,Calculation!B28,"") | B28: =IF(Calculation!E28=Calculation!$A$143,Calculation!I28,"") | C28: =IF(Calculation!E28=Calculation!$A$143,Calculation!D28,"") | D28: =IF(Calculation!E28=Calculation!$A$143,Calculation!$A$16,"") | E28: =IF(Calculation!E28=Calculation!$A$143,Calculation!C28,"") | F28: =IF(Calculation!E28=Calculation!$A$143,Calculation!F28,"") | G28: =IF(Calculation!E28=Calculation!$A$143,Calculation!G28,"") | H28: =IF(Calculation!E28=Calculation!$A$143,Calculation!H28,"")
A29: =IF(Calculation!E29=Calculation!$A$143,Calculation!B29,"") | B29: =IF(Calculation!E29=Calculation!$A$143,Calculation!I29,"") | C29: =IF(Calculation!E29=Calculation!$A$143,Calculation!D29,"") | D29: =IF(Calculation!E29=Calculation!$A$143,Calculation!$A$29,"") | E29: =IF(Calculation!E29=Calculation!$A$143,Calculation!C29,"") | F29: =IF(Calculation!E29=Calculation!$A$143,Calculation!F29,"") | G29: =IF(Calculation!E29=Calculation!$A$143,Calculation!G29,"") | H29: =IF(Calculation!E29=Calculation!$A$143,Calculation!H29,"")
A30: =IF(Calculation!E30=Calculation!$A$143,Calculation!B30,"") | B30: =IF(Calculation!E30=Calculation!$A$143,Calculation!I30,"") | C30: =IF(Calculation!E30=Calculation!$A$143,Calculation!D30,"") | D30: =IF(Calculation!E30=Calculation!$A$143,Calculation!$A$29,"") | E30: =IF(Calculation!E30=Calculation!$A$143,Calculation!C30,"") | F30: =IF(Calculation!E30=Calculation!$A$143,Calculation!F30,"") | G30: =IF(Calculation!E30=Calculation!$A$143,Calculation!G30,"") | H30: =IF(Calculation!E30=Calculation!$A$143,Calculation!H30,"")
A31: =IF(Calculation!E31=Calculation!$A$143,Calculation!B31,"") | B31: =IF(Calculation!E31=Calculation!$A$143,Calculation!I31,"") | C31: =IF(Calculation!E31=Calculation!$A$143,Calculation!D31,"") | D31: =IF(Calculation!E31=Calculation!$A$143,Calculation!$A$29,"") | E31: =IF(Calculation!E31=Calculation!$A$143,Calculation!C31,"") | F31: =IF(Calculation!E31=Calculation!$A$143,Calculation!F31,"") | G31: =IF(Calculation!E31=Calculation!$A$143,Calculation!G31,"") | H31: =IF(Calculation!E31=Calculation!$A$143,Calculation!H31,"")
A32: =IF(Calculation!E32=Calculation!$A$143,Calculation!B32,"") | B32: =IF(Calculation!E32=Calculation!$A$143,Calculation!I32,"") | C32: =IF(Calculation!E32=Calculation!$A$143,Calculation!D32,"") | D32: =IF(Calculation!E32=Calculation!$A$143,Calculation!$A$29,"") | E32: =IF(Calculation!E32=Calculation!$A$143,Calculation!C32,"") | F32: =IF(Calculation!E32=Calculation!$A$143,Calculation!F32,"") | G32: =IF(Calculation!E32=Calculation!$A$143,Calculation!G32,"") | H32: =IF(Calculation!E32=Calculation!$A$143,Calculation!H32,"")
A33: =IF(Calculation!E33=Calculation!$A$143,Calculation!B33,"") | B33: =IF(Calculation!E33=Calculation!$A$143,Calculation!I33,"") | C33: =IF(Calculation!E33=Calculation!$A$143,Calculation!D33,"") | D33: =IF(Calculation!E33=Calculation!$A$143,Calculation!$A$29,"") | E33: =IF(Calculation!E33=Calculation!$A$143,Calculation!C33,"") | F33: =IF(Calculation!E33=Calculation!$A$143,Calculation!F33,"") | G33: =IF(Calculation!E33=Calculation!$A$143,Calculation!G33,"") | H33: =IF(Calculation!E33=Calculation!$A$143,Calculation!H33,"")
A34: =IF(Calculation!E34=Calculation!$A$143,Calculation!B34,"") | B34: =IF(Calculation!E34=Calculation!$A$143,Calculation!I34,"") | C34: =IF(Calculation!E34=Calculation!$A$143,Calculation!D34,"") | D34: =IF(Calculation!E34=Calculation!$A$143,Calculation!$A$29,"") | E34: =IF(Calculation!E34=Calculation!$A$143,Calculation!C34,"") | F34: =IF(Calculation!E34=Calculation!$A$143,Calculation!F34,"") | G34: =IF(Calculation!E34=Calculation!$A$143,Calculation!G34,"") | H34: =IF(Calculation!E34=Calculation!$A$143,Calculation!H34,"")
A35: =IF(Calculation!E35=Calculation!$A$143,Calculation!B35,"") | B35: =IF(Calculation!E35=Calculation!$A$143,Calculation!I35,"") | C35: =IF(Calculation!E35=Calculation!$A$143,Calculation!D35,"") | D35: =IF(Calculation!E35=Calculation!$A$143,Calculation!$A$29,"") | E35: =IF(Calculation!E35=Calculation!$A$143,Calculation!C35,"") | F35: =IF(Calculation!E35=Calculation!$A$143,Calculation!F35,"") | G35: =IF(Calculation!E35=Calculation!$A$143,Calculation!G35,"") | H35: =IF(Calculation!E35=Calculation!$A$143,Calculation!H35,"")
A36: =IF(Calculation!E36=Calculation!$A$143,Calculation!B36,"") | B36: =IF(Calculation!E36=Calculation!$A$143,Calculation!I36,"") | C36: =IF(Calculation!E36=Calculation!$A$143,Calculation!D36,"") | D36: =IF(Calculation!E36=Calculation!$A$143,Calculation!$A$29,"") | E36: =IF(Calculation!E36=Calculation!$A$143,Calculation!C36,"") | F36: =IF(Calculation!E36=Calculation!$A$143,Calculation!F36,"") | G36: =IF(Calculation!E36=Calculation!$A$143,Calculation!G36,"") | H36: =IF(Calculation!E36=Calculation!$A$143,Calculation!H36,"")
A37: =IF(Calculation!E37=Calculation!$A$143,Calculation!B37,"") | B37: =IF(Calculation!E37=Calculation!$A$143,Calculation!I37,"") | C37: =IF(Calculation!E37=Calculation!$A$143,Calculation!D37,"") | D37: =IF(Calculation!E37=Calculation!$A$143,Calculation!$A$29,"") | E37: =IF(Calculation!E37=Calculation!$A$143,Calculation!C37,"") | F37: =IF(Calculation!E37=Calculation!$A$143,Calculation!F37,"") | G37: =IF(Calculation!E37=Calculation!$A$143,Calculation!G37,"") | H37: =IF(Calculation!E37=Calculation!$A$143,Calculation!H37,"")
A38: =IF(Calculation!E38=Calculation!$A$143,Calculation!B38,"") | B38: =IF(Calculation!E38=Calculation!$A$143,Calculation!I38,"") | C38: =IF(Calculation!E38=Calculation!$A$143,Calculation!D38,"") | D38: =IF(Calculation!E38=Calculation!$A$143,Calculation!$A$29,"") | E38: =IF(Calculation!E38=Calculation!$A$143,Calculation!C38,"") | F38: =IF(Calculation!E38=Calculation!$A$143,Calculation!F38,"") | G38: =IF(Calculation!E38=Calculation!$A$143,Calculation!G38,"") | H38: =IF(Calculation!E38=Calculation!$A$143,Calculation!H38,"")
A39: =IF(Calculation!E39=Calculation!$A$143,Calculation!B39,"") | B39: =IF(Calculation!E39=Calculation!$A$143,Calculation!I39,"") | C39: =IF(Calculation!E39=Calculation!$A$143,Calculation!D39,"") | D39: =IF(Calculation!E39=Calculation!$A$143,Calculation!$A$29,"") | E39: =IF(Calculation!E39=Calculation!$A$143,Calculation!C39,"") | F39: =IF(Calculation!E39=Calculation!$A$143,Calculation!F39,"") | G39: =IF(Calculation!E39=Calculation!$A$143,Calculation!G39,"") | H39: =IF(Calculation!E39=Calculation!$A$143,Calculation!H39,"")
A40: =IF(Calculation!E40=Calculation!$A$143,Calculation!B40,"") | B40: =IF(Calculation!E40=Calculation!$A$143,Calculation!I40,"") | C40: =IF(Calculation!E40=Calculation!$A$143,Calculation!D40,"") | D40: =IF(Calculation!E40=Calculation!$A$143,Calculation!$A$29,"") | E40: =IF(Calculation!E40=Calculation!$A$143,Calculation!C40,"") | F40: =IF(Calculation!E40=Calculation!$A$143,Calculation!F40,"") | G40: =IF(Calculation!E40=Calculation!$A$143,Calculation!G40,"") | H40: =IF(Calculation!E40=Calculation!$A$143,Calculation!H40,"")
A41: =IF(Calculation!E41=Calculation!$A$143,Calculation!B41,"") | B41: =IF(Calculation!E41=Calculation!$A$143,Calculation!I41,"") | C41: =IF(Calculation!E41=Calculation!$A$143,Calculation!D41,"") | D41: =IF(Calculation!E41=Calculation!$A$143,Calculation!$A$41,"") | E41: =IF(Calculation!E41=Calculation!$A$143,Calculation!C41,"") | F41: =IF(Calculation!E41=Calculation!$A$143,Calculation!F41,"") | G41: =IF(Calculation!E41=Calculation!$A$143,Calculation!G41,"") | H41: =IF(Calculation!E41=Calculation!$A$143,Calculation!H41,"")
A42: =IF(Calculation!E42=Calculation!$A$143,Calculation!B42,"") | B42: =IF(Calculation!E42=Calculation!$A$143,Calculation!I42,"") | C42: =IF(Calculation!E42=Calculation!$A$143,Calculation!D42,"") | D42: =IF(Calculation!E42=Calculation!$A$143,Calculation!$A$41,"") | E42: =IF(Calculation!E42=Calculation!$A$143,Calculation!C42,"") | F42: =IF(Calculation!E42=Calculation!$A$143,Calculation!F42,"") | G42: =IF(Calculation!E42=Calculation!$A$143,Calculation!G42,"") | H42: =IF(Calculation!E42=Calculation!$A$143,Calculation!H42,"")
A43: =IF(Calculation!E43=Calculation!$A$143,Calculation!B43,"") | B43: =IF(Calculation!E43=Calculation!$A$143,Calculation!I43,"") | C43: =IF(Calculation!E43=Calculation!$A$143,Calculation!D43,"") | D43: =IF(Calculation!E43=Calculation!$A$143,Calculation!$A$41,"") | E43: =IF(Calculation!E43=Calculation!$A$143,Calculation!C43,"") | F43: =IF(Calculation!E43=Calculation!$A$143,Calculation!F43,"") | G43: =IF(Calculation!E43=Calculation!$A$143,Calculation!G43,"") | H43: =IF(Calculation!E43=Calculation!$A$143,Calculation!H43,"")
A44: =IF(Calculation!E44=Calculation!$A$143,Calculation!B44,"") | B44: =IF(Calculation!E44=Calculation!$A$143,Calculation!I44,"") | C44: =IF(Calculation!E44=Calculation!$A$143,Calculation!D44,"") | D44: =IF(Calculation!E44=Calculation!$A$143,Calculation!$A$41,"") | E44: =IF(Calculation!E44=Calculation!$A$143,Calculation!C44,"") | F44: =IF(Calculation!E44=Calculation!$A$143,Calculation!F44,"") | G44: =IF(Calculation!E44=Calculation!$A$143,Calculation!G44,"") | H44: =IF(Calculation!E44=Calculation!$A$143,Calculation!H44,"")
A45: =IF(Calculation!E45=Calculation!$A$143,Calculation!B45,"") | B45: =IF(Calculation!E45=Calculation!$A$143,Calculation!I45,"") | C45: =IF(Calculation!E45=Calculation!$A$143,Calculation!D45,"") | D45: =IF(Calculation!E45=Calculation!$A$143,Calculation!$A$41,"") | E45: =IF(Calculation!E45=Calculation!$A$143,Calculation!C45,"") | F45: =IF(Calculation!E45=Calculation!$A$143,Calculation!F45,"") | G45: =IF(Calculation!E45=Calculation!$A$143,Calculation!G45,"") | H45: =IF(Calculation!E45=Calculation!$A$143,Calculation!H45,"")
A46: =IF(Calculation!E46=Calculation!$A$143,Calculation!B46,"") | B46: =IF(Calculation!E46=Calculation!$A$143,Calculation!I46,"") | C46: =IF(Calculation!E46=Calculation!$A$143,Calculation!D46,"") | D46: =IF(Calculation!E46=Calculation!$A$143,Calculation!$A$41,"") | E46: =IF(Calculation!E46=Calculation!$A$143,Calculation!C46,"") | F46: =IF(Calculation!E46=Calculation!$A$143,Calculation!F46,"") | G46: =IF(Calculation!E46=Calculation!$A$143,Calculation!G46,"") | H46: =IF(Calculation!E46=Calculation!$A$143,Calculation!H46,"")
A47: =IF(Calculation!E47=Calculation!$A$143,Calculation!B47,"") | B47: =IF(Calculation!E47=Calculation!$A$143,Calculation!I47,"") | C47: =IF(Calculation!E47=Calculation!$A$143,Calculation!D47,"") | D47: =IF(Calculation!E47=Calculation!$A$143,Calculation!$A$41,"") | E47: =IF(Calculation!E47=Calculation!$A$143,Calculation!C47,"") | F47: =IF(Calculation!E47=Calculation!$A$143,Calculation!F47,"") | G47: =IF(Calculation!E47=Calculation!$A$143,Calculation!G47,"") | H47: =IF(Calculation!E47=Calculation!$A$143,Calculation!H47,"")
A48: =IF(Calculation!E48=Calculation!$A$143,Calculation!B48,"") | B48: =IF(Calculation!E48=Calculation!$A$143,Calculation!I48,"") | C48: =IF(Calculation!E48=Calculation!$A$143,Calculation!D48,"") | D48: =IF(Calculation!E48=Calculation!$A$143,Calculation!$A$41,"") | E48: =IF(Calculation!E48=Calculation!$A$143,Calculation!C48,"") | F48: =IF(Calculation!E48=Calculation!$A$143,Calculation!F48,"") | G48: =IF(Calculation!E48=Calculation!$A$143,Calculation!G48,"") | H48: =IF(Calculation!E48=Calculation!$A$143,Calculation!H48,"")
A49: =IF(Calculation!E49=Calculation!$A$143,Calculation!B49,"") | B49: =IF(Calculation!E49=Calculation!$A$143,Calculation!I49,"") | C49: =IF(Calculation!E49=Calculation!$A$143,Calculation!D49,"") | D49: =IF(Calculation!E49=Calculation!$A$143,Calculation!$A$41,"") | E49: =IF(Calculation!E49=Calculation!$A$143,Calculation!C49,"") | F49: =IF(Calculation!E49=Calculation!$A$143,Calculation!F49,"") | G49: =IF(Calculation!E49=Calculation!$A$143,Calculation!G49,"") | H49: =IF(Calculation!E49=Calculation!$A$143,Calculation!H49,"")
A50: =IF(Calculation!E50=Calculation!$A$143,Calculation!B50,"") | B50: =IF(Calculation!E50=Calculation!$A$143,Calculation!I50,"") | C50: =IF(Calculation!E50=Calculation!$A$143,Calculation!D50,"") | D50: =IF(Calculation!E50=Calculation!$A$143,Calculation!$A$41,"") | E50: =IF(Calculation!E50=Calculation!$A$143,Calculation!C50,"") | F50: =IF(Calculation!E50=Calculation!$A$143,Calculation!F50,"") | G50: =IF(Calculation!E50=Calculation!$A$143,Calculation!G50,"") | H50: =IF(Calculation!E50=Calculation!$A$143,Calculation!H50,"")
A51: =IF(Calculation!E51=Calculation!$A$143,Calculation!B51,"") | B51: =IF(Calculation!E51=Calculation!$A$143,Calculation!I51,"") | C51: =IF(Calculation!E51=Calculation!$A$143,Calculation!D51,"") | D51: =IF(Calculation!E51=Calculation!$A$143,Calculation!$A$41,"") | E51: =IF(Calculation!E51=Calculation!$A$143,Calculation!C51,"") | F51: =IF(Calculation!E51=Calculation!$A$143,Calculation!F51,"") | G51: =IF(Calculation!E51=Calculation!$A$143,Calculation!G51,"") | H51: =IF(Calculation!E51=Calculation!$A$143,Calculation!H51,"")
A52: =IF(Calculation!E52=Calculation!$A$143,Calculation!B52,"") | B52: =IF(Calculation!E52=Calculation!$A$143,Calculation!I52,"") | C52: =IF(Calculation!E52=Calculation!$A$143,Calculation!D52,"") | D52: =IF(Calculation!E52=Calculation!$A$143,Calculation!$A$41,"") | E52: =IF(Calculation!E52=Calculation!$A$143,Calculation!C52,"") | F52: =IF(Calculation!E52=Calculation!$A$143,Calculation!F52,"") | G52: =IF(Calculation!E52=Calculation!$A$143,Calculation!G52,"") | H52: =IF(Calculation!E52=Calculation!$A$143,Calculation!H52,"")
A53: =IF(Calculation!E53=Calculation!$A$143,Calculation!B53,"") | B53: =IF(Calculation!E53=Calculation!$A$143,Calculation!I53,"") | C53: =IF(Calculation!E53=Calculation!$A$143,Calculation!D53,"") | D53: =IF(Calculation!E53=Calculation!$A$143,Calculation!$A$41,"") | E53: =IF(Calculation!E53=Calculation!$A$143,Calculation!C53,"") | F53: =IF(Calculation!E53=Calculation!$A$143,Calculation!F53,"") | G53: =IF(Calculation!E53=Calculation!$A$143,Calculation!G53,"") | H53: =IF(Calculation!E53=Calculation!$A$143,Calculation!H53,"")
A54: =IF(Calculation!E54=Calculation!$A$143,Calculation!B54,"") | B54: =IF(Calculation!E54=Calculation!$A$143,Calculation!I54,"") | C54: =IF(Calculation!E54=Calculation!$A$143,Calculation!D54,"") | D54: =IF(Calculation!E54=Calculation!$A$143,Calculation!$A$54,"") | E54: =IF(Calculation!E54=Calculation!$A$143,Calculation!C54,"") | F54: =IF(Calculation!E54=Calculation!$A$143,Calculation!F54,"") | G54: =IF(Calculation!E54=Calculation!$A$143,Calculation!G54,"") | H54: =IF(Calculation!E54=Calculation!$A$143,Calculation!H54,"")
A55: =IF(Calculation!E55=Calculation!$A$143,Calculation!B55,"") | B55: =IF(Calculation!E55=Calculation!$A$143,Calculation!I55,"") | C55: =IF(Calculation!E55=Calculation!$A$143,Calculation!D55,"") | D55: =IF(Calculation!E55=Calculation!$A$143,Calculation!$A$54,"") | E55: =IF(Calculation!E55=Calculation!$A$143,Calculation!C55,"") | F55: =IF(Calculation!E55=Calculation!$A$143,Calculation!F55,"") | G55: =IF(Calculation!E55=Calculation!$A$143,Calculation!G55,"") | H55: =IF(Calculation!E55=Calculation!$A$143,Calculation!H55,"")
A56: =IF(Calculation!E56=Calculation!$A$143,Calculation!B56,"") | B56: =IF(Calculation!E56=Calculation!$A$143,Calculation!I56,"") | C56: =IF(Calculation!E56=Calculation!$A$143,Calculation!D56,"") | D56: =IF(Calculation!E56=Calculation!$A$143,Calculation!$A$54,"") | E56: =IF(Calculation!E56=Calculation!$A$143,Calculation!C56,"") | F56: =IF(Calculation!E56=Calculation!$A$143,Calculation!F56,"") | G56: =IF(Calculation!E56=Calculation!$A$143,Calculation!G56,"") | H56: =IF(Calculation!E56=Calculation!$A$143,Calculation!H56,"")
A57: =IF(Calculation!E57=Calculation!$A$143,Calculation!B57,"") | B57: =IF(Calculation!E57=Calculation!$A$143,Calculation!I57,"") | C57: =IF(Calculation!E57=Calculation!$A$143,Calculation!D57,"") | D57: =IF(Calculation!E57=Calculation!$A$143,Calculation!$A$54,"") | E57: =IF(Calculation!E57=Calculation!$A$143,Calculation!C57,"") | F57: =IF(Calculation!E57=Calculation!$A$143,Calculation!F57,"") | G57: =IF(Calculation!E57=Calculation!$A$143,Calculation!G57,"") | H57: =IF(Calculation!E57=Calculation!$A$143,Calculation!H57,"")
A58: =IF(Calculation!E58=Calculation!$A$143,Calculation!B58,"") | B58: =IF(Calculation!E58=Calculation!$A$143,Calculation!I58,"") | C58: =IF(Calculation!E58=Calculation!$A$143,Calculation!D58,"") | D58: =IF(Calculation!E58=Calculation!$A$143,Calculation!$A$54,"") | E58: =IF(Calculation!E58=Calculation!$A$143,Calculation!C58,"") | F58: =IF(Calculation!E58=Calculation!$A$143,Calculation!F58,"") | G58: =IF(Calculation!E58=Calculation!$A$143,Calculation!G58,"") | H58: =IF(Calculation!E58=Calculation!$A$143,Calculation!H58,"")
A59: =IF(Calculation!E59=Calculation!$A$143,Calculation!B59,"") | B59: =IF(Calculation!E59=Calculation!$A$143,Calculation!I59,"") | C59: =IF(Calculation!E59=Calculation!$A$143,Calculation!D59,"") | D59: =IF(Calculation!E59=Calculation!$A$143,Calculation!$A$54,"") | E59: =IF(Calculation!E59=Calculation!$A$143,Calculation!C59,"") | F59: =IF(Calculation!E59=Calculation!$A$143,Calculation!F59,"") | G59: =IF(Calculation!E59=Calculation!$A$143,Calculation!G59,"") | H59: =IF(Calculation!E59=Calculation!$A$143,Calculation!H59,"")
A60: =IF(Calculation!E60=Calculation!$A$143,Calculation!B60,"") | B60: =IF(Calculation!E60=Calculation!$A$143,Calculation!I60,"") | C60: =IF(Calculation!E60=Calculation!$A$143,Calculation!D60,"") | D60: =IF(Calculation!E60=Calculation!$A$143,Calculation!$A$54,"") | E60: =IF(Calculation!E60=Calculation!$A$143,Calculation!C60,"") | F60: =IF(Calculation!E60=Calculation!$A$143,Calculation!F60,"") | G60: =IF(Calculation!E60=Calculation!$A$143,Calculation!G60,"") | H60: =IF(Calculation!E60=Calculation!$A$143,Calculation!H60,"")
A61: =IF(Calculation!E61=Calculation!$A$143,Calculation!B61,"") | B61: =IF(Calculation!E61=Calculation!$A$143,Calculation!I61,"") | C61: =IF(Calculation!E61=Calculation!$A$143,Calculation!D61,"") | D61: =IF(Calculation!E61=Calculation!$A$143,Calculation!$A$54,"") | E61: =IF(Calculation!E61=Calculation!$A$143,Calculation!C61,"") | F61: =IF(Calculation!E61=Calculation!$A$143,Calculation!F61,"") | G61: =IF(Calculation!E61=Calculation!$A$143,Calculation!G61,"") | H61: =IF(Calculation!E61=Calculation!$A$143,Calculation!H61,"")
A62: =IF(Calculation!E62=Calculation!$A$143,Calculation!B62,"") | B62: =IF(Calculation!E62=Calculation!$A$143,Calculation!I62,"") | C62: =IF(Calculation!E62=Calculation!$A$143,Calculation!D62,"") | D62: =IF(Calculation!E62=Calculation!$A$143,Calculation!$A$54,"") | E62: =IF(Calculation!E62=Calculation!$A$143,Calculation!C62,"") | F62: =IF(Calculation!E62=Calculation!$A$143,Calculation!F62,"") | G62: =IF(Calculation!E62=Calculation!$A$143,Calculation!G62,"") | H62: =IF(Calculation!E62=Calculation!$A$143,Calculation!H62,"")
A63: =IF(Calculation!E63=Calculation!$A$143,Calculation!B63,"") | B63: =IF(Calculation!E63=Calculation!$A$143,Calculation!I63,"") | C63: =IF(Calculation!E63=Calculation!$A$143,Calculation!D63,"") | D63: =IF(Calculation!E63=Calculation!$A$143,Calculation!$A$54,"") | E63: =IF(Calculation!E63=Calculation!$A$143,Calculation!C63,"") | F63: =IF(Calculation!E63=Calculation!$A$143,Calculation!F63,"") | G63: =IF(Calculation!E63=Calculation!$A$143,Calculation!G63,"") | H63: =IF(Calculation!E63=Calculation!$A$143,Calculation!H63,"")
A64: =IF(Calculation!E64=Calculation!$A$143,Calculation!B64,"") | B64: =IF(Calculation!E64=Calculation!$A$143,Calculation!I64,"") | C64: =IF(Calculation!E64=Calculation!$A$143,Calculation!D64,"") | D64: =IF(Calculation!E64=Calculation!$A$143,Calculation!$A$54,"") | E64: =IF(Calculation!E64=Calculation!$A$143,Calculation!C64,"") | F64: =IF(Calculation!E64=Calculation!$A$143,Calculation!F64,"") | G64: =IF(Calculation!E64=Calculation!$A$143,Calculation!G64,"") | H64: =IF(Calculation!E64=Calculation!$A$143,Calculation!H64,"")
A65: =IF(Calculation!E65=Calculation!$A$143,Calculation!B65,"") | B65: =IF(Calculation!E65=Calculation!$A$143,Calculation!I65,"") | C65: =IF(Calculation!E65=Calculation!$A$143,Calculation!D65,"") | D65: =IF(Calculation!E65=Calculation!$A$143,Calculation!$A$54,"") | E65: =IF(Calculation!E65=Calculation!$A$143,Calculation!C65,"") | F65: =IF(Calculation!E65=Calculation!$A$143,Calculation!F65,"") | G65: =IF(Calculation!E65=Calculation!$A$143,Calculation!G65,"") | H65: =IF(Calculation!E65=Calculation!$A$143,Calculation!H65,"")
A66: =IF(Calculation!E66=Calculation!$A$143,Calculation!B66,"") | B66: =IF(Calculation!E66=Calculation!$A$143,Calculation!I66,"") | C66: =IF(Calculation!E66=Calculation!$A$143,Calculation!D66,"") | D66: =IF(Calculation!E66=Calculation!$A$143,Calculation!$A$66,"") | E66: =IF(Calculation!E66=Calculation!$A$143,Calculation!C66,"") | F66: =IF(Calculation!E66=Calculation!$A$143,Calculation!F66,"") | G66: =IF(Calculation!E66=Calculation!$A$143,Calculation!G66,"") | H66: =IF(Calculation!E66=Calculation!$A$143,Calculation!H66,"")
A67: =IF(Calculation!E67=Calculation!$A$143,Calculation!B67,"") | B67: =IF(Calculation!E67=Calculation!$A$143,Calculation!I67,"") | C67: =IF(Calculation!E67=Calculation!$A$143,Calculation!D67,"") | D67: =IF(Calculation!E67=Calculation!$A$143,Calculation!$A$66,"") | E67: =IF(Calculation!E67=Calculation!$A$143,Calculation!C67,"") | F67: =IF(Calculation!E67=Calculation!$A$143,Calculation!F67,"") | G67: =IF(Calculation!E67=Calculation!$A$143,Calculation!G67,"") | H67: =IF(Calculation!E67=Calculation!$A$143,Calculation!H67,"")
A68: =IF(Calculation!E68=Calculation!$A$143,Calculation!B68,"") | B68: =IF(Calculation!E68=Calculation!$A$143,Calculation!I68,"") | C68: =IF(Calculation!E68=Calculation!$A$143,Calculation!D68,"") | D68: =IF(Calculation!E68=Calculation!$A$143,Calculation!$A$66,"") | E68: =IF(Calculation!E68=Calculation!$A$143,Calculation!C68,"") | F68: =IF(Calculation!E68=Calculation!$A$143,Calculation!F68,"") | G68: =IF(Calculation!E68=Calculation!$A$143,Calculation!G68,"") | H68: =IF(Calculation!E68=Calculation!$A$143,Calculation!H68,"")
A69: =IF(Calculation!E69=Calculation!$A$143,Calculation!B69,"") | B69: =IF(Calculation!E69=Calculation!$A$143,Calculation!I69,"") | C69: =IF(Calculation!E69=Calculation!$A$143,Calculation!D69,"") | D69: =IF(Calculation!E69=Calculation!$A$143,Calculation!$A$66,"") | E69: =IF(Calculation!E69=Calculation!$A$143,Calculation!C69,"") | F69: =IF(Calculation!E69=Calculation!$A$143,Calculation!F69,"") | G69: =IF(Calculation!E69=Calculation!$A$143,Calculation!G69,"") | H69: =IF(Calculation!E69=Calculation!$A$143,Calculation!H69,"")
A70: =IF(Calculation!E70=Calculation!$A$143,Calculation!B70,"") | B70: =IF(Calculation!E70=Calculation!$A$143,Calculation!I70,"") | C70: =IF(Calculation!E70=Calculation!$A$143,Calculation!D70,"") | D70: =IF(Calculation!E70=Calculation!$A$143,Calculation!$A$66,"") | E70: =IF(Calculation!E70=Calculation!$A$143,Calculation!C70,"") | F70: =IF(Calculation!E70=Calculation!$A$143,Calculation!F70,"") | G70: =IF(Calculation!E70=Calculation!$A$143,Calculation!G70,"") | H70: =IF(Calculation!E70=Calculation!$A$143,Calculation!H70,"")
A71: =IF(Calculation!E71=Calculation!$A$143,Calculation!B71,"") | B71: =IF(Calculation!E71=Calculation!$A$143,Calculation!I71,"") | C71: =IF(Calculation!E71=Calculation!$A$143,Calculation!D71,"") | D71: =IF(Calculation!E71=Calculation!$A$143,Calculation!$A$66,"") | E71: =IF(Calculation!E71=Calculation!$A$143,Calculation!C71,"") | F71: =IF(Calculation!E71=Calculation!$A$143,Calculation!F71,"") | G71: =IF(Calculation!E71=Calculation!$A$143,Calculation!G71,"") | H71: =IF(Calculation!E71=Calculation!$A$143,Calculation!H71,"")
A72: =IF(Calculation!E72=Calculation!$A$143,Calculation!B72,"") | B72: =IF(Calculation!E72=Calculation!$A$143,Calculation!I72,"") | C72: =IF(Calculation!E72=Calculation!$A$143,Calculation!D72,"") | D72: =IF(Calculation!E72=Calculation!$A$143,Calculation!$A$66,"") | E72: =IF(Calculation!E72=Calculation!$A$143,Calculation!C72,"") | F72: =IF(Calculation!E72=Calculation!$A$143,Calculation!F72,"") | G72: =IF(Calculation!E72=Calculation!$A$143,Calculation!G72,"") | H72: =IF(Calculation!E72=Calculation!$A$143,Calculation!H72,"")
A73: =IF(Calculation!E73=Calculation!$A$143,Calculation!B73,"") | B73: =IF(Calculation!E73=Calculation!$A$143,Calculation!I73,"") | C73: =IF(Calculation!E73=Calculation!$A$143,Calculation!D73,"") | D73: =IF(Calculation!E73=Calculation!$A$143,Calculation!$A$66,"") | E73: =IF(Calculation!E73=Calculation!$A$143,Calculation!C73,"") | F73: =IF(Calculation!E73=Calculation!$A$143,Calculation!F73,"") | G73: =IF(Calculation!E73=Calculation!$A$143,Calculation!G73,"") | H73: =IF(Calculation!E73=Calculation!$A$143,Calculation!H73,"")
A74: =IF(Calculation!E74=Calculation!$A$143,Calculation!B74,"") | B74: =IF(Calculation!E74=Calculation!$A$143,Calculation!I74,"") | C74: =IF(Calculation!E74=Calculation!$A$143,Calculation!D74,"") | D74: =IF(Calculation!E74=Calculation!$A$143,Calculation!$A$66,"") | E74: =IF(Calculation!E74=Calculation!$A$143,Calculation!C74,"") | F74: =IF(Calculation!E74=Calculation!$A$143,Calculation!F74,"") | G74: =IF(Calculation!E74=Calculation!$A$143,Calculation!G74,"") | H74: =IF(Calculation!E74=Calculation!$A$143,Calculation!H74,"")
A75: =IF(Calculation!E75=Calculation!$A$143,Calculation!B75,"") | B75: =IF(Calculation!E75=Calculation!$A$143,Calculation!I75,"") | C75: =IF(Calculation!E75=Calculation!$A$143,Calculation!D75,"") | D75: =IF(Calculation!E75=Calculation!$A$143,Calculation!$A$66,"") | E75: =IF(Calculation!E75=Calculation!$A$143,Calculation!C75,"") | F75: =IF(Calculation!E75=Calculation!$A$143,Calculation!F75,"") | G75: =IF(Calculation!E75=Calculation!$A$143,Calculation!G75,"") | H75: =IF(Calculation!E75=Calculation!$A$143,Calculation!H75,"")
A76: =IF(Calculation!E76=Calculation!$A$143,Calculation!B76,"") | B76: =IF(Calculation!E76=Calculation!$A$143,Calculation!I76,"") | C76: =IF(Calculation!E76=Calculation!$A$143,Calculation!D76,"") | D76: =IF(Calculation!E76=Calculation!$A$143,Calculation!$A$66,"") | E76: =IF(Calculation!E76=Calculation!$A$143,Calculation!C76,"") | F76: =IF(Calculation!E76=Calculation!$A$143,Calculation!F76,"") | G76: =IF(Calculation!E76=Calculation!$A$143,Calculation!G76,"") | H76: =IF(Calculation!E76=Calculation!$A$143,Calculation!H76,"")
A77: =IF(Calculation!E77=Calculation!$A$143,Calculation!B77,"") | B77: =IF(Calculation!E77=Calculation!$A$143,Calculation!I77,"") | C77: =IF(Calculation!E77=Calculation!$A$143,Calculation!D77,"") | D77: =IF(Calculation!E77=Calculation!$A$143,Calculation!$A$66,"") | E77: =IF(Calculation!E77=Calculation!$A$143,Calculation!C77,"") | F77: =IF(Calculation!E77=Calculation!$A$143,Calculation!F77,"") | G77: =IF(Calculation!E77=Calculation!$A$143,Calculation!G77,"") | H77: =IF(Calculation!E77=Calculation!$A$143,Calculation!H77,"")
A78: =IF(Calculation!E78=Calculation!$A$143,Calculation!B78,"") | B78: =IF(Calculation!E78=Calculation!$A$143,Calculation!I78,"") | C78: =IF(Calculation!E78=Calculation!$A$143,Calculation!D78,"") | D78: =IF(Calculation!E78=Calculation!$A$143,Calculation!$A$66,"") | E78: =IF(Calculation!E78=Calculation!$A$143,Calculation!C78,"") | F78: =IF(Calculation!E78=Calculation!$A$143,Calculation!F78,"") | G78: =IF(Calculation!E78=Calculation!$A$143,Calculation!G78,"") | H78: =IF(Calculation!E78=Calculation!$A$143,Calculation!H78,"")
A79: =IF(Calculation!E79=Calculation!$A$143,Calculation!B79,"") | B79: =IF(Calculation!E79=Calculation!$A$143,Calculation!I79,"") | C79: =IF(Calculation!E79=Calculation!$A$143,Calculation!D79,"") | D79: =IF(Calculation!E79=Calculation!$A$143,Calculation!$A$79,"") | E79: =IF(Calculation!E79=Calculation!$A$143,Calculation!C79,"") | F79: =IF(Calculation!E79=Calculation!$A$143,Calculation!F79,"") | G79: =IF(Calculation!E79=Calculation!$A$143,Calculation!G79,"") | H79: =IF(Calculation!E79=Calculation!$A$143,Calculation!H79,"")
A80: =IF(Calculation!E80=Calculation!$A$143,Calculation!B80,"") | B80: =IF(Calculation!E80=Calculation!$A$143,Calculation!I80,"") | C80: =IF(Calculation!E80=Calculation!$A$143,Calculation!D80,"") | D80: =IF(Calculation!E80=Calculation!$A$143,Calculation!$A$79,"") | E80: =IF(Calculation!E80=Calculation!$A$143,Calculation!C80,"") | F80: =IF(Calculation!E80=Calculation!$A$143,Calculation!F80,"") | G80: =IF(Calculation!E80=Calculation!$A$143,Calculation!G80,"") | H80: =IF(Calculation!E80=Calculation!$A$143,Calculation!H80,"")
A81: =IF(Calculation!E81=Calculation!$A$143,Calculation!B81,"") | B81: =IF(Calculation!E81=Calculation!$A$143,Calculation!I81,"") | C81: =IF(Calculation!E81=Calculation!$A$143,Calculation!D81,"") | D81: =IF(Calculation!E81=Calculation!$A$143,Calculation!$A$79,"") | E81: =IF(Calculation!E81=Calculation!$A$143,Calculation!C81,"") | F81: =IF(Calculation!E81=Calculation!$A$143,Calculation!F81,"") | G81: =IF(Calculation!E81=Calculation!$A$143,Calculation!G81,"") | H81: =IF(Calculation!E81=Calculation!$A$143,Calculation!H81,"")
A82: =IF(Calculation!E82=Calculation!$A$143,Calculation!B82,"") | B82: =IF(Calculation!E82=Calculation!$A$143,Calculation!I82,"") | C82: =IF(Calculation!E82=Calculation!$A$143,Calculation!D82,"") | D82: =IF(Calculation!E82=Calculation!$A$143,Calculation!$A$79,"") | E82: =IF(Calculation!E82=Calculation!$A$143,Calculation!C82,"") | F82: =IF(Calculation!E82=Calculation!$A$143,Calculation!F82,"") | G82: =IF(Calculation!E82=Calculation!$A$143,Calculation!G82,"") | H82: =IF(Calculation!E82=Calculation!$A$143,Calculation!H82,"")
